Workbook

Sheet Overview
A1: DRAFT - Marine Cloud Brightening: Cost, Benefit, and Planetary-Scale Assessment
A3: Intent
A4: The intent of this workbook is to do bottom up assessment of marine cloud brightening. The intent is to use the best available academic sources and connect those pieces together for this end to end assessment. Then we work through different delivery mechanisms, whether a dedicated vessel, piggybacking on a cargo ship, fixed platforms, or stationary vessels.
A5: Methodology
A6: Wherever possible, our intent is to use academic sources for inputs. On the last tab, references, you can find all the papers that we pulled data from. In this sense, we're pulling parts of a shelf and attempting to assemble them. As the foundation we take the exact numbers from Daniel Harrison's prototype in the Great Barrier Reef. However, these "parts" weren't built to be put together. This has two effects. One is that we may be connecting them together in the wrong order. The second is there are gaps, which means we make assumptions, which are not academically sourced.
A7: How the Workbook is Organized
A8: The workbook is broken roughly into two parts. The first section is modeling a machine/ship that spits out aerosol particles. The second section is then figuring out what the climate effect and outcome of those particles is.
A9: Particle cost model (tabs 1-4): what it costs to produce and spray particles
A10: 1. Technology Description: the spray machine. CCN product = 30-1000 nm particles (Harrison 2025 convention).
A11: 2. Cost Inputs: the blue input cells (capital, energy, crew, unit costs).
A12: 3a. Outputs - Dedicated Vessel: levelized cost per tonne of aerosol (the anchor number).
A13: 3b/3c/3d: cheaper siting and delivery vs a dedicated vessel (piggyback, fixed platform, stationary).
... A31: Tito Jankowski, tito.jankowski@renphil.org

Sheet 1. Technology Description
A1: DRAFT - Technology Description
A3: System Definition
A4: A single effervescent nozzle: seawater + compressed air + power in, CCN aerosol out. TEA stops at particle production; climatology on subsequent tabs
A6: Particle Production
A7: Quantity | B7: Value | C7: Unit | D7: Notes / Source | E7: Sources
A8: Particle output | B8: 1730000000000 | C8: particles/s | D8: Harrison et al. 2025, Environ. Sci.: Atmos. 5, 1071-1080 (doi:10.1039/d5ea00073d, OA; RSC blocks automated download, get PDF via DOI): ~1.73e12 droplets/s per nozzle. Cross-checks from files held: CS-06 Final Report 2025, p.24: the 2020 sea trial made "an estimated 2.7 x 10^14 droplets per second" from a "100 nozzle fan driven array [that] matched that of a single nozzle characterised under laboratory conditions" (about 2.7e12 per nozzle); CS-06 p.1: current prototype "~10^15 s-1 sea salt aerosols using 320 kilowatts (kW) of energy" (about 1.6e12 per nozzle over 640 nozzles). | E8: Harrison et al. 2025, Environ. Sci.: Atmos. 5, 1071-1080 (doi:10.1039/d5ea00073d).
A9: CCN-production window fraction (30-1000 nm) | B9: 0.71 | D9: Harrison 2025 (doi:10.1039/d5ea00073d): CCN production rate = counts in the 30-1000 nm window (~71%). No separate activation cut (would double-count). Field target window is tighter, CS-06 Final Report 2025, p.12, Fig. 5 caption: "Green shading indicates a MCB target range of 30-800 nm dry diameter." | E9: Harrison et al. 2025, Environ. Sci.: Atmos. 5, 1071-1080 (doi:10.1039/d5ea00073d).
A10: Dry particle diameter | B10: 150 | C10: nm | D10: One important note this model currently does not respond to changes in particle size. It calls all particles equivalent as long as they're within a certain range. Design value stays mass-weighted; mass sits in the large tail. Count mode is much smaller: CS-06 Final Report 2025, p.24: "mode dry aerosol diameter around 40 nm"; ERL 2025 (doi:10.1088/1748-9326/adccd7), p.6: sea-salt plume has "a notable peak at 47.03 nm average". Count-equivalent from the measured count + mass: ~143 nm. | E10: CS-06 Final Report 2025, p.24 + ERL 2025 p.6 (doi:10.1088/1748-9326/adccd7).
A11: Particles per tonne of salt | B11: =1000/B12 -> 2.6198345e+20 | C11: particles/tonne | D11: Field count runs ~15% higher than the lab math (2020 GBR trial; Hernandez-Jaramillo 2025), so cooling cost may come out slightly high. Tab 5a pulls this cell.
A12: Mass per dry particle | B12: =PI()/6*(B10*10^-9)^3*2160 -> 3.8170351e-18 | C12: kg | D12: Sphere volume x dry NaCl density 2160 kg/m3.
A13: CCN-production output (30-1000 nm window) | B13: =B8*B9*B12*86400*1000 -> 405.08331 | C13: g/day | D13: per nozzle particle rate x window fraction x dry mass x time. Window output is the product (Harrison 2025); plume survival charged per-scenario on 5a/6a.
A14: CCN-production output (30-1000 nm window) | B14: =B13/1000000 -> 0.00040508331 | C14: tonne/day
A16: Energy | G16: Nozzle power scenario (selector)
A17: Power | B17: =CHOOSE($H$17,$H$18,$H$19) -> 512 | C17: W | D17: Set by the scenario selector in H17 (1 = measured 512 W, 2 = CS-06 10x energy target 51.2 W). Harrison 2025 (doi:10.1039/d5ea00073d): nozzle power, ~98% air compression. Scale check from file held, CS-06 Final Report 2025, p.1: "The current prototype produces ~10^15 s-1 sea salt aerosols using 320 kilowatts (kW) of energy", about 0.32 W per 1e9 particles/s, i.e. ~550 W per nozzle at 1.73e12/s. Consistent with 512 W. | E17: Harrison et al. 2025, Environ. Sci.: Atmos. 5, 1071-1080 (doi:10.1039/d5ea00073d); scale check vs CS-06 Final Report 2025, p.1 | G17: Selected scenario | H17: 1 | I17: enter 1 or 2
A18: Energy per hour | B18: =B17/1000 -> 0.512 | C18: kWh | G18: 1: Harrison 2025 as measured | H18: 512 | I18: W
A19: Energy per day | B19: =B18*24 -> 12.288 | C19: kWh | G19: 2: CS-06 10x energy target | H19: 51.2 | I19: W
A20: Efficiency: energy per tonne of aerosol | B20: =B19/B14 -> 30334.501 | C20: kWh/tonne | D20: x power price = marginal $/tonne (~$9,100 at $0.30/kWh diesel). CS-06's ARIEL is roughly equal per-particle; CS-06 wants a further ~10x. | G20: B17 reads the selection; tab 2 and every output tab read B17.
A22: Water Handling
A23: Seawater flow rate | B23: 0.41 | C23: mL/s | D23: Harrison 2025 (doi:10.1039/d5ea00073d): ~1.73e12 droplets/s from 0.41 mL/s filtered seawater + 0.3 L/s air per nozzle. Field rigs run lower per nozzle: ERL 2025 (doi:10.1088/1748-9326/adccd7), p.2: "320 effervescent nozzles ... assembled into 5 manifold towers atomising a total of 68 ml s-1 of seawater" (about 0.21 mL/s each). Per-second value; next row converts to daily. | E23: Harrison et al. 2025, Environ. Sci.: Atmos. 5, 1071-1080 (doi:10.1039/d5ea00073d); field config: ERL 2025, p.2.
A24: Seawater sprayed | B24: =B23*86.4 -> 35.424 | C24: L/day | D24: 0.41 mL/s x 86,400 = per-day volume, converted once here so downstream stays in day-units. Only ~3.5% is salt.
A25: Seawater intensity | B25: =B24/(B13/1000000)/1000 -> 87.448679 | C25: m3/tonne | D25: Wet volume handled per dry tonne of CCN. Drives pumping/filtration/UV energy (x 0.6 kWh/m3 on Cost Inputs). Computed from the output of Harrison's 2025 nozzle.
A26: Pumping + filtration + UV energy | B26: 0.6 | C26: kWh per m3 seawater | D26: Electricity to lift, filter and UV-treat one cubic metre of seawater before atomizing. Assumption; until 10/07 this 0.6 was typed inside formulas on tab 2 (B28) and tab 3a (row 37, column AI).
A27: Process Flow
B29: Seawater intake
B30: ↓
B31: Filtration + UV
B32: ↓
B33: Pressurize seawater
B34: ↓
B35: Compress air
B36: ↓
B37: Effervescent nozzle
B38: ↓
B39: Evaporation
B40: ↓
... B52: Cooling Conversion

Sheet 2. Cost Inputs
A1: DRAFT - Cost Input Sheet
A2: General Parameters
B4: Value | C4: Unit | E4: Notes / Source | F4: Sources
A5: Equipment availability | B5: 0.9 | C5: fraction | E5: Mechanical uptime of the system, accounting for repairs and maintenance downtime | F5: Assumption (mechanical uptime target).
A6: Project lifetime | B6: 15 | C6: years | E6: Hardware life | F6: Assumption (hardware life).
A7: Discount rate | B7: 0.1 | E7: Cost of capital | F7: Assumption (cost of capital).
A8: Exchange rate, AUD to USD | B8: 0.7 | C8: USD per AUD | E8: Used by tab 5c to convert the A$ reef valuation. Until 10/07 typed inside 5c B27. | F8: Assumption (0.70 USD/AUD).
A9: Equipment Sizing
B10: Value | C10: Unit | E10: Notes / Source | F10: Sources
A11: Aerosol per nozzle per year | B11: ='1. Technology Description'!B13*365*$B$5/1000000 -> 0.13306987 | C11: tonnes/yr | E11: g/day x 365 x equipment availability, to tonnes
A12: Particle flux per vessel-unit | B12: =B13*'1. Technology Description'!B8*'1. Technology Description'!B9 -> 1e+16 | C12: particles/s | E12: Output now: nozzles x rate x window fraction. Shows 10^16/s at base (Latham et al. 2012, ~10^15-10^16/s per sprayer); it is no longer a requirement.
A13: Nozzle count (per vessel-unit) | B13: =B14*1000/'1. Technology Description'!B17 -> 8141.3336 | C13: nozzles | E13: Spray power (B14) / watts per nozzle (tab 1 B17). Until 10/07 this was 10^16/s / particles per nozzle, so a better nozzle meant the same count at lower power instead of more nozzles on the same plant.
A14: Spray power per vessel-unit | B14: 4168.3628 | C14: kW | E14: The sizing lever since 10/07: the vessel is built around this power plant and carries as many nozzles as it can run (B13). 4,168 kW = 8,142 nozzles at Harrison's 512 W, so the base case is unchanged. At 51 W the same plant runs 81,400 nozzles: no one has checked that many booms and manifolds (127 ARIEL rigs) fit the modelled vessel, and the seawater intake would be 33 L/s. Same approach as the piggyback's 4.5 MW on tab 3b. | F14: Model structure (power-sized vessel-unit, 10/07). Harrison 2025: 814 nozzles at 10^15/s need 417 kW; 10^16/s about 4.2 MW.
A15: Annual production per vessel-unit (equipment basis) | B15: =B13*B11 -> 1083.3662 | C15: tonnes/yr | E15: Nozzle count x aerosol per nozzle-year (equipment basis)
A17: Operating Expenditure (annual)
A18: 1. Raw Materials
B19: Amount | C19: Unit | D19: Cost/Unit | E19: Notes / Source | F19: Sources
A20: Seawater | B20: ='1. Technology Description'!B25*1000 -> 87448.679 | C20: L/tonne | D20: 0 | E20: Drawn from the sea | F20: Structural: seawater drawn at sea, no purchase cost.
A22: 2. Process Energy
B23: Amount | C23: Unit | D23: Cost/Unit
A24: Energy (compression, atomizes wet seawater) | B24: ='1. Technology Description'!B20 -> 30334.501 | C24: kWh/tonne | D24: 0.3 | E24: Power x 24h per nozzle / aerosol per nozzle. | F24: Derived: tab-1 nozzle power (Harrison 2025) x 24 h x energy price assumption.
A25: Vessel propulsion burn (underway) | B25: 16000 | C25: L/day | D25: 0.9 | E25: PSV cruise ~16.4 m3/day at 10 kn, 22.7 at 12 kn (UT 755L); Brazilian PSV fleet average ~9.3 t/day (Vianna et al. 2025). | F25: Vessel spec sheets: UT 755L PSV ~16.4 m3/day at 10 kn (Hornbeck HOS269). PSV fleet average ~9.3 t/day: Vianna, Ribas, Martins Ferreira Filho & Gribkovskaia (2025), J. Mar. Sci. Eng. 13(4):686 (was attributed to "Adland"). Links: https://horizonoffshoreservices.com/wp-content/uploads/2024/07/HOS269.pdf ; https://www.mdpi.com/2077-1312/13/4/686
A26: Vessel hotel burn (at rest / on station) | B26: 2700 | C26: L/day | D26: =D25 -> 0.9 | E26: Hotel plus light station-keeping.
A27: Fuel tank capacity | B27: 1000000 | C27: L
A28: Seawater pumping + filtration + UV | B28: ='1. Technology Description'!B25*'1. Technology Description'!B26 -> 52.469208 | C28: kWh/tonne | D28: 0.3 | E28: Lift, filter, UV-treat seawater before atomizing. Scales with wet volume (~87 m3 per dry tonne). | F28: Assumption: scales with wet volume (~87 m3 per dry tonne).
A29: 3. Labor
B30: Amount | C30: Unit | D30: Cost/Unit
A31: Crew | B31: 6 | C31: crew | D31: 150000 | E31: 6 crew per vessel x vessels (base scenario vessel count lives on tab 3a). | F31: Assumption: 6 crew per vessel.
A33: 4. Fixed Operating Expenditure
B34: Amount | C34: Unit
A35: Maintenance & insurance | B35: 0.07 | C35: of capex/yr | E35: 5% maintenance + 2% insurance | F35: Assumption: 5% maintenance + 2% insurance of capital.
A37: Capital Expenditure
A38: 5. Purchased Equipment
B39: Amount | C39: Unit | D39: Cost/Unit | E39: Notes / Source | F39: Sources | G39: Nozzle unit cost scenario (selector)
A40: Nozzles & manifolds | B40: =B13 -> 8141.3336 | C40: nozzles | D40: =CHOOSE($H$40,$H$41,$H$42,$H$43) -> 100 | E40: No published price for the SCU/ARIEL effervescent nozzle (searched Harrison 2025, CS-01/04/06/07, T14, ARIA proposal, Hernandez-Jaramillo thesis, 10/07). Bracket: CS-07 2025 p.31 'commercially proven nozzles ... ~$10 to ~$1000 each', marine 316 SS 'considerably more expensive'; CS-07 p.35 MeeFog manifolds 'about US$50 per nozzle, including nozzles, adapters, fittings, support frame'; CS-06 p.23 cartridge redesign 'significantly reducing costs'. Scenario 2 ($100) assumes the prototype nozzle unchanged, just made in volume. Compressors are priced separately (row 41). Installation (row 51) is 20% of equipment, so it scales with this price; a flat per-nozzle labour cost would be more honest at $10. | F40: RRAP CS-07 Fogging Development Final Report 2025, p.31 and p.35 (MeeFog manifold US$50/nozzle); RRAP CS-06 Final Report 2025, p.23 (cartridge nozzle). No price for the ARIEL nozzle in any Harrison-group publication. | G40: Selected scenario | H40: 2 | I40: enter 1, 2 or 3
A41: Compression + generation | B41: =B14 -> 4168.3628 | C41: kW | D41: 1500 | E41: Used Ariel 200 hp CNG compressor package listed $180k ≈ $1,200/kW (Bakersfield yard listing). Link: https://inventory.freeoilfieldquote.com/product/ariel-jgq-2-3-200-hp-vfd-electric-drive-3-stage-cng-com | F41: Market reference (website): used Ariel 200 hp CNG compressor package listed $180k, ~$1,200/kW (Bakersfield yard listing). Link: https://inventory.freeoilfieldquote.com/product/ariel-jgq-2-3-200-hp-vfd-electric-drive-3-stage-cng-com | G41: 1: $10, commodity nozzle at volume | H41: 10 | I41: $/nozzle
A42: Seawater intake/filtration/UV | B42: 1 | C42: per vessel | D42: 25000 | E42: $25k marinized: pump + strainer + polish + UV + spares. Ballast-water systems cost $640k+ but treat ~1,000x our throughput (Transport Canada, Transactions on BWTS 2015). | F42: Assumption ($25k marinized); ballast-water treatment systems ($640k+, Transport Canada 'Transactions on BWTS' 2015) as comparator at ~1,000x throughput. Link: https://www.tc.canada.ca/sites/default/files/migrated/transactions_for_bwts_on_the_great_lakes___transport_canada.pdf | G42: 2: $100, cartridge nozzle in a welded manifold, made in volume | H42: 100 | I42: $/nozzle
A43: Vessel structure & integration | B43: 1 | C43: per vessel | D43: =D44*0.25 -> 7500000 | E43: Assumption: nothing published exists for installing a ~1,000-nozzle spray array. Set at 25% of vessel cost. | G43: 3: $1,000, installed research-grade nozzle | H43: 1000 | I43: $/nozzle
A44: Vessel purchase | B44: 1 | C44: vessels | D44: 30000000 | E44: Newbuild 70-80 m PSV (Clarksons basis), sized for the ~3 MW spray plant. Platform = ~6-7 such vessels (sizing block below). | F44: Market reference (website): newbuild 70-80 m PSV, Clarksons basis; sized for the ~3 MW spray plant. Link: https://www.rivieramm.com/news-content-hub/sticker-shock-price-of-psv-newbuildings-up-68-since-2016-79964 | G44: D40 reads the selection; every capex line reads D40. The 3a tornado runs $10 to $1,000 regardless of the selection.
A45: Total purchased equipment | B45: =B40*D40+B41*D41+B42*D42+B43*D43+B44*D44 -> 44591678
A47: 6. Contingency & Indirect Capital | E47: Notes / Source | F47: Sources
B48: Fraction
A49: Engineering & supervision | B49: 0.2 | F49: Assumption (share of capital).
A50: Installation & commissioning | B50: 0.15 | F50: Assumption (share of capital).
A51: Marinization premium | B51: 0.2 | C51: =((D42*B42)+(D40*B40)+(D41*B41))*B51 -> 1418335.5 | E51: Corrosion, classification, maintenance access; applied to equipment, not the vessel. | F51: Assumption (marinization premium on equipment).
A52: Process contingency | B52: 0.25 | F52: Assumption (process contingency).
A53: Total capex | B53: =B45*(1+B49+B50+B52)+C51 -> 72765020
A55: 7. Charter Rate | E55: Notes / Source
A56: Bareboat charter rate, workboat class (hull + crew) | B56: 150000 | C56: $/vessel/week | D56: Assumption, no market quote (moved from tab 5d). Hull and crew only; the spray gear is charged separately in B58. Until 10/07 this cell was total capex / 2000 per day, a kitted-vessel rate. | E56: This is a rough estimate. Total capex divided by 2000. Wanted some way to be able to break the cost down for charter scenarios like the Reef scenario. Indendent to represent the hull, crew, and insurance.
A57: Spray-train capex per vessel-unit (mounted gear, excl. hull) | B57: =(B40*D40+B41*D41+B42*D42)*(1+B49+B50+B52)+C51 -> 12765020 | C57: $ | D57: Nozzles + compressors/gensets + seawater skid, with the contingency stack and installation. What gets mounted on a chartered hull (5c, 5c-alt, 5d).
A58: Spray-train capital charge per vessel-day | B58: =B57*((B7*(1+B7)^B6)/((1+B7)^B6-1))/365 -> 4597.9872 | C58: $/vessel/day | D58: B57 x capital recovery factor (B6, B7) / 365. Charged per vessel-day of a chartered campaign.
A60: 8. Diesel CO2 (added in review 2026-10)
A61: Diesel CO2 emission factor | B61: 3.206 | C61: t CO2 / t fuel | E61: Carbon factor for marine diesel / gas oil. | F61: IMO Fourth GHG Study 2020: Cf 3.206 t CO2/t fuel for MDO/MGO.
A62: Diesel density | B62: 0.845 | C62: kg/L | E62: Converts vessel fuel litres (tab 3a rows 24-25) to tonnes. | F62: Assumption: typical marine gas oil 0.83-0.89 kg/L (ISO 8217 DMA limit 0.890).
A63: Carbon price (social cost of CO2) | B63: 190 | C63: $/t CO2 | E63: Prices diesel CO2 in tabs 3a/3b (key metric) and in the 6b/6c benefit-cost ratios. EPA 2023 central ($190, 2% near-term rate). Alternative: $51 (IWG 2021 interim, 3%). Set 0 to exclude. | F63: US EPA (2023) Report on the Social Cost of Greenhouse Gases, Table ES.1; Interagency Working Group (2021) Technical Support Document, Table ES-1.
A64: Genset fuel rate | B64: ='6c. Benefit - Global Piggyback'!B50 -> 0.2 | C64: kg fuel / kWh | E64: Pulled from tab 6c B50. Fuel burned by the spray gensets per kWh. | F64: IMO Fourth GHG Study 2020, Table 19 (SFC).

Sheet 3a. Outputs - Dedicated Vessel
A1: Output Sheet
A3: Annualized Cost Build-up | F3: Key Metrics
A4: Component | B4: Annual cost | C4: $/tonne of aerosol | D4: % of total | F4: Metric | G4: Value | H4: Unit
A5: Capital recovery factor | B5: =('2. Cost Inputs'!B7*(1+'2. Cost Inputs'!B7)^'2. Cost Inputs'!B6)/((1+'2. Cost Inputs'!B7)^'2. Cost Inputs'!B6-1) -> 0.13147378 | F5: Levelized cost of aerosol | G5: =B13/$B$22 -> 54047.979 | H5: $/tonne of aerosol
A6: Annualized capital | B6: ='2. Cost Inputs'!B53*B5 -> 9566691.9 | C6: =B6/$B$22 -> 24173.562 | D6: =B6/$B$13 -> 0.44726117 | F6: Annual aerosol production | G6: =$B$22 -> 395.7502 | H6: tonnes/yr
A7: Energy | B7: ='2. Cost Inputs'!B24*'2. Cost Inputs'!D24*$B$22 -> 3601465.4 | C7: =B7/$B$22 -> 9100.3504 | D7: =B7/$B$13 -> 0.16837541 | F7: Total capex | G7: ='2. Cost Inputs'!B53 -> 72765020 | H7: $
A8: Seawater pumping + filtration | B8: ='2. Cost Inputs'!B28*'2. Cost Inputs'!D28*$B$22 -> 6229.4098 | C8: =B8/$B$22 -> 15.740762 | D8: =B8/$B$13 -> 0.00029123684 | F8: Total annual cost | G8: =B13 -> 21389498 | H8: $/yr
A9: Seawater feedstock | B9: ='2. Cost Inputs'!B20*'2. Cost Inputs'!D20*$B$22 -> 0 | C9: =B9/$B$22 -> 0 | D9: =B9/$B$13 -> 0 | F9: Nozzles per system | G9: ='2. Cost Inputs'!B13 -> 8141.3336 | H9: nozzles
A10: Crew | B10: ='2. Cost Inputs'!B31*'2. Cost Inputs'!D31 -> 900000 | C10: =B10/$B$22 -> 2274.1619 | D10: =B10/$B$13 -> 0.042076724 | F10: Operating days per year | G10: =B21 -> 132 | H10: days/yr
A11: Maintenance & insurance | B11: ='2. Cost Inputs'!B53*'2. Cost Inputs'!B35 -> 5093551.4 | C11: =B11/$B$22 -> 12870.622 | D11: =B11/$B$13 -> 0.23813328 | F11: Spray power | G11: ='2. Cost Inputs'!B14 -> 4168.3628 | H11: kW
A12: Vessel energy | B12: =(B24+B25)*'2. Cost Inputs'!D25 -> 2221560 | C12: =B12/$B$22 -> 5613.5411 | D12: =B12/$B$13 -> 0.10386218 | F12: Capex share of annual cost | G12: =B6/B13 -> 0.44726117 | H12: fraction
A13: Total Annual Cost | B13: =SUM(B6:B12) -> 21389498 | C13: =B13/$B$22 -> 54047.979 | D13: =1 -> 1 | F13: Variable cost share | G13: =(B7+B8)/B13 -> 0.16866664 | H13: fraction
A14: Total incl. diesel CO2 at tab 2 carbon price (added 2026-10) | B14: =B13+G15*'2. Cost Inputs'!$B$63*$B$22 -> 24122572 | C14: =B14/$B$22 -> 60954.037 | F14: Cost per delivered tonne | G14: =G5/'5a. Cooling Model - Local'!B5 -> 180159.93 | H14: $/tonne delivered at cloud base
F15: Diesel CO2 per tonne of aerosol (added 2026-10) | G15: =('2. Cost Inputs'!$B$24*'2. Cost Inputs'!$B$64+($B$24+$B$25)*'2. Cost Inputs'!$B$62/$B$22)/1000*'2. Cost Inputs'!$B$61 -> 36.347678 | H15: t CO2 / tonne of aerosol
A16: Mission & Endurance
A17: Component | E17: Notes | I17: Sources
A18: Spray time - moving (underway) | B18: 0.3652968 | C18: % of avail. time | E18: Spraying while the vessel is underway - the dedicated vessel sprays on the move | I18: Assumption: dedicated vessel sprays underway.
A19: Spray time - on station | B19: 0 | C19: % of avail. time | E19: Spraying while holding station; zero for the dedicated vessel | I19: Assumption: zero on-station for this scenario.
A20: Transit time (no spray) | B20: 0.03652968 | C20: % of avail. time | E20: Repositioning between spray areas plus refuel legs; only propulsion+hotel burn | I20: Assumption: repositioning + refuel legs.
A21: Operating days per year | B21: =(B18+B19+B20)*365*'2. Cost Inputs'!$B$5 -> 132 | C21: days | E21: = (spray + transit) % of available time x 365 x equipment availability
A22: Effective production | B22: =(B18+B19)*'2. Cost Inputs'!$B$15 -> 395.7502 | C22: tonnes/yr | E22: = spray % x equipment-basis annual production (availability already applied)
A23: Endurance per tank | B23: =$B$26*'2. Cost Inputs'!B27/('2. Cost Inputs'!B25+'2. Cost Inputs'!B26) -> 48.128342 | C23: days | E23: 90% of tank at combined underway burn (propulsion + hotel)
A24: Vessel fuel per year (propulsion) | B24: =(B18+B20)*365*'2. Cost Inputs'!$B$5*'2. Cost Inputs'!B25 -> 2112000 | C24: L/yr | E24: = (spray-moving + transit) % x 365 x availability x underway burn
A25: Hotel fuel per year | B25: =B21*'2. Cost Inputs'!B26 -> 356400 | C25: L/yr | E25: = operating days x hotel burn
A26: Usable fraction of fuel tank | B26: 0.9 | C26: fraction | E26: Tanks are not run dry; 90% usable. Read by B23 here and by tab 3d. Until 10/07 typed inside both formulas.
A27: Levelized cost per tonne of aerosol
A28: Cost build-up with every tornado input at worst / base / best. Particle size fixed; only power per unit varies for nozzle improvements.
A30: Component | B30: Pessimistic | C30: Base | D30: Optimistic
A31: Production (t/yr) | B31: =('2. Cost Inputs'!$B$14*1000/B49)*B50*'1. Technology Description'!$B$9*'1. Technology Description'!$B$12*86400*365*B53/1000 -> 134.55507 | C31: =('2. Cost Inputs'!$B$14*1000/C49)*C50*'1. Technology Description'!$B$9*'1. Technology Description'!$B$12*86400*365*C53/1000 -> 395.7502 | D31: =('2. Cost Inputs'!$B$14*1000/D49)*D50*'1. Technology Description'!$B$9*'1. Technology Description'!$B$12*86400*365*D53/1000 -> 5916.4654 | E31: Rebuilt 2026-10 on the power-sized vessel (tab 2 B14 fixed; nozzles = plant / W per nozzle), with hotel fuel and the tab 2 capex stack. The Base column now equals G5.
A32: Energy intensity (kWh/tonne) | B32: =B49*24/1000/(B50*'1. Technology Description'!$B$9*'1. Technology Description'!$B$12*86400/1000) -> 53531.473 | C32: =C49*24/1000/(C50*'1. Technology Description'!$B$9*'1. Technology Description'!$B$12*86400/1000) -> 30334.501 | D32: =D49*24/1000/(D50*'1. Technology Description'!$B$9*'1. Technology Description'!$B$12*86400/1000) -> 2637.7827
A33: Total capex ($) | B33: =(('2. Cost Inputs'!$B$14*1000/B49)*B54+'2. Cost Inputs'!$B$14*B59+'2. Cost Inputs'!$D$42+B55)*(1+'2. Cost Inputs'!$B$49+'2. Cost Inputs'!$B$50+'2. Cost Inputs'!$B$52)+(('2. Cost Inputs'!$B$14*1000/B49)*B54+'2. Cost Inputs'!$B$14*B59+'2. Cost Inputs'!$D$42)*'2. Cost Inputs'!$B$51 -> 1.1669647e+08 | C33: =(('2. Cost Inputs'!$B$14*1000/C49)*C54+'2. Cost Inputs'!$B$14*C59+'2. Cost Inputs'!$D$42+C55)*(1+'2. Cost Inputs'!$B$49+'2. Cost Inputs'!$B$50+'2. Cost Inputs'!$B$52)+(('2. Cost Inputs'!$B$14*1000/C49)*C54+'2. Cost Inputs'!$B$14*C59+'2. Cost Inputs'!$D$42)*'2. Cost Inputs'!$B$51 -> 72765020 | D33: =(('2. Cost Inputs'!$B$14*1000/D49)*D54+'2. Cost Inputs'!$B$14*D59+'2. Cost Inputs'!$D$42+D55)*(1+'2. Cost Inputs'!$B$49+'2. Cost Inputs'!$B$50+'2. Cost Inputs'!$B$52)+(('2. Cost Inputs'!$B$14*1000/D49)*D54+'2. Cost Inputs'!$B$14*D59+'2. Cost Inputs'!$D$42)*'2. Cost Inputs'!$B$51 -> 44263188
A34: Capital recovery factor | B34: =(B57*(1+B57)^'2. Cost Inputs'!B6)/((1+B57)^'2. Cost Inputs'!B6-1) -> 0.17101705 | C34: =(C57*(1+C57)^'2. Cost Inputs'!B6)/((1+C57)^'2. Cost Inputs'!B6-1) -> 0.13147378 | D34: =(D57*(1+D57)^'2. Cost Inputs'!B6)/((1+D57)^'2. Cost Inputs'!B6-1) -> 0.10296276
A35: Annualized capital ($/yr) | B35: =B33*B34 -> 19957086 | C35: =C33*C34 -> 9566691.9 | D35: =D33*D34 -> 4557460.2
A36: Spray energy ($/yr) | B36: =B32*B58*B31 -> 3241318.9 | C36: =C32*C58*C31 -> 3601465.4 | D36: =D32*D58*D31 -> 2809143
A37: Seawater pumping + UV ($/yr) | B37: ='2. Cost Inputs'!$B$28*'2. Cost Inputs'!$D$28*B31 -> 2117.9993 | C37: ='2. Cost Inputs'!$B$28*'2. Cost Inputs'!$D$28*C31 -> 6229.4098 | D37: ='2. Cost Inputs'!$B$28*'2. Cost Inputs'!$D$28*D31 -> 93129.676 | E37: kWh/tonne (tab 2 B28) x price x production for the case. Until 10/07 this row used litres where it needed cubic metres, 1,000x low on a ~$16/tonne line.
A38: Crew ($/yr) | B38: ='2. Cost Inputs'!$B$31*B52 -> 1260000 | C38: ='2. Cost Inputs'!$B$31*C52 -> 900000 | D38: ='2. Cost Inputs'!$B$31*D52 -> 630000
A39: Maintenance & insurance ($/yr) | B39: =B33*B56 -> 13070005 | C39: =C33*C56 -> 5093551.4 | D39: =D33*D56 -> 1549211.6
A40: Vessel energy ($/yr) | B40: =B51*'2. Cost Inputs'!$D$25 -> 3332340 | C40: =C51*'2. Cost Inputs'!$D$25 -> 2221560 | D40: =D51*'2. Cost Inputs'!$D$25 -> 1110780
A41: Levelized cost ($/tonne) | B41: =SUM(B35:B40)/B31 -> 303688.81 | C41: =SUM(C35:C40)/C31 -> 54047.979 | D41: =SUM(D35:D40)/D31 -> 1816.9166
A45: Sensitivity Analysis
A47: Tornado Diagram Inputs
A48: Variable | B48: Pessimistic | C48: Base Case | D48: Optimistic | E48: Units | F48: Description | I48: Live calc, drives the tornado (safe to hide columns R:AS)
A49: Power per unit | B49: =C49*1.5 -> 768 | C49: ='1. Technology Description'!B17 -> 512 | D49: =C49*0.1 -> 51.2 | E49: W | F49: Worst = 1.5x (degradation/losses). Best = 0.1x miracle machine (electrospray-class). Power-sized vessel: the plant (tab 2 B14) is fixed, so lower W per nozzle means more nozzles and more tonnes. | J49: d | K49: util | L49: disc | M49: nozcost | N49: compcost | O49: vescost | P49: maint | Q49: eprice | R49: vfuel | S49: crew | AJ49: $/tonne of aerosol | AK49: t/yr (power-sized)
A50: Particle output rate | B50: =C50*0.85 -> 1470500000000 | C50: ='1. Technology Description'!B8 -> 1730000000000 | D50: =C50*1.15 -> 1989500000000 | E50: particles/s | F50: Harrison et al. 2025: field count rate runs ~15% above the lab value (2020 GBR trial vs CS-06 bench); +/-15% band. | J50: ='1. Technology Description'!$B$10 -> 150 | K50: =($B$18+$B$19)*'2. Cost Inputs'!$B$5 -> 0.32876712 | L50: ='2. Cost Inputs'!$B$7 -> 0.1 | M50: ='2. Cost Inputs'!$D$40 -> 100 | N50: ='2. Cost Inputs'!$D$41 -> 1500 | O50: ='2. Cost Inputs'!$D$43 -> 7500000 | P50: ='2. Cost Inputs'!$B$35 -> 0.07 | Q50: ='2. Cost Inputs'!$D$24 -> 0.3 | R50: =((K50/'2. Cost Inputs'!$B$5-$B$19+$B$20)*'2. Cost Inputs'!$B$25+(K50/'2. Cost Inputs'!$B$5+$B$20)*'2. Cost Inputs'!$B$26)*365*'2. Cost Inputs'!$B$5 -> 2468400 | S50: ='2. Cost Inputs'!$D$31 -> 150000 | T50: =PI()/6*(J50*10^-9)^3*2160 -> 3.8170351e-18 | U50: ='1. Technology Description'!$B$8*'1. Technology Description'!$B$9*T50*86400*1000 -> 405.08331 | V50: =U50*365*K50/1000000 -> 0.048609997 | W50: ='2. Cost Inputs'!$B$14*1000/'1. Technology Description'!$B$17 -> 8141.3336 | X50: ='2. Cost Inputs'!$B$14 -> 4168.3628 | Y50: =1 -> 1 | Z50: =W50*M50+X50*N50+Y50*'2. Cost Inputs'!$D$42+Y50*O50+Y50*'2. Cost Inputs'!$D$44 -> 44591678 | AA50: =Z50*(1+'2. Cost Inputs'!$B$49+'2. Cost Inputs'!$B$50+'2. Cost Inputs'!$B$52)+(W50*M50+X50*N50+Y50*'2. Cost Inputs'!$D$42)*'2. Cost Inputs'!$B$51 -> 72765020 | AB50: =(L50*(1+L50)^'2. Cost Inputs'!$B$6)/((1+L50)^'2. Cost Inputs'!$B$6-1) -> 0.13147378 | AC50: =AA50*AB50 -> 9566691.9 | AD50: ='1. Technology Description'!$B$17*24/1000/(U50/1000000) -> 30334.501 | AE50: =AD50*Q50*AK50 -> 3601465.4 | AF50: =Y50*'2. Cost Inputs'!$B$31*S50 -> 900000 | AG50: =AA50*P50 -> 5093551.4 | AH50: =R50*'2. Cost Inputs'!$D$25*Y50 -> 2221560 | AI50: =AC50+AE50+AF50+AG50+AH50+(('1. Technology Description'!$B$24/(U50/1000000)/1000)*'1. Technology Description'!$B$26*'2. Cost Inputs'!$D$28*AK50) -> 21389498 | AJ50: =AI50/AK50 -> 54047.979 | AK50: =W50*V50 -> 395.7502
A51: Vessel fuel/yr | B51: =C51*1.5 -> 3702600 | C51: =$B$24+$B$25 -> 2468400 | D51: =C51*0.5 -> 1234200 | E51: L/vessel/yr | F51: Propulsion + hotel, dedicated vessel | J51: =$B$49 -> 768 | K51: =($B$18+$B$19)*'2. Cost Inputs'!$B$5 -> 0.32876712 | L51: ='2. Cost Inputs'!$B$7 -> 0.1 | M51: ='2. Cost Inputs'!$D$40 -> 100 | N51: ='2. Cost Inputs'!$D$41 -> 1500 | O51: ='2. Cost Inputs'!$D$43 -> 7500000 | P51: ='2. Cost Inputs'!$B$35 -> 0.07 | Q51: ='2. Cost Inputs'!$D$24 -> 0.3 | R51: =((K51/'2. Cost Inputs'!$B$5-$B$19+$B$20)*'2. Cost Inputs'!$B$25+(K51/'2. Cost Inputs'!$B$5+$B$20)*'2. Cost Inputs'!$B$26)*365*'2. Cost Inputs'!$B$5 -> 2468400 | S51: ='2. Cost Inputs'!$D$31 -> 150000 | T51: =$T$50 -> 3.8170351e-18 | U51: ='1. Technology Description'!$B$8*'1. Technology Description'!$B$9*T51*86400*1000 -> 405.08331 | V51: =U51*365*K51/1000000 -> 0.048609997 | W51: ='2. Cost Inputs'!$B$14*1000/J51 -> 5427.5557 | X51: ='2. Cost Inputs'!$B$14 -> 4168.3628 | Y51: =1 -> 1 | Z51: =W51*M51+X51*N51+Y51*'2. Cost Inputs'!$D$42+Y51*O51+Y51*'2. Cost Inputs'!$D$44 -> 44320300 | AA51: =Z51*(1+'2. Cost Inputs'!$B$49+'2. Cost Inputs'!$B$50+'2. Cost Inputs'!$B$52)+(W51*M51+X51*N51+Y51*'2. Cost Inputs'!$D$42)*'2. Cost Inputs'!$B$51 -> 72276540 | AB51: =(L51*(1+L51)^'2. Cost Inputs'!$B$6)/((1+L51)^'2. Cost Inputs'!$B$6-1) -> 0.13147378 | AC51: =AA51*AB51 -> 9502469.6 | AD51: =J51*24/1000/(U51/1000000) -> 45501.752 | AE51: =AD51*Q51*AK51 -> 3601465.4 | AF51: =Y51*'2. Cost Inputs'!$B$31*S51 -> 900000 | AG51: =AA51*P51 -> 5059357.8 | AH51: =R51*'2. Cost Inputs'!$D$25*Y51 -> 2221560 | AI51: =AC51+AE51+AF51+AG51+AH51+(('1. Technology Description'!$B$24/(U51/1000000)/1000)*'1. Technology Description'!$B$26*'2. Cost Inputs'!$D$28*AK51) -> 21289006 | AJ51: =AI51/AK51 -> 80691.075 | AK51: =W51*V51 -> 263.83346
A52: Crew cost | B52: =C52*1.4 -> 210000 | C52: ='2. Cost Inputs'!D31 -> 150000 | D52: =C52*0.7 -> 105000 | E52: $/person | F52: Annual loaded cost per crew | J52: =$D$49 -> 51.2 | K52: =($B$18+$B$19)*'2. Cost Inputs'!$B$5 -> 0.32876712 | L52: ='2. Cost Inputs'!$B$7 -> 0.1 | M52: ='2. Cost Inputs'!$D$40 -> 100 | N52: ='2. Cost Inputs'!$D$41 -> 1500 | O52: ='2. Cost Inputs'!$D$43 -> 7500000 | P52: ='2. Cost Inputs'!$B$35 -> 0.07 | Q52: ='2. Cost Inputs'!$D$24 -> 0.3 | R52: =((K52/'2. Cost Inputs'!$B$5-$B$19+$B$20)*'2. Cost Inputs'!$B$25+(K52/'2. Cost Inputs'!$B$5+$B$20)*'2. Cost Inputs'!$B$26)*365*'2. Cost Inputs'!$B$5 -> 2468400 | S52: ='2. Cost Inputs'!$D$31 -> 150000 | T52: =$T$50 -> 3.8170351e-18 | U52: ='1. Technology Description'!$B$8*'1. Technology Description'!$B$9*T52*86400*1000 -> 405.08331 | V52: =U52*365*K52/1000000 -> 0.048609997 | W52: ='2. Cost Inputs'!$B$14*1000/J52 -> 81413.336 | X52: ='2. Cost Inputs'!$B$14 -> 4168.3628 | Y52: =1 -> 1 | Z52: =W52*M52+X52*N52+Y52*'2. Cost Inputs'!$D$42+Y52*O52+Y52*'2. Cost Inputs'!$D$44 -> 51918878 | AA52: =Z52*(1+'2. Cost Inputs'!$B$49+'2. Cost Inputs'!$B$50+'2. Cost Inputs'!$B$52)+(W52*M52+X52*N52+Y52*'2. Cost Inputs'!$D$42)*'2. Cost Inputs'!$B$51 -> 85953980 | AB52: =(L52*(1+L52)^'2. Cost Inputs'!$B$6)/((1+L52)^'2. Cost Inputs'!$B$6-1) -> 0.13147378 | AC52: =AA52*AB52 -> 11300694 | AD52: =J52*24/1000/(U52/1000000) -> 3033.4501 | AE52: =AD52*Q52*AK52 -> 3601465.4 | AF52: =Y52*'2. Cost Inputs'!$B$31*S52 -> 900000 | AG52: =AA52*P52 -> 6016778.6 | AH52: =R52*'2. Cost Inputs'!$D$25*Y52 -> 2221560 | AI52: =AC52+AE52+AF52+AG52+AH52+(('1. Technology Description'!$B$24/(U52/1000000)/1000)*'1. Technology Description'!$B$26*'2. Cost Inputs'!$D$28*AK52) -> 24102793 | AJ52: =AI52/AK52 -> 6090.4057 | AK52: =W52*V52 -> 3957.502
A53: Annual utilization | B53: =C53*0.6 -> 0.19726027 | C53: =($B$18+$B$19)*'2. Cost Inputs'!$B$5 -> 0.32876712 | D53: =C53*1.3 -> 0.42739726 | E53: fraction | F53: Spray-time fraction of year | J53: ='1. Technology Description'!$B$10 -> 150 | K53: =($B$18+$B$19)*'2. Cost Inputs'!$B$5 -> 0.32876712 | L53: ='2. Cost Inputs'!$B$7 -> 0.1 | M53: ='2. Cost Inputs'!$D$40 -> 100 | N53: ='2. Cost Inputs'!$D$41 -> 1500 | O53: ='2. Cost Inputs'!$D$43 -> 7500000 | P53: ='2. Cost Inputs'!$B$35 -> 0.07 | Q53: ='2. Cost Inputs'!$D$24 -> 0.3 | R53: =$B$51 -> 3702600 | S53: ='2. Cost Inputs'!$D$31 -> 150000 | T53: =PI()/6*(J53*10^-9)^3*2160 -> 3.8170351e-18 | U53: ='1. Technology Description'!$B$8*'1. Technology Description'!$B$9*T53*86400*1000 -> 405.08331 | V53: =U53*365*K53/1000000 -> 0.048609997 | W53: ='2. Cost Inputs'!$B$14*1000/'1. Technology Description'!$B$17 -> 8141.3336 | X53: ='2. Cost Inputs'!$B$14 -> 4168.3628 | Y53: =1 -> 1 | Z53: =W53*M53+X53*N53+Y53*'2. Cost Inputs'!$D$42+Y53*O53+Y53*'2. Cost Inputs'!$D$44 -> 44591678 | AA53: =Z53*(1+'2. Cost Inputs'!$B$49+'2. Cost Inputs'!$B$50+'2. Cost Inputs'!$B$52)+(W53*M53+X53*N53+Y53*'2. Cost Inputs'!$D$42)*'2. Cost Inputs'!$B$51 -> 72765020 | AB53: =(L53*(1+L53)^'2. Cost Inputs'!$B$6)/((1+L53)^'2. Cost Inputs'!$B$6-1) -> 0.13147378 | AC53: =AA53*AB53 -> 9566691.9 | AD53: ='1. Technology Description'!$B$17*24/1000/(U53/1000000) -> 30334.501 | AE53: =AD53*Q53*AK53 -> 3601465.4 | AF53: =Y53*'2. Cost Inputs'!$B$31*S53 -> 900000 | AG53: =AA53*P53 -> 5093551.4 | AH53: =R53*'2. Cost Inputs'!$D$25*Y53 -> 3332340 | AI53: =AC53+AE53+AF53+AG53+AH53+(('1. Technology Description'!$B$24/(U53/1000000)/1000)*'1. Technology Description'!$B$26*'2. Cost Inputs'!$D$28*AK53) -> 22500278 | AJ53: =AI53/AK53 -> 56854.749 | AK53: =W53*V53 -> 395.7502
A54: Nozzle unit cost | B54: ='2. Cost Inputs'!$H$43 -> 1000 | C54: ='2. Cost Inputs'!D40 -> 100 | D54: ='2. Cost Inputs'!$H$41 -> 10 | E54: $/nozzle | F54: Installed cost per nozzle. Worst = $1,000 scenario (tab 2 H43), base = selected scenario (D40), best = $10 scenario (H41): the full published bracket (CS-07 p.31), not a multiple of the selection. | I54: vessel fuel best | J54: ='1. Technology Description'!$B$10 -> 150 | K54: =($B$18+$B$19)*'2. Cost Inputs'!$B$5 -> 0.32876712 | L54: ='2. Cost Inputs'!$B$7 -> 0.1 | M54: ='2. Cost Inputs'!$D$40 -> 100 | N54: ='2. Cost Inputs'!$D$41 -> 1500 | O54: ='2. Cost Inputs'!$D$43 -> 7500000 | P54: ='2. Cost Inputs'!$B$35 -> 0.07 | Q54: ='2. Cost Inputs'!$D$24 -> 0.3 | R54: =$D$51 -> 1234200 | S54: ='2. Cost Inputs'!$D$31 -> 150000 | T54: =PI()/6*(J54*10^-9)^3*2160 -> 3.8170351e-18 | U54: ='1. Technology Description'!$B$8*'1. Technology Description'!$B$9*T54*86400*1000 -> 405.08331 | V54: =U54*365*K54/1000000 -> 0.048609997 | W54: ='2. Cost Inputs'!$B$14*1000/'1. Technology Description'!$B$17 -> 8141.3336 | X54: ='2. Cost Inputs'!$B$14 -> 4168.3628 | Y54: =1 -> 1 | Z54: =W54*M54+X54*N54+Y54*'2. Cost Inputs'!$D$42+Y54*O54+Y54*'2. Cost Inputs'!$D$44 -> 44591678 | AA54: =Z54*(1+'2. Cost Inputs'!$B$49+'2. Cost Inputs'!$B$50+'2. Cost Inputs'!$B$52)+(W54*M54+X54*N54+Y54*'2. Cost Inputs'!$D$42)*'2. Cost Inputs'!$B$51 -> 72765020 | AB54: =(L54*(1+L54)^'2. Cost Inputs'!$B$6)/((1+L54)^'2. Cost Inputs'!$B$6-1) -> 0.13147378 | AC54: =AA54*AB54 -> 9566691.9 | AD54: ='1. Technology Description'!$B$17*24/1000/(U54/1000000) -> 30334.501 | AE54: =AD54*Q54*AK54 -> 3601465.4 | AF54: =Y54*'2. Cost Inputs'!$B$31*S54 -> 900000 | AG54: =AA54*P54 -> 5093551.4 | AH54: =R54*'2. Cost Inputs'!$D$25*Y54 -> 1110780 | AI54: =AC54+AE54+AF54+AG54+AH54+(('1. Technology Description'!$B$24/(U54/1000000)/1000)*'1. Technology Description'!$B$26*'2. Cost Inputs'!$D$28*AK54) -> 20278718 | AJ54: =AI54/AK54 -> 51241.208 | AK54: =W54*V54 -> 395.7502
A55: Vessel cost | B55: =C55*1.5 -> 56250000 | C55: ='2. Cost Inputs'!D43+'2. Cost Inputs'!D44 -> 37500000 | D55: =C55*0.6 -> 22500000 | E55: $/vessel | F55: Spray vessel purchase + integration, per vessel | I55: crew worst | J55: ='1. Technology Description'!$B$10 -> 150 | K55: =($B$18+$B$19)*'2. Cost Inputs'!$B$5 -> 0.32876712 | L55: ='2. Cost Inputs'!$B$7 -> 0.1 | M55: ='2. Cost Inputs'!$D$40 -> 100 | N55: ='2. Cost Inputs'!$D$41 -> 1500 | O55: ='2. Cost Inputs'!$D$43 -> 7500000 | P55: ='2. Cost Inputs'!$B$35 -> 0.07 | Q55: ='2. Cost Inputs'!$D$24 -> 0.3 | R55: =((K55/'2. Cost Inputs'!$B$5-$B$19+$B$20)*'2. Cost Inputs'!$B$25+(K55/'2. Cost Inputs'!$B$5+$B$20)*'2. Cost Inputs'!$B$26)*365*'2. Cost Inputs'!$B$5 -> 2468400 | S55: =$B$52 -> 210000 | T55: =PI()/6*(J55*10^-9)^3*2160 -> 3.8170351e-18 | U55: ='1. Technology Description'!$B$8*'1. Technology Description'!$B$9*T55*86400*1000 -> 405.08331 | V55: =U55*365*K55/1000000 -> 0.048609997 | W55: ='2. Cost Inputs'!$B$14*1000/'1. Technology Description'!$B$17 -> 8141.3336 | X55: ='2. Cost Inputs'!$B$14 -> 4168.3628 | Y55: =1 -> 1 | Z55: =W55*M55+X55*N55+Y55*'2. Cost Inputs'!$D$42+Y55*O55+Y55*'2. Cost Inputs'!$D$44 -> 44591678 | AA55: =Z55*(1+'2. Cost Inputs'!$B$49+'2. Cost Inputs'!$B$50+'2. Cost Inputs'!$B$52)+(W55*M55+X55*N55+Y55*'2. Cost Inputs'!$D$42)*'2. Cost Inputs'!$B$51 -> 72765020 | AB55: =(L55*(1+L55)^'2. Cost Inputs'!$B$6)/((1+L55)^'2. Cost Inputs'!$B$6-1) -> 0.13147378 | AC55: =AA55*AB55 -> 9566691.9 | AD55: ='1. Technology Description'!$B$17*24/1000/(U55/1000000) -> 30334.501 | AE55: =AD55*Q55*AK55 -> 3601465.4 | AF55: =Y55*'2. Cost Inputs'!$B$31*S55 -> 1260000 | AG55: =AA55*P55 -> 5093551.4 | AH55: =R55*'2. Cost Inputs'!$D$25*Y55 -> 2221560 | AI55: =AC55+AE55+AF55+AG55+AH55+(('1. Technology Description'!$B$24/(U55/1000000)/1000)*'1. Technology Description'!$B$26*'2. Cost Inputs'!$D$28*AK55) -> 21749498 | AJ55: =AI55/AK55 -> 54957.643 | AK55: =W55*V55 -> 395.7502
A56: Maintenance % | B56: =C56*1.6 -> 0.112 | C56: ='2. Cost Inputs'!B35 -> 0.07 | D56: =C56*0.5 -> 0.035 | E56: of capex/yr | F56: Maintenance + insurance rate | J56: ='1. Technology Description'!$B$10 -> 150 | K56: =($B$18+$B$19)*'2. Cost Inputs'!$B$5 -> 0.32876712 | L56: ='2. Cost Inputs'!$B$7 -> 0.1 | M56: ='2. Cost Inputs'!$D$40 -> 100 | N56: ='2. Cost Inputs'!$D$41 -> 1500 | O56: ='2. Cost Inputs'!$D$43 -> 7500000 | P56: ='2. Cost Inputs'!$B$35 -> 0.07 | Q56: ='2. Cost Inputs'!$D$24 -> 0.3 | R56: =((K56/'2. Cost Inputs'!$B$5-$B$19+$B$20)*'2. Cost Inputs'!$B$25+(K56/'2. Cost Inputs'!$B$5+$B$20)*'2. Cost Inputs'!$B$26)*365*'2. Cost Inputs'!$B$5 -> 2468400 | S56: =$D$52 -> 105000 | T56: =PI()/6*(J56*10^-9)^3*2160 -> 3.8170351e-18 | U56: ='1. Technology Description'!$B$8*'1. Technology Description'!$B$9*T56*86400*1000 -> 405.08331 | V56: =U56*365*K56/1000000 -> 0.048609997 | W56: ='2. Cost Inputs'!$B$14*1000/'1. Technology Description'!$B$17 -> 8141.3336 | X56: ='2. Cost Inputs'!$B$14 -> 4168.3628 | Y56: =1 -> 1 | Z56: =W56*M56+X56*N56+Y56*'2. Cost Inputs'!$D$42+Y56*O56+Y56*'2. Cost Inputs'!$D$44 -> 44591678 | AA56: =Z56*(1+'2. Cost Inputs'!$B$49+'2. Cost Inputs'!$B$50+'2. Cost Inputs'!$B$52)+(W56*M56+X56*N56+Y56*'2. Cost Inputs'!$D$42)*'2. Cost Inputs'!$B$51 -> 72765020 | AB56: =(L56*(1+L56)^'2. Cost Inputs'!$B$6)/((1+L56)^'2. Cost Inputs'!$B$6-1) -> 0.13147378 | AC56: =AA56*AB56 -> 9566691.9 | AD56: ='1. Technology Description'!$B$17*24/1000/(U56/1000000) -> 30334.501 | AE56: =AD56*Q56*AK56 -> 3601465.4 | AF56: =Y56*'2. Cost Inputs'!$B$31*S56 -> 630000 | AG56: =AA56*P56 -> 5093551.4 | AH56: =R56*'2. Cost Inputs'!$D$25*Y56 -> 2221560 | AI56: =AC56+AE56+AF56+AG56+AH56+(('1. Technology Description'!$B$24/(U56/1000000)/1000)*'1. Technology Description'!$B$26*'2. Cost Inputs'!$D$28*AK56) -> 21119498 | AJ56: =AI56/AK56 -> 53365.73 | AK56: =W56*V56 -> 395.7502
A57: Discount rate | B57: =C57*1.5 -> 0.15 | C57: ='2. Cost Inputs'!B7 -> 0.1 | D57: =C57*0.6 -> 0.06 | E57: fraction | F57: Cost of capital | I57: util worst | J57: ='1. Technology Description'!$B$10 -> 150 | K57: =$B$53 -> 0.19726027 | L57: ='2. Cost Inputs'!$B$7 -> 0.1 | M57: ='2. Cost Inputs'!$D$40 -> 100 | N57: ='2. Cost Inputs'!$D$41 -> 1500 | O57: ='2. Cost Inputs'!$D$43 -> 7500000 | P57: ='2. Cost Inputs'!$B$35 -> 0.07 | Q57: ='2. Cost Inputs'!$D$24 -> 0.3 | R57: =((K57/'2. Cost Inputs'!$B$5-$B$19+$B$20)*'2. Cost Inputs'!$B$25+(K57/'2. Cost Inputs'!$B$5+$B$20)*'2. Cost Inputs'!$B$26)*365*'2. Cost Inputs'!$B$5 -> 1570800 | S57: ='2. Cost Inputs'!$D$31 -> 150000 | T57: =PI()/6*(J57*10^-9)^3*2160 -> 3.8170351e-18 | U57: ='1. Technology Description'!$B$8*'1. Technology Description'!$B$9*T57*86400*1000 -> 405.08331 | V57: =U57*365*K57/1000000 -> 0.029165998 | W57: ='2. Cost Inputs'!$B$14*1000/'1. Technology Description'!$B$17 -> 8141.3336 | X57: ='2. Cost Inputs'!$B$14 -> 4168.3628 | Y57: =1 -> 1 | Z57: =W57*M57+X57*N57+Y57*'2. Cost Inputs'!$D$42+Y57*O57+Y57*'2. Cost Inputs'!$D$44 -> 44591678 | AA57: =Z57*(1+'2. Cost Inputs'!$B$49+'2. Cost Inputs'!$B$50+'2. Cost Inputs'!$B$52)+(W57*M57+X57*N57+Y57*'2. Cost Inputs'!$D$42)*'2. Cost Inputs'!$B$51 -> 72765020 | AB57: =(L57*(1+L57)^'2. Cost Inputs'!$B$6)/((1+L57)^'2. Cost Inputs'!$B$6-1) -> 0.13147378 | AC57: =AA57*AB57 -> 9566691.9 | AD57: ='1. Technology Description'!$B$17*24/1000/(U57/1000000) -> 30334.501 | AE57: =AD57*Q57*AK57 -> 2160879.3 | AF57: =Y57*'2. Cost Inputs'!$B$31*S57 -> 900000 | AG57: =AA57*P57 -> 5093551.4 | AH57: =R57*'2. Cost Inputs'!$D$25*Y57 -> 1413720 | AI57: =AC57+AE57+AF57+AG57+AH57+(('1. Technology Description'!$B$24/(U57/1000000)/1000)*'1. Technology Description'!$B$26*'2. Cost Inputs'!$D$28*AK57) -> 19138580 | AJ57: =AI57/AK57 -> 80600.424 | AK57: =W57*V57 -> 237.45012
A58: Energy price | B58: =C58*1.5 -> 0.45 | C58: ='2. Cost Inputs'!D24 -> 0.3 | D58: =C58*0.6 -> 0.18 | E58: $/kWh | F58: Marine diesel price | I58: util best | J58: ='1. Technology Description'!$B$10 -> 150 | K58: =$D$53 -> 0.42739726 | L58: ='2. Cost Inputs'!$B$7 -> 0.1 | M58: ='2. Cost Inputs'!$D$40 -> 100 | N58: ='2. Cost Inputs'!$D$41 -> 1500 | O58: ='2. Cost Inputs'!$D$43 -> 7500000 | P58: ='2. Cost Inputs'!$B$35 -> 0.07 | Q58: ='2. Cost Inputs'!$D$24 -> 0.3 | R58: =((K58/'2. Cost Inputs'!$B$5-$B$19+$B$20)*'2. Cost Inputs'!$B$25+(K58/'2. Cost Inputs'!$B$5+$B$20)*'2. Cost Inputs'!$B$26)*365*'2. Cost Inputs'!$B$5 -> 3141600 | S58: ='2. Cost Inputs'!$D$31 -> 150000 | T58: =PI()/6*(J58*10^-9)^3*2160 -> 3.8170351e-18 | U58: ='1. Technology Description'!$B$8*'1. Technology Description'!$B$9*T58*86400*1000 -> 405.08331 | V58: =U58*365*K58/1000000 -> 0.063192996 | W58: ='2. Cost Inputs'!$B$14*1000/'1. Technology Description'!$B$17 -> 8141.3336 | X58: ='2. Cost Inputs'!$B$14 -> 4168.3628 | Y58: =1 -> 1 | Z58: =W58*M58+X58*N58+Y58*'2. Cost Inputs'!$D$42+Y58*O58+Y58*'2. Cost Inputs'!$D$44 -> 44591678 | AA58: =Z58*(1+'2. Cost Inputs'!$B$49+'2. Cost Inputs'!$B$50+'2. Cost Inputs'!$B$52)+(W58*M58+X58*N58+Y58*'2. Cost Inputs'!$D$42)*'2. Cost Inputs'!$B$51 -> 72765020 | AB58: =(L58*(1+L58)^'2. Cost Inputs'!$B$6)/((1+L58)^'2. Cost Inputs'!$B$6-1) -> 0.13147378 | AC58: =AA58*AB58 -> 9566691.9 | AD58: ='1. Technology Description'!$B$17*24/1000/(U58/1000000) -> 30334.501 | AE58: =AD58*Q58*AK58 -> 4681905.1 | AF58: =Y58*'2. Cost Inputs'!$B$31*S58 -> 900000 | AG58: =AA58*P58 -> 5093551.4 | AH58: =R58*'2. Cost Inputs'!$D$25*Y58 -> 2827440 | AI58: =AC58+AE58+AF58+AG58+AH58+(('1. Technology Description'!$B$24/(U58/1000000)/1000)*'1. Technology Description'!$B$26*'2. Cost Inputs'!$D$28*AK58) -> 23077687 | AJ58: =AI58/AK58 -> 44856.747 | AK58: =W58*V58 -> 514.47526
A59: Compressor $/kW | B59: =C59*1.5 -> 2250 | C59: ='2. Cost Inputs'!D41 -> 1500 | D59: =C59*0.6 -> 900 | E59: $/kW | F59: HP compressor + genset | I59: nozzle cost worst | J59: ='1. Technology Description'!$B$10 -> 150 | K59: =($B$18+$B$19)*'2. Cost Inputs'!$B$5 -> 0.32876712 | L59: ='2. Cost Inputs'!$B$7 -> 0.1 | M59: =$B$54 -> 1000 | N59: ='2. Cost Inputs'!$D$41 -> 1500 | O59: ='2. Cost Inputs'!$D$43 -> 7500000 | P59: ='2. Cost Inputs'!$B$35 -> 0.07 | Q59: ='2. Cost Inputs'!$D$24 -> 0.3 | R59: =((K59/'2. Cost Inputs'!$B$5-$B$19+$B$20)*'2. Cost Inputs'!$B$25+(K59/'2. Cost Inputs'!$B$5+$B$20)*'2. Cost Inputs'!$B$26)*365*'2. Cost Inputs'!$B$5 -> 2468400 | S59: ='2. Cost Inputs'!$D$31 -> 150000 | T59: =PI()/6*(J59*10^-9)^3*2160 -> 3.8170351e-18 | U59: ='1. Technology Description'!$B$8*'1. Technology Description'!$B$9*T59*86400*1000 -> 405.08331 | V59: =U59*365*K59/1000000 -> 0.048609997 | W59: ='2. Cost Inputs'!$B$14*1000/'1. Technology Description'!$B$17 -> 8141.3336 | X59: ='2. Cost Inputs'!$B$14 -> 4168.3628 | Y59: =1 -> 1 | Z59: =W59*M59+X59*N59+Y59*'2. Cost Inputs'!$D$42+Y59*O59+Y59*'2. Cost Inputs'!$D$44 -> 51918878 | AA59: =Z59*(1+'2. Cost Inputs'!$B$49+'2. Cost Inputs'!$B$50+'2. Cost Inputs'!$B$52)+(W59*M59+X59*N59+Y59*'2. Cost Inputs'!$D$42)*'2. Cost Inputs'!$B$51 -> 85953980 | AB59: =(L59*(1+L59)^'2. Cost Inputs'!$B$6)/((1+L59)^'2. Cost Inputs'!$B$6-1) -> 0.13147378 | AC59: =AA59*AB59 -> 11300694 | AD59: ='1. Technology Description'!$B$17*24/1000/(U59/1000000) -> 30334.501 | AE59: =AD59*Q59*AK59 -> 3601465.4 | AF59: =Y59*'2. Cost Inputs'!$B$31*S59 -> 900000 | AG59: =AA59*P59 -> 6016778.6 | AH59: =R59*'2. Cost Inputs'!$D$25*Y59 -> 2221560 | AI59: =AC59+AE59+AF59+AG59+AH59+(('1. Technology Description'!$B$24/(U59/1000000)/1000)*'1. Technology Description'!$B$26*'2. Cost Inputs'!$D$28*AK59) -> 24046728 | AJ59: =AI59/AK59 -> 60762.39 | AK59: =W59*V59 -> 395.7502
J60: ='1. Technology Description'!$B$10 -> 150 | K60: =($B$18+$B$19)*'2. Cost Inputs'!$B$5 -> 0.32876712 | L60: ='2. Cost Inputs'!$B$7 -> 0.1 | M60: =$D$54 -> 10 | N60: ='2. Cost Inputs'!$D$41 -> 1500 | O60: ='2. Cost Inputs'!$D$43 -> 7500000 | P60: ='2. Cost Inputs'!$B$35 -> 0.07 | Q60: ='2. Cost Inputs'!$D$24 -> 0.3 | R60: =((K60/'2. Cost Inputs'!$B$5-$B$19+$B$20)*'2. Cost Inputs'!$B$25+(K60/'2. Cost Inputs'!$B$5+$B$20)*'2. Cost Inputs'!$B$26)*365*'2. Cost Inputs'!$B$5 -> 2468400 | S60: ='2. Cost Inputs'!$D$31 -> 150000 | T60: =PI()/6*(J60*10^-9)^3*2160 -> 3.8170351e-18 | U60: ='1. Technology Description'!$B$8*'1. Technology Description'!$B$9*T60*86400*1000 -> 405.08331 | V60: =U60*365*K60/1000000 -> 0.048609997 | W60: ='2. Cost Inputs'!$B$14*1000/'1. Technology Description'!$B$17 -> 8141.3336 | X60: ='2. Cost Inputs'!$B$14 -> 4168.3628 | Y60: =1 -> 1 | Z60: =W60*M60+X60*N60+Y60*'2. Cost Inputs'!$D$42+Y60*O60+Y60*'2. Cost Inputs'!$D$44 -> 43858958 | AA60: =Z60*(1+'2. Cost Inputs'!$B$49+'2. Cost Inputs'!$B$50+'2. Cost Inputs'!$B$52)+(W60*M60+X60*N60+Y60*'2. Cost Inputs'!$D$42)*'2. Cost Inputs'!$B$51 -> 71446124 | AB60: =(L60*(1+L60)^'2. Cost Inputs'!$B$6)/((1+L60)^'2. Cost Inputs'!$B$6-1) -> 0.13147378 | AC60: =AA60*AB60 -> 9393291.7 | AD60: ='1. Technology Description'!$B$17*24/1000/(U60/1000000) -> 30334.501 | AE60: =AD60*Q60*AK60 -> 3601465.4 | AF60: =Y60*'2. Cost Inputs'!$B$31*S60 -> 900000 | AG60: =AA60*P60 -> 5001228.6 | AH60: =R60*'2. Cost Inputs'!$D$25*Y60 -> 2221560 | AI60: =AC60+AE60+AF60+AG60+AH60+(('1. Technology Description'!$B$24/(U60/1000000)/1000)*'1. Technology Description'!$B$26*'2. Cost Inputs'!$D$28*AK60) -> 21123775 | AJ60: =AI60/AK60 -> 53376.537 | AK60: =W60*V60 -> 395.7502
I61: vessel cost worst | J61: ='1. Technology Description'!$B$10 -> 150 | K61: =($B$18+$B$19)*'2. Cost Inputs'!$B$5 -> 0.32876712 | L61: ='2. Cost Inputs'!$B$7 -> 0.1 | M61: ='2. Cost Inputs'!$D$40 -> 100 | N61: ='2. Cost Inputs'!$D$41 -> 1500 | O61: =$B$55 -> 56250000 | P61: ='2. Cost Inputs'!$B$35 -> 0.07 | Q61: ='2. Cost Inputs'!$D$24 -> 0.3 | R61: =((K61/'2. Cost Inputs'!$B$5-$B$19+$B$20)*'2. Cost Inputs'!$B$25+(K61/'2. Cost Inputs'!$B$5+$B$20)*'2. Cost Inputs'!$B$26)*365*'2. Cost Inputs'!$B$5 -> 2468400 | S61: ='2. Cost Inputs'!$D$31 -> 150000 | T61: =PI()/6*(J61*10^-9)^3*2160 -> 3.8170351e-18 | U61: ='1. Technology Description'!$B$8*'1. Technology Description'!$B$9*T61*86400*1000 -> 405.08331 | V61: =U61*365*K61/1000000 -> 0.048609997 | W61: ='2. Cost Inputs'!$B$14*1000/'1. Technology Description'!$B$17 -> 8141.3336 | X61: ='2. Cost Inputs'!$B$14 -> 4168.3628 | Y61: =1 -> 1 | Z61: =W61*M61+X61*N61+Y61*'2. Cost Inputs'!$D$42+Y61*O61 -> 63341678 | AA61: =Z61*(1+'2. Cost Inputs'!$B$49+'2. Cost Inputs'!$B$50+'2. Cost Inputs'!$B$52)+(W61*M61+X61*N61+Y61*'2. Cost Inputs'!$D$42)*'2. Cost Inputs'!$B$51 -> 1.0276502e+08 | AB61: =(L61*(1+L61)^'2. Cost Inputs'!$B$6)/((1+L61)^'2. Cost Inputs'!$B$6-1) -> 0.13147378 | AC61: =AA61*AB61 -> 13510905 | AD61: ='1. Technology Description'!$B$17*24/1000/(U61/1000000) -> 30334.501 | AE61: =AD61*Q61*AK61 -> 3601465.4 | AF61: =Y61*'2. Cost Inputs'!$B$31*S61 -> 900000 | AG61: =AA61*P61 -> 7193551.4 | AH61: =R61*'2. Cost Inputs'!$D$25*Y61 -> 2221560 | AI61: =AC61+AE61+AF61+AG61+AH61+(('1. Technology Description'!$B$24/(U61/1000000)/1000)*'1. Technology Description'!$B$26*'2. Cost Inputs'!$D$28*AK61) -> 27433711 | AJ61: =AI61/AK61 -> 69320.778 | AK61: =W61*V61 -> 395.7502
A62: Tornado chart data (helper) | I62: vessel cost best | J62: ='1. Technology Description'!$B$10 -> 150 | K62: =($B$18+$B$19)*'2. Cost Inputs'!$B$5 -> 0.32876712 | L62: ='2. Cost Inputs'!$B$7 -> 0.1 | M62: ='2. Cost Inputs'!$D$40 -> 100 | N62: ='2. Cost Inputs'!$D$41 -> 1500 | O62: =$D$55 -> 22500000 | P62: ='2. Cost Inputs'!$B$35 -> 0.07 | Q62: ='2. Cost Inputs'!$D$24 -> 0.3 | R62: =((K62/'2. Cost Inputs'!$B$5-$B$19+$B$20)*'2. Cost Inputs'!$B$25+(K62/'2. Cost Inputs'!$B$5+$B$20)*'2. Cost Inputs'!$B$26)*365*'2. Cost Inputs'!$B$5 -> 2468400 | S62: ='2. Cost Inputs'!$D$31 -> 150000 | T62: =PI()/6*(J62*10^-9)^3*2160 -> 3.8170351e-18 | U62: ='1. Technology Description'!$B$8*'1. Technology Description'!$B$9*T62*86400*1000 -> 405.08331 | V62: =U62*365*K62/1000000 -> 0.048609997 | W62: ='2. Cost Inputs'!$B$14*1000/'1. Technology Description'!$B$17 -> 8141.3336 | X62: ='2. Cost Inputs'!$B$14 -> 4168.3628 | Y62: =1 -> 1 | Z62: =W62*M62+X62*N62+Y62*'2. Cost Inputs'!$D$42+Y62*O62 -> 29591678 | AA62: =Z62*(1+'2. Cost Inputs'!$B$49+'2. Cost Inputs'!$B$50+'2. Cost Inputs'!$B$52)+(W62*M62+X62*N62+Y62*'2. Cost Inputs'!$D$42)*'2. Cost Inputs'!$B$51 -> 48765020 | AB62: =(L62*(1+L62)^'2. Cost Inputs'!$B$6)/((1+L62)^'2. Cost Inputs'!$B$6-1) -> 0.13147378 | AC62: =AA62*AB62 -> 6411321.3 | AD62: ='1. Technology Description'!$B$17*24/1000/(U62/1000000) -> 30334.501 | AE62: =AD62*Q62*AK62 -> 3601465.4 | AF62: =Y62*'2. Cost Inputs'!$B$31*S62 -> 900000 | AG62: =AA62*P62 -> 3413551.4 | AH62: =R62*'2. Cost Inputs'!$D$25*Y62 -> 2221560 | AI62: =AC62+AE62+AF62+AG62+AH62+(('1. Technology Description'!$B$24/(U62/1000000)/1000)*'1. Technology Description'!$B$26*'2. Cost Inputs'!$D$28*AK62) -> 16554128 | AJ62: =AI62/AK62 -> 41829.739 | AK62: =W62*V62 -> 395.7502
A63: Variable | B63: spacer (hidden) | C63: cost-reducing span | D63: cost-raising span | E63: max (label helper) | I63: maint worst | J63: ='1. Technology Description'!$B$10 -> 150 | K63: =($B$18+$B$19)*'2. Cost Inputs'!$B$5 -> 0.32876712 | L63: ='2. Cost Inputs'!$B$7 -> 0.1 | M63: ='2. Cost Inputs'!$D$40 -> 100 | N63: ='2. Cost Inputs'!$D$41 -> 1500 | O63: ='2. Cost Inputs'!$D$43 -> 7500000 | P63: =$B$56 -> 0.112 | Q63: ='2. Cost Inputs'!$D$24 -> 0.3 | R63: =((K63/'2. Cost Inputs'!$B$5-$B$19+$B$20)*'2. Cost Inputs'!$B$25+(K63/'2. Cost Inputs'!$B$5+$B$20)*'2. Cost Inputs'!$B$26)*365*'2. Cost Inputs'!$B$5 -> 2468400 | S63: ='2. Cost Inputs'!$D$31 -> 150000 | T63: =PI()/6*(J63*10^-9)^3*2160 -> 3.8170351e-18 | U63: ='1. Technology Description'!$B$8*'1. Technology Description'!$B$9*T63*86400*1000 -> 405.08331 | V63: =U63*365*K63/1000000 -> 0.048609997 | W63: ='2. Cost Inputs'!$B$14*1000/'1. Technology Description'!$B$17 -> 8141.3336 | X63: ='2. Cost Inputs'!$B$14 -> 4168.3628 | Y63: =1 -> 1 | Z63: =W63*M63+X63*N63+Y63*'2. Cost Inputs'!$D$42+Y63*O63+Y63*'2. Cost Inputs'!$D$44 -> 44591678 | AA63: =Z63*(1+'2. Cost Inputs'!$B$49+'2. Cost Inputs'!$B$50+'2. Cost Inputs'!$B$52)+(W63*M63+X63*N63+Y63*'2. Cost Inputs'!$D$42)*'2. Cost Inputs'!$B$51 -> 72765020 | AB63: =(L63*(1+L63)^'2. Cost Inputs'!$B$6)/((1+L63)^'2. Cost Inputs'!$B$6-1) -> 0.13147378 | AC63: =AA63*AB63 -> 9566691.9 | AD63: ='1. Technology Description'!$B$17*24/1000/(U63/1000000) -> 30334.501 | AE63: =AD63*Q63*AK63 -> 3601465.4 | AF63: =Y63*'2. Cost Inputs'!$B$31*S63 -> 900000 | AG63: =AA63*P63 -> 8149682.2 | AH63: =R63*'2. Cost Inputs'!$D$25*Y63 -> 2221560 | AI63: =AC63+AE63+AF63+AG63+AH63+(('1. Technology Description'!$B$24/(U63/1000000)/1000)*'1. Technology Description'!$B$26*'2. Cost Inputs'!$D$28*AK63) -> 24445629 | AJ63: =AI63/AK63 -> 61770.352 | AK63: =W63*V63 -> 395.7502
A64: Compressor $/kW | B64: =MIN(AJ69,AJ70) -> 51756.126 | C64: =$AJ$50-MIN(AJ69,AJ70) -> 2291.8524 | D64: =MAX(AJ69,AJ70)-$AJ$50 -> 2864.8156 | E64: =MAX(AJ69,AJ70) -> 56912.794 | I64: maint best | J64: ='1. Technology Description'!$B$10 -> 150 | K64: =($B$18+$B$19)*'2. Cost Inputs'!$B$5 -> 0.32876712 | L64: ='2. Cost Inputs'!$B$7 -> 0.1 | M64: ='2. Cost Inputs'!$D$40 -> 100 | N64: ='2. Cost Inputs'!$D$41 -> 1500 | O64: ='2. Cost Inputs'!$D$43 -> 7500000 | P64: =$D$56 -> 0.035 | Q64: ='2. Cost Inputs'!$D$24 -> 0.3 | R64: =((K64/'2. Cost Inputs'!$B$5-$B$19+$B$20)*'2. Cost Inputs'!$B$25+(K64/'2. Cost Inputs'!$B$5+$B$20)*'2. Cost Inputs'!$B$26)*365*'2. Cost Inputs'!$B$5 -> 2468400 | S64: ='2. Cost Inputs'!$D$31 -> 150000 | T64: =PI()/6*(J64*10^-9)^3*2160 -> 3.8170351e-18 | U64: ='1. Technology Description'!$B$8*'1. Technology Description'!$B$9*T64*86400*1000 -> 405.08331 | V64: =U64*365*K64/1000000 -> 0.048609997 | W64: ='2. Cost Inputs'!$B$14*1000/'1. Technology Description'!$B$17 -> 8141.3336 | X64: ='2. Cost Inputs'!$B$14 -> 4168.3628 | Y64: =1 -> 1 | Z64: =W64*M64+X64*N64+Y64*'2. Cost Inputs'!$D$42+Y64*O64+Y64*'2. Cost Inputs'!$D$44 -> 44591678 | AA64: =Z64*(1+'2. Cost Inputs'!$B$49+'2. Cost Inputs'!$B$50+'2. Cost Inputs'!$B$52)+(W64*M64+X64*N64+Y64*'2. Cost Inputs'!$D$42)*'2. Cost Inputs'!$B$51 -> 72765020 | AB64: =(L64*(1+L64)^'2. Cost Inputs'!$B$6)/((1+L64)^'2. Cost Inputs'!$B$6-1) -> 0.13147378 | AC64: =AA64*AB64 -> 9566691.9 | AD64: ='1. Technology Description'!$B$17*24/1000/(U64/1000000) -> 30334.501 | AE64: =AD64*Q64*AK64 -> 3601465.4 | AF64: =Y64*'2. Cost Inputs'!$B$31*S64 -> 900000 | AG64: =AA64*P64 -> 2546775.7 | AH64: =R64*'2. Cost Inputs'!$D$25*Y64 -> 2221560 | AI64: =AC64+AE64+AF64+AG64+AH64+(('1. Technology Description'!$B$24/(U64/1000000)/1000)*'1. Technology Description'!$B$26*'2. Cost Inputs'!$D$28*AK64) -> 18842722 | AJ64: =AI64/AK64 -> 47612.667 | AK64: =W64*V64 -> 395.7502
A65: Energy price | B65: =MIN(AJ67,AJ68) -> 50407.838 | C65: =$AJ$50-MIN(AJ67,AJ68) -> 3640.1401 | D65: =MAX(AJ67,AJ68)-$AJ$50 -> 4550.1752 | E65: =MAX(AJ67,AJ68) -> 58598.154 | I65: disc worst | J65: ='1. Technology Description'!$B$10 -> 150 | K65: =($B$18+$B$19)*'2. Cost Inputs'!$B$5 -> 0.32876712 | L65: =$B$57 -> 0.15 | M65: ='2. Cost Inputs'!$D$40 -> 100 | N65: ='2. Cost Inputs'!$D$41 -> 1500 | O65: ='2. Cost Inputs'!$D$43 -> 7500000 | P65: ='2. Cost Inputs'!$B$35 -> 0.07 | Q65: ='2. Cost Inputs'!$D$24 -> 0.3 | R65: =((K65/'2. Cost Inputs'!$B$5-$B$19+$B$20)*'2. Cost Inputs'!$B$25+(K65/'2. Cost Inputs'!$B$5+$B$20)*'2. Cost Inputs'!$B$26)*365*'2. Cost Inputs'!$B$5 -> 2468400 | S65: ='2. Cost Inputs'!$D$31 -> 150000 | T65: =PI()/6*(J65*10^-9)^3*2160 -> 3.8170351e-18 | U65: ='1. Technology Description'!$B$8*'1. Technology Description'!$B$9*T65*86400*1000 -> 405.08331 | V65: =U65*365*K65/1000000 -> 0.048609997 | W65: ='2. Cost Inputs'!$B$14*1000/'1. Technology Description'!$B$17 -> 8141.3336 | X65: ='2. Cost Inputs'!$B$14 -> 4168.3628 | Y65: =1 -> 1 | Z65: =W65*M65+X65*N65+Y65*'2. Cost Inputs'!$D$42+Y65*O65+Y65*'2. Cost Inputs'!$D$44 -> 44591678 | AA65: =Z65*(1+'2. Cost Inputs'!$B$49+'2. Cost Inputs'!$B$50+'2. Cost Inputs'!$B$52)+(W65*M65+X65*N65+Y65*'2. Cost Inputs'!$D$42)*'2. Cost Inputs'!$B$51 -> 72765020 | AB65: =(L65*(1+L65)^'2. Cost Inputs'!$B$6)/((1+L65)^'2. Cost Inputs'!$B$6-1) -> 0.17101705 | AC65: =AA65*AB65 -> 12444059 | AD65: ='1. Technology Description'!$B$17*24/1000/(U65/1000000) -> 30334.501 | AE65: =AD65*Q65*AK65 -> 3601465.4 | AF65: =Y65*'2. Cost Inputs'!$B$31*S65 -> 900000 | AG65: =AA65*P65 -> 5093551.4 | AH65: =R65*'2. Cost Inputs'!$D$25*Y65 -> 2221560 | AI65: =AC65+AE65+AF65+AG65+AH65+(('1. Technology Description'!$B$24/(U65/1000000)/1000)*'1. Technology Description'!$B$26*'2. Cost Inputs'!$D$28*AK65) -> 24266865 | AJ65: =AI65/AK65 -> 61318.644 | AK65: =W65*V65 -> 395.7502
A66: Discount rate | B66: =MIN(AJ65,AJ66) -> 48805.772 | C66: =$AJ$50-MIN(AJ65,AJ66) -> 5242.2069 | D66: =MAX(AJ65,AJ66)-$AJ$50 -> 7270.6653 | E66: =MAX(AJ65,AJ66) -> 61318.644 | I66: disc best | J66: ='1. Technology Description'!$B$10 -> 150 | K66: =($B$18+$B$19)*'2. Cost Inputs'!$B$5 -> 0.32876712 | L66: =$D$57 -> 0.06 | M66: ='2. Cost Inputs'!$D$40 -> 100 | N66: ='2. Cost Inputs'!$D$41 -> 1500 | O66: ='2. Cost Inputs'!$D$43 -> 7500000 | P66: ='2. Cost Inputs'!$B$35 -> 0.07 | Q66: ='2. Cost Inputs'!$D$24 -> 0.3 | R66: =((K66/'2. Cost Inputs'!$B$5-$B$19+$B$20)*'2. Cost Inputs'!$B$25+(K66/'2. Cost Inputs'!$B$5+$B$20)*'2. Cost Inputs'!$B$26)*365*'2. Cost Inputs'!$B$5 -> 2468400 | S66: ='2. Cost Inputs'!$D$31 -> 150000 | T66: =PI()/6*(J66*10^-9)^3*2160 -> 3.8170351e-18 | U66: ='1. Technology Description'!$B$8*'1. Technology Description'!$B$9*T66*86400*1000 -> 405.08331 | V66: =U66*365*K66/1000000 -> 0.048609997 | W66: ='2. Cost Inputs'!$B$14*1000/'1. Technology Description'!$B$17 -> 8141.3336 | X66: ='2. Cost Inputs'!$B$14 -> 4168.3628 | Y66: =1 -> 1 | Z66: =W66*M66+X66*N66+Y66*'2. Cost Inputs'!$D$42+Y66*O66+Y66*'2. Cost Inputs'!$D$44 -> 44591678 | AA66: =Z66*(1+'2. Cost Inputs'!$B$49+'2. Cost Inputs'!$B$50+'2. Cost Inputs'!$B$52)+(W66*M66+X66*N66+Y66*'2. Cost Inputs'!$D$42)*'2. Cost Inputs'!$B$51 -> 72765020 | AB66: =(L66*(1+L66)^'2. Cost Inputs'!$B$6)/((1+L66)^'2. Cost Inputs'!$B$6-1) -> 0.10296276 | AC66: =AA66*AB66 -> 7492087.5 | AD66: ='1. Technology Description'!$B$17*24/1000/(U66/1000000) -> 30334.501 | AE66: =AD66*Q66*AK66 -> 3601465.4 | AF66: =Y66*'2. Cost Inputs'!$B$31*S66 -> 900000 | AG66: =AA66*P66 -> 5093551.4 | AH66: =R66*'2. Cost Inputs'!$D$25*Y66 -> 2221560 | AI66: =AC66+AE66+AF66+AG66+AH66+(('1. Technology Description'!$B$24/(U66/1000000)/1000)*'1. Technology Description'!$B$26*'2. Cost Inputs'!$D$28*AK66) -> 19314894 | AJ66: =AI66/AK66 -> 48805.772 | AK66: =W66*V66 -> 395.7502
A67: Maintenance % | B67: =MIN(AJ63,AJ64) -> 47612.667 | C67: =$AJ$50-MIN(AJ63,AJ64) -> 6435.3112 | D67: =MAX(AJ63,AJ64)-$AJ$50 -> 7722.3735 | E67: =MAX(AJ63,AJ64) -> 61770.352 | I67: energy price worst | J67: ='1. Technology Description'!$B$10 -> 150 | K67: =($B$18+$B$19)*'2. Cost Inputs'!$B$5 -> 0.32876712 | L67: ='2. Cost Inputs'!$B$7 -> 0.1 | M67: ='2. Cost Inputs'!$D$40 -> 100 | N67: ='2. Cost Inputs'!$D$41 -> 1500 | O67: ='2. Cost Inputs'!$D$43 -> 7500000 | P67: ='2. Cost Inputs'!$B$35 -> 0.07 | Q67: =$B$58 -> 0.45 | R67: =((K67/'2. Cost Inputs'!$B$5-$B$19+$B$20)*'2. Cost Inputs'!$B$25+(K67/'2. Cost Inputs'!$B$5+$B$20)*'2. Cost Inputs'!$B$26)*365*'2. Cost Inputs'!$B$5 -> 2468400 | S67: ='2. Cost Inputs'!$D$31 -> 150000 | T67: =PI()/6*(J67*10^-9)^3*2160 -> 3.8170351e-18 | U67: ='1. Technology Description'!$B$8*'1. Technology Description'!$B$9*T67*86400*1000 -> 405.08331 | V67: =U67*365*K67/1000000 -> 0.048609997 | W67: ='2. Cost Inputs'!$B$14*1000/'1. Technology Description'!$B$17 -> 8141.3336 | X67: ='2. Cost Inputs'!$B$14 -> 4168.3628 | Y67: =1 -> 1 | Z67: =W67*M67+X67*N67+Y67*'2. Cost Inputs'!$D$42+Y67*O67+Y67*'2. Cost Inputs'!$D$44 -> 44591678 | AA67: =Z67*(1+'2. Cost Inputs'!$B$49+'2. Cost Inputs'!$B$50+'2. Cost Inputs'!$B$52)+(W67*M67+X67*N67+Y67*'2. Cost Inputs'!$D$42)*'2. Cost Inputs'!$B$51 -> 72765020 | AB67: =(L67*(1+L67)^'2. Cost Inputs'!$B$6)/((1+L67)^'2. Cost Inputs'!$B$6-1) -> 0.13147378 | AC67: =AA67*AB67 -> 9566691.9 | AD67: ='1. Technology Description'!$B$17*24/1000/(U67/1000000) -> 30334.501 | AE67: =AD67*Q67*AK67 -> 5402198.2 | AF67: =Y67*'2. Cost Inputs'!$B$31*S67 -> 900000 | AG67: =AA67*P67 -> 5093551.4 | AH67: =R67*'2. Cost Inputs'!$D$25*Y67 -> 2221560 | AI67: =AC67+AE67+AF67+AG67+AH67+(('1. Technology Description'!$B$24/(U67/1000000)/1000)*'1. Technology Description'!$B$26*'2. Cost Inputs'!$D$28*AK67) -> 23190231 | AJ67: =AI67/AK67 -> 58598.154 | AK67: =W67*V67 -> 395.7502
A68: Vessel cost | B68: =MIN(AJ61,AJ62) -> 41829.739 | C68: =$AJ$50-MIN(AJ61,AJ62) -> 12218.239 | D68: =MAX(AJ61,AJ62)-$AJ$50 -> 15272.799 | E68: =MAX(AJ61,AJ62) -> 69320.778 | I68: energy price best | J68: ='1. Technology Description'!$B$10 -> 150 | K68: =($B$18+$B$19)*'2. Cost Inputs'!$B$5 -> 0.32876712 | L68: ='2. Cost Inputs'!$B$7 -> 0.1 | M68: ='2. Cost Inputs'!$D$40 -> 100 | N68: ='2. Cost Inputs'!$D$41 -> 1500 | O68: ='2. Cost Inputs'!$D$43 -> 7500000 | P68: ='2. Cost Inputs'!$B$35 -> 0.07 | Q68: =$D$58 -> 0.18 | R68: =((K68/'2. Cost Inputs'!$B$5-$B$19+$B$20)*'2. Cost Inputs'!$B$25+(K68/'2. Cost Inputs'!$B$5+$B$20)*'2. Cost Inputs'!$B$26)*365*'2. Cost Inputs'!$B$5 -> 2468400 | S68: ='2. Cost Inputs'!$D$31 -> 150000 | T68: =PI()/6*(J68*10^-9)^3*2160 -> 3.8170351e-18 | U68: ='1. Technology Description'!$B$8*'1. Technology Description'!$B$9*T68*86400*1000 -> 405.08331 | V68: =U68*365*K68/1000000 -> 0.048609997 | W68: ='2. Cost Inputs'!$B$14*1000/'1. Technology Description'!$B$17 -> 8141.3336 | X68: ='2. Cost Inputs'!$B$14 -> 4168.3628 | Y68: =1 -> 1 | Z68: =W68*M68+X68*N68+Y68*'2. Cost Inputs'!$D$42+Y68*O68+Y68*'2. Cost Inputs'!$D$44 -> 44591678 | AA68: =Z68*(1+'2. Cost Inputs'!$B$49+'2. Cost Inputs'!$B$50+'2. Cost Inputs'!$B$52)+(W68*M68+X68*N68+Y68*'2. Cost Inputs'!$D$42)*'2. Cost Inputs'!$B$51 -> 72765020 | AB68: =(L68*(1+L68)^'2. Cost Inputs'!$B$6)/((1+L68)^'2. Cost Inputs'!$B$6-1) -> 0.13147378 | AC68: =AA68*AB68 -> 9566691.9 | AD68: ='1. Technology Description'!$B$17*24/1000/(U68/1000000) -> 30334.501 | AE68: =AD68*Q68*AK68 -> 2160879.3 | AF68: =Y68*'2. Cost Inputs'!$B$31*S68 -> 900000 | AG68: =AA68*P68 -> 5093551.4 | AH68: =R68*'2. Cost Inputs'!$D$25*Y68 -> 2221560 | AI68: =AC68+AE68+AF68+AG68+AH68+(('1. Technology Description'!$B$24/(U68/1000000)/1000)*'1. Technology Description'!$B$26*'2. Cost Inputs'!$D$28*AK68) -> 19948912 | AJ68: =AI68/AK68 -> 50407.838 | AK68: =W68*V68 -> 395.7502
A69: Nozzle unit cost | B69: =MIN(AJ59,AJ60) -> 53376.537 | C69: =$AJ$50-MIN(AJ59,AJ60) -> 671.44115 | D69: =MAX(AJ59,AJ60)-$AJ$50 -> 6714.4115 | E69: =MAX(AJ59,AJ60) -> 60762.39 | I69: compressor worst | J69: ='1. Technology Description'!$B$10 -> 150 | K69: =($B$18+$B$19)*'2. Cost Inputs'!$B$5 -> 0.32876712 | L69: ='2. Cost Inputs'!$B$7 -> 0.1 | M69: ='2. Cost Inputs'!$D$40 -> 100 | N69: =$B$59 -> 2250 | O69: ='2. Cost Inputs'!$D$43 -> 7500000 | P69: ='2. Cost Inputs'!$B$35 -> 0.07 | Q69: ='2. Cost Inputs'!$D$24 -> 0.3 | R69: =((K69/'2. Cost Inputs'!$B$5-$B$19+$B$20)*'2. Cost Inputs'!$B$25+(K69/'2. Cost Inputs'!$B$5+$B$20)*'2. Cost Inputs'!$B$26)*365*'2. Cost Inputs'!$B$5 -> 2468400 | S69: ='2. Cost Inputs'!$D$31 -> 150000 | T69: =PI()/6*(J69*10^-9)^3*2160 -> 3.8170351e-18 | U69: ='1. Technology Description'!$B$8*'1. Technology Description'!$B$9*T69*86400*1000 -> 405.08331 | V69: =U69*365*K69/1000000 -> 0.048609997 | W69: ='2. Cost Inputs'!$B$14*1000/'1. Technology Description'!$B$17 -> 8141.3336 | X69: ='2. Cost Inputs'!$B$14 -> 4168.3628 | Y69: =1 -> 1 | Z69: =W69*M69+X69*N69+Y69*'2. Cost Inputs'!$D$42+Y69*O69+Y69*'2. Cost Inputs'!$D$44 -> 47717950 | AA69: =Z69*(1+'2. Cost Inputs'!$B$49+'2. Cost Inputs'!$B$50+'2. Cost Inputs'!$B$52)+(W69*M69+X69*N69+Y69*'2. Cost Inputs'!$D$42)*'2. Cost Inputs'!$B$51 -> 78392309 | AB69: =(L69*(1+L69)^'2. Cost Inputs'!$B$6)/((1+L69)^'2. Cost Inputs'!$B$6-1) -> 0.13147378 | AC69: =AA69*AB69 -> 10306533 | AD69: ='1. Technology Description'!$B$17*24/1000/(U69/1000000) -> 30334.501 | AE69: =AD69*Q69*AK69 -> 3601465.4 | AF69: =Y69*'2. Cost Inputs'!$B$31*S69 -> 900000 | AG69: =AA69*P69 -> 5487461.7 | AH69: =R69*'2. Cost Inputs'!$D$25*Y69 -> 2221560 | AI69: =AC69+AE69+AF69+AG69+AH69+(('1. Technology Description'!$B$24/(U69/1000000)/1000)*'1. Technology Description'!$B$26*'2. Cost Inputs'!$D$28*AK69) -> 22523249 | AJ69: =AI69/AK69 -> 56912.794 | AK69: =W69*V69 -> 395.7502
A70: Annual utilization | B70: =MIN(AJ57,AJ58) -> 44856.747 | C70: =$AJ$50-MIN(AJ57,AJ58) -> 9191.2311 | D70: =MAX(AJ57,AJ58)-$AJ$50 -> 26552.446 | E70: =MAX(AJ57,AJ58) -> 80600.424 | I70: compressor best | J70: ='1. Technology Description'!$B$10 -> 150 | K70: =($B$18+$B$19)*'2. Cost Inputs'!$B$5 -> 0.32876712 | L70: ='2. Cost Inputs'!$B$7 -> 0.1 | M70: ='2. Cost Inputs'!$D$40 -> 100 | N70: =$D$59 -> 900 | O70: ='2. Cost Inputs'!$D$43 -> 7500000 | P70: ='2. Cost Inputs'!$B$35 -> 0.07 | Q70: ='2. Cost Inputs'!$D$24 -> 0.3 | R70: =((K70/'2. Cost Inputs'!$B$5-$B$19+$B$20)*'2. Cost Inputs'!$B$25+(K70/'2. Cost Inputs'!$B$5+$B$20)*'2. Cost Inputs'!$B$26)*365*'2. Cost Inputs'!$B$5 -> 2468400 | S70: ='2. Cost Inputs'!$D$31 -> 150000 | T70: =PI()/6*(J70*10^-9)^3*2160 -> 3.8170351e-18 | U70: ='1. Technology Description'!$B$8*'1. Technology Description'!$B$9*T70*86400*1000 -> 405.08331 | V70: =U70*365*K70/1000000 -> 0.048609997 | W70: ='2. Cost Inputs'!$B$14*1000/'1. Technology Description'!$B$17 -> 8141.3336 | X70: ='2. Cost Inputs'!$B$14 -> 4168.3628 | Y70: =1 -> 1 | Z70: =W70*M70+X70*N70+Y70*'2. Cost Inputs'!$D$42+Y70*O70+Y70*'2. Cost Inputs'!$D$44 -> 42090660 | AA70: =Z70*(1+'2. Cost Inputs'!$B$49+'2. Cost Inputs'!$B$50+'2. Cost Inputs'!$B$52)+(W70*M70+X70*N70+Y70*'2. Cost Inputs'!$D$42)*'2. Cost Inputs'!$B$51 -> 68263188 | AB70: =(L70*(1+L70)^'2. Cost Inputs'!$B$6)/((1+L70)^'2. Cost Inputs'!$B$6-1) -> 0.13147378 | AC70: =AA70*AB70 -> 8974819.1 | AD70: ='1. Technology Description'!$B$17*24/1000/(U70/1000000) -> 30334.501 | AE70: =AD70*Q70*AK70 -> 3601465.4 | AF70: =Y70*'2. Cost Inputs'!$B$31*S70 -> 900000 | AG70: =AA70*P70 -> 4778423.1 | AH70: =R70*'2. Cost Inputs'!$D$25*Y70 -> 2221560 | AI70: =AC70+AE70+AF70+AG70+AH70+(('1. Technology Description'!$B$24/(U70/1000000)/1000)*'1. Technology Description'!$B$26*'2. Cost Inputs'!$D$28*AK70) -> 20482497 | AJ70: =AI70/AK70 -> 51756.126 | AK70: =W70*V70 -> 395.7502
A71: Crew cost | B71: =MIN(AJ55,AJ56) -> 53365.73 | C71: =$AJ$50-MIN(AJ55,AJ56) -> 682.24856 | D71: =MAX(AJ55,AJ56)-$AJ$50 -> 909.66474 | E71: =MAX(AJ55,AJ56) -> 54957.643 | I71: Particle rate worst | J71: ='1. Technology Description'!$B$10 -> 150 | K71: =($B$18+$B$19)*'2. Cost Inputs'!$B$5 -> 0.32876712 | L71: ='2. Cost Inputs'!$B$7 -> 0.1 | M71: ='2. Cost Inputs'!$D$40 -> 100 | N71: ='2. Cost Inputs'!$D$41 -> 1500 | O71: ='2. Cost Inputs'!$D$43 -> 7500000 | P71: ='2. Cost Inputs'!$B$35 -> 0.07 | Q71: ='2. Cost Inputs'!$D$24 -> 0.3 | R71: =((K71/'2. Cost Inputs'!$B$5-$B$19+$B$20)*'2. Cost Inputs'!$B$25+(K71/'2. Cost Inputs'!$B$5+$B$20)*'2. Cost Inputs'!$B$26)*365*'2. Cost Inputs'!$B$5 -> 2468400 | S71: ='2. Cost Inputs'!$D$31 -> 150000 | T71: =PI()/6*(J71*10^-9)^3*2160 -> 3.8170351e-18 | U71: =$B$50*'1. Technology Description'!$B$9*T71*86400*1000 -> 344.32081 | V71: =U71*365*K71/1000000 -> 0.041318497 | W71: ='2. Cost Inputs'!$B$14*1000/'1. Technology Description'!$B$17 -> 8141.3336 | X71: ='2. Cost Inputs'!$B$14 -> 4168.3628 | Y71: =1 -> 1 | Z71: =W71*M71+X71*N71+Y71*'2. Cost Inputs'!$D$42+Y71*O71+Y71*'2. Cost Inputs'!$D$44 -> 44591678 | AA71: =Z71*(1+'2. Cost Inputs'!$B$49+'2. Cost Inputs'!$B$50+'2. Cost Inputs'!$B$52)+(W71*M71+X71*N71+Y71*'2. Cost Inputs'!$D$42)*'2. Cost Inputs'!$B$51 -> 72765020 | AB71: =(L71*(1+L71)^'2. Cost Inputs'!$B$6)/((1+L71)^'2. Cost Inputs'!$B$6-1) -> 0.13147378 | AC71: =AA71*AB71 -> 9566691.9 | AD71: ='1. Technology Description'!$B$17*24/1000/(U71/1000000) -> 35687.648 | AE71: =AD71*Q71*AK71 -> 3601465.4 | AF71: =Y71*'2. Cost Inputs'!$B$31*S71 -> 900000 | AG71: =AA71*P71 -> 5093551.4 | AH71: =R71*'2. Cost Inputs'!$D$25*Y71 -> 2221560 | AI71: =AC71+AE71+AF71+AG71+AH71+(('1. Technology Description'!$B$24/(U71/1000000)/1000)*'1. Technology Description'!$B$26*'2. Cost Inputs'!$D$28*AK71) -> 21389498 | AJ71: =AI71/AK71 -> 63585.857 | AK71: =W71*V71 -> 336.38767
A72: Vessel fuel/yr | B72: =MIN(AJ53,AJ54) -> 51241.208 | C72: =$AJ$50-MIN(AJ53,AJ54) -> 2806.7706 | D72: =MAX(AJ53,AJ54)-$AJ$50 -> 2806.7706 | E72: =MAX(AJ53,AJ54) -> 56854.749 | I72: Particle rate best | J72: ='1. Technology Description'!$B$10 -> 150 | K72: =($B$18+$B$19)*'2. Cost Inputs'!$B$5 -> 0.32876712 | L72: ='2. Cost Inputs'!$B$7 -> 0.1 | M72: ='2. Cost Inputs'!$D$40 -> 100 | N72: ='2. Cost Inputs'!$D$41 -> 1500 | O72: ='2. Cost Inputs'!$D$43 -> 7500000 | P72: ='2. Cost Inputs'!$B$35 -> 0.07 | Q72: ='2. Cost Inputs'!$D$24 -> 0.3 | R72: =((K72/'2. Cost Inputs'!$B$5-$B$19+$B$20)*'2. Cost Inputs'!$B$25+(K72/'2. Cost Inputs'!$B$5+$B$20)*'2. Cost Inputs'!$B$26)*365*'2. Cost Inputs'!$B$5 -> 2468400 | S72: ='2. Cost Inputs'!$D$31 -> 150000 | T72: =PI()/6*(J72*10^-9)^3*2160 -> 3.8170351e-18 | U72: =$D$50*'1. Technology Description'!$B$9*T72*86400*1000 -> 465.8458 | V72: =U72*365*K72/1000000 -> 0.055901496 | W72: ='2. Cost Inputs'!$B$14*1000/'1. Technology Description'!$B$17 -> 8141.3336 | X72: ='2. Cost Inputs'!$B$14 -> 4168.3628 | Y72: =1 -> 1 | Z72: =W72*M72+X72*N72+Y72*'2. Cost Inputs'!$D$42+Y72*O72+Y72*'2. Cost Inputs'!$D$44 -> 44591678 | AA72: =Z72*(1+'2. Cost Inputs'!$B$49+'2. Cost Inputs'!$B$50+'2. Cost Inputs'!$B$52)+(W72*M72+X72*N72+Y72*'2. Cost Inputs'!$D$42)*'2. Cost Inputs'!$B$51 -> 72765020 | AB72: =(L72*(1+L72)^'2. Cost Inputs'!$B$6)/((1+L72)^'2. Cost Inputs'!$B$6-1) -> 0.13147378 | AC72: =AA72*AB72 -> 9566691.9 | AD72: ='1. Technology Description'!$B$17*24/1000/(U72/1000000) -> 26377.827 | AE72: =AD72*Q72*AK72 -> 3601465.4 | AF72: =Y72*'2. Cost Inputs'!$B$31*S72 -> 900000 | AG72: =AA72*P72 -> 5093551.4 | AH72: =R72*'2. Cost Inputs'!$D$25*Y72 -> 2221560 | AI72: =AC72+AE72+AF72+AG72+AH72+(('1. Technology Description'!$B$24/(U72/1000000)/1000)*'1. Technology Description'!$B$26*'2. Cost Inputs'!$D$28*AK72) -> 21389498 | AJ72: =AI72/AK72 -> 46998.242 | AK72: =W72*V72 -> 455.11273
A73: Particle output rate | B73: =MIN(AJ71,AJ72) -> 46998.242 | C73: =$AJ$50-MIN(AJ71,AJ72) -> 7049.7363 | D73: =MAX(AJ71,AJ72)-$AJ$50 -> 9537.8786 | E73: =MAX(AJ71,AJ72) -> 63585.857 | I73: PPS worst
A74: Power per unit | B74: =MIN(AJ51,AJ52) -> 6090.4057 | C74: =$AJ$50-MIN(AJ51,AJ52) -> 47957.573 | D74: =MAX(AJ51,AJ52)-$AJ$50 -> 26643.096 | E74: =MAX(AJ51,AJ52) -> 80691.075 | I74: PPS best

Sheet 3b. Outputs - Ship Piggyback
A1: Container Ship Piggyback Scenario
A2: Rent deck slots on container ships already running liners. The spray train is sized to its own 4.5 MW of generation (rows 40-43); liner schedules set the spray fraction.
A3: Piggyback Assumptions
B4: Value | C4: Unit | D4: Notes | G4: Sources
A5: Containerized mounting capital per vessel | B5: 100000 | C5: $/vessel | D5: Gear mounting and integration only, no hull purchased | E5: Assumption: gear mounting and integration only, no hull purchased. | G5: Assumption: gear mounting and integration only, no hull purchased.
A6: Technicians per vessel | B6: 3 | C6: people | D6: Ship crew already covered | E6: Assumption: 3 technicians per vessel. | G6: Assumption: 3 technicians per vessel.
A7: Technician annual cost | B7: 180000 | C7: $/person | D7: Loaded annual cost | E7: Assumption (loaded annual cost). | G7: Assumption (loaded annual cost).
A8: Energy price (own generation: tab 2 diesel rate) | B8: ='2. Cost Inputs'!D24 -> 0.3 | C8: $/kWh | D8: The spray train brings its own gensets (tab 2 row 41 capex), so power is priced at the tab-2 diesel rate. Until 10/07 a separate "shipboard" $0.25 was typed here. | E8: Assumption within noted range: grid ~$0.10-0.15, marine diesel generation ~$0.20-0.35/kWh. | G8: Assumption within noted range: grid ~$0.10-0.15, marine diesel generation ~$0.20-0.35/kWh.
A9: Spray-train energy (compression + atomization) | B9: ='2. Cost Inputs'!B24*B8*$B$43 -> 3888000 | C9: $/yr | D9: kWh/tonne x shipboard price x annual production
A10: Deck-slot rental per vessel per year | B10: 2000000 | C10: $/vessel/yr | D10: Assumption | E10: Assumption (deck-slot rental per vessel-year). | G10: Assumption (deck-slot rental per vessel-year).
A11: Seawater skid, containerized (pumps, filtration, UV) | B11: 80000 | C11: $/vessel | D11: Until 10/07 typed inside the row-22 formula.
A12: Mission & Endurance
A13: Spray time - moving (underway) | B13: 0.3652968 | C13: % of avail. time | D13: % of available time spraying; host vessel is underway on its route regardless | G13: Assumption: host vessel underway on its route regardless.
A14: Spray time - on station | B14: 0 | C14: % of avail. time | D14: Zero: host vessel does not hold station to spray | G14: Structural zero: host vessel does not hold station to spray.
A15: Transit time (no spray) | B15: 0 | C15: % of avail. time | D15: Zero: no dedicated transit legs - host vessel is on its route | G15: Structural zero: no dedicated transit legs.
A16: Operating days per year | B16: =(B13+B14+B15)*365*'2. Cost Inputs'!$B$5 -> 120 | C16: days | D16: = (spray + transit) % of available time x 365 x equipment availability
A17: Fuel & endurance | D17: Host vessel carries fuel; deck-slot rental covers logistics; no tank endurance limit
A19: Recomputed Levelized Cost
B20: $/yr | C20: $/tonne of aerosol | D20: Notes
A21: Nozzles & compression capex | B21: =B42*'2. Cost Inputs'!D40+B42*'1. Technology Description'!B17/1000*'2. Cost Inputs'!D41 -> 7628906.2
A22: Seawater skid + mounting | B22: =B5+B11 -> 180000 | C22: Skid + container mounting, no hull (single vessel)
A23: Total purchased equipment | B23: =B21+B22 -> 7808906.2
A24: Total capex (x1.8 contingency) | B24: =B23*(1+'2. Cost Inputs'!B49+'2. Cost Inputs'!B50+'2. Cost Inputs'!B51+'2. Cost Inputs'!B52) -> 14056031
A25: Capital recovery factor | B25: =('2. Cost Inputs'!B7*(1+'2. Cost Inputs'!B7)^'2. Cost Inputs'!B6)/((1+'2. Cost Inputs'!B7)^'2. Cost Inputs'!B6-1) -> 0.13147378
A26: Annualized capital | B26: =B24*B25 -> 1847999.5 | C26: =B26/$B$43 -> 4325.474
A27: Energy | B27: =B9 -> 3888000 | C27: =B27/$B$43 -> 9100.3504 | D27: Spray-train energy at the shipboard price (B9). Until 10/07 this row priced energy again at the tab-2 diesel rate and the total added B9 on top, counting energy twice.
A28: Technician (replaces crew) | B28: =B6*B7 -> 540000 | C28: =B28/$B$43 -> 1263.9375
A29: Deck-slot rental | B29: =B10 -> 2000000 | C29: =B29/$B$43 -> 4681.2502
A30: Maintenance & insurance | B30: =B24*'2. Cost Inputs'!B35 -> 983922.19 | C30: =B30/$B$43 -> 2302.993
A31: Total Annual Cost | B31: =(B26+B27+B28+B29+B30) -> 9259921.7
A32: Levelized Cost per Tonne | C32: =B31/$B$43 -> 21674.005
A34: Container Ship vs Dedicated Vessel
B35: Value | C35: Unit | D35: Notes
A36: Dedicated vessel: $/tonne of aerosol | B36: ='3a. Outputs - Dedicated Vessel'!G5 -> 54047.979 | C36: From main model
A37: Container ship: $/tonne of aerosol | B37: =C32 -> 21674.005
A38: Cost relative to dedicated vessel | B38: =B37/B36 -> 0.40101417
A40: Host-ship sizing (own generation)
A41: Power per host ship, own gensets | B41: 4500 | C41: kW | D41: 4.5 MW of containerized gensets is 3 to 5 forty-foot boxes; with compressors the train takes ~20-30 TEU of slots. Sizes the train on this tab. Until 10/07 the train was tab 2's 10^16/s unit (4.2 MW) while 6c assumed 2 MW from the host.
A42: Nozzles per host ship | B42: =B41*1000/'1. Technology Description'!B17 -> 8789.0625 | C42: nozzles | D42: Power per ship / watts per nozzle (tab 1 B17).
A43: Production per host ship | B43: =($B$13+$B$14)*$B$42*'2. Cost Inputs'!$B$11 -> 427.2363 | C43: tonnes/yr | D43: Spray fraction x nozzles x aerosol per nozzle-year (tab 2 B11). Read by 6c.
A44: Diesel CO2 per tonne of aerosol (own gensets, added 2026-10) | B44: ='2. Cost Inputs'!$B$24*'2. Cost Inputs'!$B$64/1000*'2. Cost Inputs'!$B$61 -> 19.450482 | C44: t CO2 / tonne | D44: Spray energy x genset fuel rate x CO2 factor (tab 2 rows 61-64). Host-ship propulsion is not charged to MCB.
A45: Levelized cost incl. diesel CO2 | B45: =C32+B44*'2. Cost Inputs'!$B$63 -> 25369.597 | C45: $/tonne of aerosol | D45: At the tab 2 carbon price (B63). Tab 6c benefit-cost ratios use this.

Sheet 3c. Outputs - Fixed Platform
A1: Fixed Coastal Platform Scenario
A2: Fixed platforms: stay put, run continuously, shore or renewable power, no propulsion fuel. Shore cable priced since 2026-10 (rows 42-46): a ~4.2 MW platform needs array-class 33-66 kV cable (~$0.24-0.65M/km supply). The earlier $0.8-1.5M/km figure was export-class (132-220 kV).
A3: Platform Assumptions
B4: Value | C4: Unit | D4: Notes | G4: Sources
A5: Platform capital per unit | B5: 3000000 | C5: $/platform | D5: Moored buoy / small jack-up / repurposed barge with mooring. Assumption: purpose-built marine structure, far above a $50k container slot. | G5: Assumption: moored buoy / small jack-up / repurposed barge with mooring.
A6: Technicians per platform | B6: 1 | C6: people | D6: Largely automated; periodic maintenance from shore. Closer to the piggyback technician model than a 6-person crew. | G6: Assumption: largely automated, periodic maintenance from shore.
A7: Technician annual cost | B7: 180000 | C7: $/person | D7: Loaded annual cost incl. boat transfers for maintenance trips. | E7: Assumption (includes boat transfers for maintenance trips).
A8: Shore power price | B8: 0.15 | C8: $/kWh | D8: Shore power, cheaper than marine diesel ($0.30/kWh). Set to 0.30 to model diesel gensets. | G8: Assumption: shore-power price; set to 0.30 to model diesel gensets.
A9: Siting + permitting per platform | B9: 250000 | C9: $/platform | D9: New: environmental review, marine permits, consultation near a populated coast. Amortized as capital. | G9: Assumption: environmental review, marine permits, consultation near a populated coast.
A10: Mooring + station-keeping O&M | B10: 60000 | C10: $/platform/yr | D10: New annual cost: mooring inspection, anti-fouling, station-keeping for a fixed marine structure. | E10: Assumption: mooring inspection, anti-fouling, station-keeping O&M.
A12: Mission & Endurance
A13: Spray time - moving (underway) | B13: 0 | C13: % of avail. time | D13: Zero: fixed platform does not move | G13: Structural zero: fixed platform does not move.
A14: Spray time - on station | B14: 0.3652968 | C14: % of avail. time | D14: % of available time spraying; platform is permanently on station | G14: Assumption: platform permanently on station.
A15: Transit time (no spray) | B15: 0 | C15: % of avail. time | D15: Zero: fixed platform has no transit | G15: Structural zero: no transit legs.
A16: Operating days per year | B16: =(B13+B14+B15)*365*'2. Cost Inputs'!$B$5 -> 120 | C16: days | D16: = (spray + transit) % of available time x 365 x equipment availability
A17: Fuel & endurance | D17: Shore-powered; no fuel endurance limit; crew access in suitable weather windows
A19: Recomputed Levelized Cost
B20: $/yr | C20: $/tonne of aerosol | D20: Notes
A21: Nozzles & compression capex | B21: ='2. Cost Inputs'!B13*'2. Cost Inputs'!D40+'2. Cost Inputs'!B14*'2. Cost Inputs'!D41 -> 7066677.5
A22: Seawater skid | B22: ='2. Cost Inputs'!D42 -> 25000 | C22: Intake/filtration/UV skid, one per platform-edge (single platform)
A23: Platform structure + siting | B23: =B5+B9 -> 3250000 | C23: Fixed offshore structure + permitting, single platform
A24: Total purchased equipment | B24: =B21+B22+B23+B46 -> 13640428
A25: Total capex (contingency stack) | B25: =B24*(1+'2. Cost Inputs'!B49+'2. Cost Inputs'!B50+'2. Cost Inputs'!B51+'2. Cost Inputs'!B52) -> 24552770
A26: Capital recovery factor | B26: =('2. Cost Inputs'!B7*(1+'2. Cost Inputs'!B7)^'2. Cost Inputs'!B6)/((1+'2. Cost Inputs'!B7)^'2. Cost Inputs'!B6-1) -> 0.13147378
A27: Annualized capital | B27: =B25*B26 -> 3228045.3 | C27: =B27/(($B$13+$B$14)*'2. Cost Inputs'!$B$15) -> 8156.7751
A28: Energy (shore power) | B28: ='2. Cost Inputs'!B24*B8*(($B$13+$B$14)*'2. Cost Inputs'!$B$15) -> 1800732.7 | C28: =B28/(($B$13+$B$14)*'2. Cost Inputs'!$B$15) -> 4550.1752 | D28: Same kWh/tonne as main model, priced at shore power. No propulsion fuel: platform does not move.
A29: Technician (replaces crew) | B29: =B6*B7 -> 180000 | C29: =B29/(($B$13+$B$14)*'2. Cost Inputs'!$B$15) -> 454.83237 | D29: Automated platform, minimal staffing
A30: Mooring + station-keeping O&M | B30: =B10 -> 60000 | C30: =B30/(($B$13+$B$14)*'2. Cost Inputs'!$B$15) -> 151.61079
A31: Maintenance & insurance | B31: =B25*'2. Cost Inputs'!B35 -> 1718693.9 | C31: =B31/(($B$13+$B$14)*'2. Cost Inputs'!$B$15) -> 4342.8756 | D31: Same 7% of capex as main model
A32: Total Annual Cost | B32: =B27+B28+B29+B30+B31 -> 6987471.9
A33: Levelized Cost per Tonne | C33: =B32/(($B$13+$B$14)*'2. Cost Inputs'!$B$15) -> 17656.269
A35: Fixed Platform vs Other Sitings
B36: Value | C36: Unit | D36: Notes
A37: Dedicated vessel: $/tonne of aerosol | B37: ='3a. Outputs - Dedicated Vessel'!G5 -> 54047.979
A38: Container ship: $/tonne of aerosol | B38: ='3b. Outputs - Ship Piggyback'!C32 -> 21674.005
A39: Fixed platform: $/tonne of aerosol | B39: =C33 -> 17656.269
A40: Cost relative to dedicated vessel | B40: =B39/B37 -> 0.32667769
A42: Shore power cable (added 2026-10)
A43: Cable length to shore | B43: 5 | C43: km | D43: Assumption: near-shore platform. Set 0 with B8 = 0.30 to model diesel gensets on the platform instead (~$19k/t, which bounds this case). | G43: Assumption.
A44: Array-class subsea cable, supply | B44: 455000 | C44: $/km | D44: 33-66 kV array-class cable, $0.24-0.65M/km supply (NREL ORBIT cable library); 0.455 is the library central. | G44: NREL/WISDEM ORBIT library/cables (github.com/WISDEM/ORBIT); Nunemaker et al. 2020, NREL/TP-5000-77081.
A45: Cable installation markup over supply | B45: 0.45 | C45: fraction | D45: +30-60% over supply (BVG Associates 2023, stated for export cables); midpoint. | G45: BVG Associates (2023), Guide to a Floating Offshore Wind Farm.
A46: Cable capex (installed) | B46: =B43*B44*(1+B45) -> 3298750 | C46: $ | D46: Added to purchased equipment (B24), so the contingency stack applies.

Sheet 3d. Outputs - Stationary Vessel
A1: Stationary Vessel Scenario
A2: Transit to position, then hold station. Fuel = hotel burn all days + propulsion on transit days.
A3: Mission & Endurance | G3: Sources
A4: Spray time - moving (underway) | B4: 0 | C4: % of avail. time | D4: Zero: this vessel does not spray while underway | G4: Structural zero: does not spray while underway.
A5: Spray time - on station | B5: 0.3652968 | C5: % of avail. time | D5: Spraying while holding station | G5: Assumption: sprays while holding station.
A6: Transit time (no spray) | B6: 0.01217656 | C6: % of avail. time | D6: Steam out and back; one round trip per year | G6: Assumption: steam out and back, one round trip per year.
A7: Operating days per year | B7: =(B4+B5+B6)*365*'2. Cost Inputs'!$B$5 -> 124 | C7: days | D7: = (spray + transit) % of available time x 365 x equipment availability
A8: Effective production | B8: =(B4+B5)*'2. Cost Inputs'!$B$15 -> 395.7502 | C8: tonnes/yr | D8: = spray % x equipment-basis annual production (availability already applied)
A9: Endurance per tank (on station) | B9: ='3a. Outputs - Dedicated Vessel'!$B$26*'2. Cost Inputs'!B27/'2. Cost Inputs'!B26 -> 333.33333 | C9: days | D9: 90% of tank at hotel burn only - about 11 months on station
A10: Missions per year (tank-limited) | B10: =ROUNDUP(B7/B9,0) -> 1 | C10: missions | D10: Returns to port to refuel this many times
A11: Hotel fuel per year | B11: =B7*'2. Cost Inputs'!B26 -> 334800 | C11: L/yr | D11: = operating days x hotel burn
A12: Transit fuel per year | B12: =(B4+B6)*365*'2. Cost Inputs'!$B$5*'2. Cost Inputs'!B25 -> 64000 | C12: L/yr | D12: = (spray-moving + transit) % x 365 x availability x underway burn
A15: Recomputed Levelized Cost
B16: $/yr | C16: $/tonne of aerosol | D16: Notes
A17: Capital recovery factor | B17: =('2. Cost Inputs'!B7*(1+'2. Cost Inputs'!B7)^'2. Cost Inputs'!B6)/((1+'2. Cost Inputs'!B7)^'2. Cost Inputs'!B6-1) -> 0.13147378
A18: Annualized capital | B18: ='2. Cost Inputs'!B53*B17 -> 9566691.9 | C18: =B18/$B$8 -> 24173.562
A19: Energy (spray) | B19: ='2. Cost Inputs'!B24*'2. Cost Inputs'!D24*$B$8 -> 3601465.4 | C19: =B19/$B$8 -> 9100.3504
A20: Seawater pumping + filtration | B20: ='2. Cost Inputs'!B28*'2. Cost Inputs'!D28*$B$8 -> 6229.4098 | C20: =B20/$B$8 -> 15.740762
A21: Seawater feedstock | B21: ='2. Cost Inputs'!B20*'2. Cost Inputs'!D20*$B$8 -> 0 | C21: =B21/$B$8 -> 0
A22: Crew | B22: ='2. Cost Inputs'!B31*'2. Cost Inputs'!D31 -> 900000 | C22: =B22/$B$8 -> 2274.1619
A23: Maintenance & insurance | B23: ='2. Cost Inputs'!B53*'2. Cost Inputs'!B35 -> 5093551.4 | C23: =B23/$B$8 -> 12870.622
A24: Vessel energy (hotel + transit) | B24: =(B11+B12)*'2. Cost Inputs'!D26 -> 358920 | C24: =B24/$B$8 -> 906.93575 | D24: (operating days x hotel burn + moving days x underway burn) x diesel price
A25: Total Annual Cost | B25: =SUM(B18:B24) -> 19526858
A26: Levelized Cost per Tonne | C26: =B25/$B$8 -> 49341.373
A28: Stationary vs Moving Vessel
B29: Value | C29: Unit | D29: Notes
A30: Moving vessel: $/tonne of aerosol (tab 3a) | B30: ='3a. Outputs - Dedicated Vessel'!G5 -> 54047.979 | C30: From main model
A31: Stationary vessel: $/tonne of aerosol | B31: =C26 -> 49341.373
A32: Saving vs moving vessel | B32: =B30-B31 -> 4706.6054 | C32: $/tonne
A33: Cost relative to moving vessel | B33: =B31/B30 -> 0.91291801

Sheet 4. Scenario Comparison
A1: 4. Scenario Comparison
A2: All values pulled live from tabs 3a-3d (green fill); nothing is computed here. Sources for each number sit on its home tab.
A4: Levelized cost per tonne of aerosol
A5: Scenario | B5: $/tonne | C5: $/yr | D5: vs dedicated (3a) | E5: Note
A6: 3a. Dedicated vessel | B6: ='3a. Outputs - Dedicated Vessel'!G5 -> 54047.979 | C6: ='3a. Outputs - Dedicated Vessel'!B13 -> 21389498 | D6: anchor | E6: Main model.
A7: 3b. Ship piggyback | B7: ='3b. Outputs - Ship Piggyback'!C32 -> 21674.005 | C7: ='3b. Outputs - Ship Piggyback'!B31 -> 9259921.7 | D7: ='3b. Outputs - Ship Piggyback'!B38 -> 0.40101417 | E7: Rent deck slots; host vessel runs its route.
A8: 3c. Fixed platform | B8: ='3c. Outputs - Fixed Platform'!C33 -> 17656.269 | C8: ='3c. Outputs - Fixed Platform'!B32 -> 6987471.9 | D8: ='3c. Outputs - Fixed Platform'!B40 -> 0.32667769 | E8: Moored buoy / jack-up; shore power.
A9: 3d. Stationary vessel | B9: ='3d. Outputs - Stationary Vessel'!C26 -> 49341.373 | C9: ='3d. Outputs - Stationary Vessel'!B25 -> 19526858 | D9: ='3d. Outputs - Stationary Vessel'!B33 -> 0.91291801 | E9: Steam out and back once; holds station.

Sheet 5a. Cooling Model - Local
A1: Cost of Cooling: Cost per Unit of Cooling Produced
A2: Converts cost per tonne of aerosol (from the TEA) into cost per unit of cooling, using the particle-size physics below.
A4: Aerosol Delivery | H4: Sources
A5: Survival factor | B5: 0.3 | C5: fraction | D5: Fraction surviving in-plume coagulation/deposition to cloud base. Open research gap (2025 plume review; CS-06 targets it). Range 0.1-0.5. | H5: Hernandez-Jaramillo et al. 2025a, Front. Mar. Sci. 12:1450175, p.1: effectiveness "depends on what fraction of the sea salt aerosols are incorporated into clouds after being emitted"; still an open research gap, so 0.3 is a scenario choice.
A6: Boundary-layer mixing depth | B6: 900 | C6: m | D6: Measured: plumes reached cloud base at 825-900 m across five GBR campaigns (CS-06 Final Report 2025). | H6: CS-06 Final Report 2025, p.2: "plumes consistently reached cloud base heights (800 - 900 metres) under typical trade-wind and low-wind speed doldrum type atmospheric conditions." ERL 2025 abstract: plume detected "just below cloud bases at 700-900 m altitudes".
A7: Cloud susceptibility
A8: Particles per tonne of salt | B8: ='1. Technology Description'!B11 -> 2.6198345e+20 | C8: #/tonne | D8: From tab 1
A9: Background cloud droplet number | B9: 100 | C9: /cm3 | D9: Natural marine background. CS-06 2025 p.34: GBR runs 50-200/cm3, most common ~100. | H9: CS-06 Final Report 2025, pp.25-26: "background CCN concentrations range from approximately 50 to 200 cm-3... The most common value is near 100 cm-3".
A10: Required droplet addition | B10: =(B18-1)*B9 -> 30 | C10: /cm3 | D10: (Droplet-number enhancement - 1) x background: 0.3 x 100 = add 30/cm3 at the 1.3x base. The measured ceiling (CS-06 p.34) is ~200/cm3 total, i.e. at most +100/cm3 (2.0x).
A11: Area per tonne | B11: =B8*B5/(B10*1000000*B6*1000000) -> 2910.9272 | C11: km2/tonne | D11: Particles available / needed per km2. Not applied as a factor: ~9 in 100 windowed arrivals don't activate at 0.5% SS (field-measured, ERL 2025); worse at 0.2% SS.
A12: Critical activation diameter (Köhler threshold) | B12: 50 | C12: nm | D12: Hernandez-Jaramillo 2025 (ERL): ~50 nm activates at 0.5% SS over the GBR; ~73 nm at 0.2% SS (trade-cumulus Hoppel minimum). | H12: ERL 2025, p.9: "a critical diameter of ~ 50 nm at 0.5% supersaturation (SS) and ~73 nm at 0.2% SS" (GBR seawater).
A13: Unused - do not wire (superseded by cloud availability) | B13: 0.43 | C13: fraction | D13: Neutralized 2026-09-09: overlaps cloud availability, same weather gate, would double-count. No formulas reference this input.
A14: Cloud Radiative Effect
B15: Value | C15: Unit | D15: Notes | H15: Sources
A16: Cloud-top shortwave, 24-h mean | B16: 380 | C16: W/m2 | D16: 24-h mean downwelling SW at cloud top, GBR Dec-Apr. 475 was the DJF 24-h mean at the top of the atmosphere (CERES via NASA POWER: 460-491 at three GBR points), not a daytime value. x ~0.8 free-troposphere transmission (Wood 2021) gives ~380. Solar-geometry check, 14-22S, 1 Dec-30 Apr: 442 W/m2 24-h TOA, 376-385 at cloud top. Changed 2026-10 from 475, which was then multiplied by a 0.4 day/night factor in B20, counting the diurnal cycle twice. | H16: Wood 2021, ACP 21:14507 (doi:10.5194/acp-21-14507-2021), Sect. 2.1: day+night-mean irradiance, free-troposphere transmissivity 0.8, no separate diurnal factor. NASA POWER CERES SYN1deg TOA_SW_DWN climatology. Daily-mean insolation computed from solar geometry in review.
A17: Marine cloud albedo | B17: 0.4 | C17: - | D17: Cloud albedo 0.4 (author choice, kept). Stratocumulus decks run ~0.5-0.6 (Wood 2021). GBR summer trade cumulus is lower: 0.1-0.3 domain average (Harrison et al. 2019 T14, pp.64-65), which would cut the Twomey term A(1-A) from 0.24 to 0.09-0.21. | H17: Assumption: literature-typical stratocumulus albedo. Talked with Graham who suggested 0.30 a lower range.
A18: Droplet-number enhancement | B18: 1.3 | C18: x | D18: 1.3x over a 100/cm3 background (+30/cm3). Zhao et al. 2026 GBR modelling: domain-mean droplet increase 1.14-1.73x (central 1.32). Measured ceiling ~200/cm3, i.e. at most 2.0x (CS-06 p.34). Cooling per tonne scales as ln(r)/(r-1), so a higher ratio lowers cooling per tonne.
A19: Local forcing under brightened cloud | B19: =B16*B17*(1-B17)*(1/3)*LN(B18) -> 7.9758736 | C19: W/m2 | D19: Twomey: Fsw x Ac x (1-Ac) x (1/3) x ln(Nd ratio)
A20: Diurnal factor | B20: 1 | D20: 1.0 because B16 is already a 24-h mean. Was 0.4 on top of a 24-h mean, which counted the diurnal cycle twice. If you prefer a daytime B16 (~720-740 W/m2 at cloud top), set this to the daylight fraction, ~0.52 for 14-22S Dec-Apr. | H20: Wood 2021 (doi:10.5194/acp-21-14507-2021): no separate diurnal factor with day+night-mean irradiance. Daylight fraction 0.52 for 14-22S Dec-Apr computed in review.
A21: Cloud availability | B21: 0.2 | D21: CS-01 Final Report 2025, p.11: susceptible low cloud in summer '20% at the north and increases to 55% at the south'. | H21: CS-01 Final Report 2025, p.11: occurrence of susceptible low cloud in summer "is 20% at the north and increases to 55% at the south"
A22: Realization Factor | B22: =B21*B20 -> 0.2 | D22: Diurnal factor (1.0) x cloud availability
A23: Surface energy budget sensitivity
A24: Aerosol lifetime | B24: 3 | C24: days | D24: Boundary-layer residence (uncertain) | H24: Assumption (boundary-layer residence; uncertain).
A25: Local temperature sensitivity | B25: 0.0225 | C25: degC/(W/m2) | D25: Local forcing to local surface cooling. Harrison et al. 2019, RRAP T14 report. | H25: Harrison et al. 2019 (T14), pp.32-33: relationship "approximately linear... with the gradient of 0.225°C per 10 Wm-2 reduction in solar forcing"
A27: From the Aerosol TEA
B28: Value | C28: Unit | D28: Source
A29: Levelized cost of aerosol | B29: ='3a. Outputs - Dedicated Vessel'!G5 -> 54047.979 | C29: $/tonne of aerosol | D29: Headline from the TEA Outputs tab
A31: Cooling Conversion
B32: Value | C32: Unit | D32: Notes / Source
A33: Cooling produced per tonne of aerosol | B33: =(B19*B25*(B11*100)*B24)*B20*B21 -> 31343.203 | C33: degC-ha-days/tonne | D33: local forcing x local temperature sensitivity x area (ha) x lifetime (days) x realization
A34: Cost of cooling produced | B34: =B29/B33 -> 1.7243923 | C34: $/degC-ha-day | D34: Aerosol cost / cooling per tonne

Sheet 5b. Cooling-Value Sensitivity
A1: Cooling-Value Sensitivity: Cost per Unit of Cooling
A2: One-way sensitivity of cost per degC-ha-day to model and cost drivers.
A3: Sensitivity: what Moves the Cost per Unit Cooling
A4: One-way sensitivity of cost per degC-ha-day. Model drivers scale cooling directly (the 3a tornado can't see them); cost drivers pull live from 3a. Survival is the dominant, softest bar. Particle size fixed at 150 nm.
A5: Driver | B5: Downside input | C5: Base | D5: Upside input | E5: at downside ($) | F5: at base ($) | G5: at upside ($) | H5: Swing ($) | I5: Sources | J5: spacer (hidden) | K5: cost-reducing span | L5: cost-raising span | M5: max (label helper) | N5: tail (hidden)
A6: Model: Marine cloud albedo | B6: 0.3 | C6: ='5a. Cooling Model - Local'!$B$17 -> 0.4 | D6: 0.6 | E6: ='5a. Cooling Model - Local'!$B$34*(('5a. Cooling Model - Local'!$B$17*(1-'5a. Cooling Model - Local'!$B$17))/(B6*(1-B6))) -> 1.9707341 | F6: ='5a. Cooling Model - Local'!$B$34 -> 1.7243923 | G6: ='5a. Cooling Model - Local'!$B$34*(('5a. Cooling Model - Local'!$B$17*(1-'5a. Cooling Model - Local'!$B$17))/(D6*(1-D6))) -> 1.7243923 | H6: =MAX(E6,F6,G6)-MIN(E6,F6,G6) -> 0.24634176 | I6: Sensitivity bounds around the tab 5a base cloud albedo; see tab 5a Sources. | J6: =MIN(E6,F6,G6) -> 1.7243923 | K6: =MAX(0,F6-MIN(E6,G6)) -> 0 | L6: =MAX(0,MAX(E6,G6)-F6) -> 0.24634176 | M6: =J6+K6+L6 -> 1.9707341 | N6: =20-MAX(E6:G6) -> 18.029266
A7: Cost: Energy price | B7: ='3a. Outputs - Dedicated Vessel'!B58 -> 0.45 | C7: ='2. Cost Inputs'!D24 -> 0.3 | D7: ='3a. Outputs - Dedicated Vessel'!D58 -> 0.18 | E7: =MAX('3a. Outputs - Dedicated Vessel'!AJ67,'3a. Outputs - Dedicated Vessel'!AJ68)/'5a. Cooling Model - Local'!$B$33 -> 1.869565 | F7: ='5a. Cooling Model - Local'!$B$34 -> 1.7243923 | G7: =MIN('3a. Outputs - Dedicated Vessel'!AJ67,'3a. Outputs - Dedicated Vessel'!AJ68)/'5a. Cooling Model - Local'!$B$33 -> 1.6082542 | H7: =MAX(E7,F7,G7)-MIN(E7,F7,G7) -> 0.26131073 | J7: =MIN(E7,F7,G7) -> 1.6082542 | K7: =MAX(0,F7-MIN(E7,G7)) -> 0.1161381 | L7: =MAX(0,MAX(E7,G7)-F7) -> 0.14517263 | M7: =J7+K7+L7 -> 1.869565 | N7: =20-MAX(E7:G7) -> 18.130435
A8: Cost: Vessel cost | B8: ='3a. Outputs - Dedicated Vessel'!B55 -> 56250000 | C8: ='2. Cost Inputs'!D43 -> 7500000 | D8: ='3a. Outputs - Dedicated Vessel'!D55 -> 22500000 | E8: =MAX('3a. Outputs - Dedicated Vessel'!AJ61,'3a. Outputs - Dedicated Vessel'!AJ62)/'5a. Cooling Model - Local'!$B$33 -> 2.2116686 | F8: ='5a. Cooling Model - Local'!$B$34 -> 1.7243923 | G8: =MIN('3a. Outputs - Dedicated Vessel'!AJ61,'3a. Outputs - Dedicated Vessel'!AJ62)/'5a. Cooling Model - Local'!$B$33 -> 1.3345713 | H8: =MAX(E8,F8,G8)-MIN(E8,F8,G8) -> 0.8770973 | J8: =MIN(E8,F8,G8) -> 1.3345713 | K8: =MAX(0,F8-MIN(E8,G8)) -> 0.38982102 | L8: =MAX(0,MAX(E8,G8)-F8) -> 0.48727628 | M8: =J8+K8+L8 -> 2.2116686 | N8: =20-MAX(E8:G8) -> 17.788331
A9: Cost: Nozzle unit cost | B9: ='3a. Outputs - Dedicated Vessel'!B54 -> 1000 | C9: ='2. Cost Inputs'!D40 -> 100 | D9: ='3a. Outputs - Dedicated Vessel'!D54 -> 10 | E9: =MAX('3a. Outputs - Dedicated Vessel'!AJ59,'3a. Outputs - Dedicated Vessel'!AJ60)/'5a. Cooling Model - Local'!$B$33 -> 1.9386146 | F9: ='5a. Cooling Model - Local'!$B$34 -> 1.7243923 | G9: =MIN('3a. Outputs - Dedicated Vessel'!AJ59,'3a. Outputs - Dedicated Vessel'!AJ60)/'5a. Cooling Model - Local'!$B$33 -> 1.7029701 | H9: =MAX(E9,F9,G9)-MIN(E9,F9,G9) -> 0.23564448 | J9: =MIN(E9,F9,G9) -> 1.7029701 | K9: =MAX(0,F9-MIN(E9,G9)) -> 0.021422225 | L9: =MAX(0,MAX(E9,G9)-F9) -> 0.21422225 | M9: =J9+K9+L9 -> 1.9386146 | N9: =20-MAX(E9:G9) -> 18.061385
A10: Cost: Annual utilization | B10: ='3a. Outputs - Dedicated Vessel'!B53 -> 0.19726027 | C10: =('3a. Outputs - Dedicated Vessel'!$B$18+'3a. Outputs - Dedicated Vessel'!$B$19)*'2. Cost Inputs'!$B$5 -> 0.32876712 | D10: ='3a. Outputs - Dedicated Vessel'!D53 -> 0.42739726 | E10: =MAX('3a. Outputs - Dedicated Vessel'!AJ57,'3a. Outputs - Dedicated Vessel'!AJ58)/'5a. Cooling Model - Local'!$B$33 -> 2.571544 | F10: ='5a. Cooling Model - Local'!$B$34 -> 1.7243923 | G10: =MIN('3a. Outputs - Dedicated Vessel'!AJ57,'3a. Outputs - Dedicated Vessel'!AJ58)/'5a. Cooling Model - Local'!$B$33 -> 1.4311475 | H10: =MAX(E10,F10,G10)-MIN(E10,F10,G10) -> 1.1403964 | J10: =MIN(E10,F10,G10) -> 1.4311475 | K10: =MAX(0,F10-MIN(E10,G10)) -> 0.2932448 | L10: =MAX(0,MAX(E10,G10)-F10) -> 0.84715164 | M10: =J10+K10+L10 -> 2.571544 | N10: =20-MAX(E10:G10) -> 17.428456
A11: Cost: Crew cost | B11: ='3a. Outputs - Dedicated Vessel'!B52 -> 210000 | C11: ='2. Cost Inputs'!D31 -> 150000 | D11: ='3a. Outputs - Dedicated Vessel'!D52 -> 105000 | E11: =MAX('3a. Outputs - Dedicated Vessel'!AJ55,'3a. Outputs - Dedicated Vessel'!AJ56)/'5a. Cooling Model - Local'!$B$33 -> 1.753415 | F11: ='5a. Cooling Model - Local'!$B$34 -> 1.7243923 | G11: =MIN('3a. Outputs - Dedicated Vessel'!AJ55,'3a. Outputs - Dedicated Vessel'!AJ56)/'5a. Cooling Model - Local'!$B$33 -> 1.7026253 | H11: =MAX(E11,F11,G11)-MIN(E11,F11,G11) -> 0.050789746 | J11: =MIN(E11,F11,G11) -> 1.7026253 | K11: =MAX(0,F11-MIN(E11,G11)) -> 0.021767034 | L11: =MAX(0,MAX(E11,G11)-F11) -> 0.029022712 | M11: =J11+K11+L11 -> 1.753415 | N11: =20-MAX(E11:G11) -> 18.246585
A12: Model: Cloud-top shortwave | B12: 340 | C12: ='5a. Cooling Model - Local'!$B$16 -> 380 | D12: 420 | E12: ='5a. Cooling Model - Local'!$B$34*('5a. Cooling Model - Local'!$B$16/B12) -> 1.927262 | F12: ='5a. Cooling Model - Local'!$B$34 -> 1.7243923 | G12: ='5a. Cooling Model - Local'!$B$34*('5a. Cooling Model - Local'!$B$16/D12) -> 1.5601645 | H12: =MAX(E12,F12,G12)-MIN(E12,F12,G12) -> 0.36709753 | I12: Bounds on the 24-h mean cloud-top SW (5a B16 = 380): 340 (the 5c-alt basis) to 420 (DJF TOA 475-491 x 0.85-0.87 transmission). Were 400/550 around the old 475. Changed 2026-10. | J12: =MIN(E12,F12,G12) -> 1.5601645 | K12: =MAX(0,F12-MIN(E12,G12)) -> 0.16422784 | L12: =MAX(0,MAX(E12,G12)-F12) -> 0.20286969 | M12: =J12+K12+L12 -> 1.927262 | N12: =20-MAX(E12:G12) -> 18.072738
A13: Model: Droplet-number enhancement | B13: 1.14 | C13: ='5a. Cooling Model - Local'!$B$18 -> 1.3 | D13: 1.73 | E13: ='5a. Cooling Model - Local'!$B$34*((LN('5a. Cooling Model - Local'!$B$18)/('5a. Cooling Model - Local'!$B$18-1))/(LN(B13)/(B13-1))) -> 1.6113228 | F13: ='5a. Cooling Model - Local'!$B$34 -> 1.7243923 | G13: ='5a. Cooling Model - Local'!$B$34*((LN('5a. Cooling Model - Local'!$B$18)/('5a. Cooling Model - Local'!$B$18-1))/(LN(D13)/(D13-1))) -> 2.0084712 | H13: =MAX(E13,F13,G13)-MIN(E13,F13,G13) -> 0.39714834 | I13: Zhao et al. 2026 GBR range 1.14-1.73x (doi:10.5194/egusphere-2026-1251). Formula includes the area-per-tonne term (5a B11 ~ 1/(r-1)), so cost scales with (r-1)/ln(r). Was 2 and 4 (both above the 1.3 base) with ln(r) only, which showed losses as gains. Changed 2026-10. | J13: =MIN(E13,F13,G13) -> 1.6113228 | K13: =MAX(0,F13-MIN(E13,G13)) -> 0.11306949 | L13: =MAX(0,MAX(E13,G13)-F13) -> 0.28407885 | M13: =J13+K13+L13 -> 2.0084712 | N13: =20-MAX(E13:G13) -> 17.991529
A14: Model: Aerosol lifetime | B14: 2 | C14: ='5a. Cooling Model - Local'!$B$24 -> 3 | D14: 4 | E14: ='5a. Cooling Model - Local'!$B$34*('5a. Cooling Model - Local'!$B$24/B14) -> 2.5865885 | F14: ='5a. Cooling Model - Local'!$B$34 -> 1.7243923 | G14: ='5a. Cooling Model - Local'!$B$34*('5a. Cooling Model - Local'!$B$24/D14) -> 1.2932942 | H14: =MAX(E14,F14,G14)-MIN(E14,F14,G14) -> 1.2932942 | J14: =MIN(E14,F14,G14) -> 1.2932942 | K14: =MAX(0,F14-MIN(E14,G14)) -> 0.43109808 | L14: =MAX(0,MAX(E14,G14)-F14) -> 0.86219617 | M14: =J14+K14+L14 -> 2.5865885 | N14: =20-MAX(E14:G14) -> 17.413412
A15: Model: Temperature sensitivity | B15: 0.015 | C15: ='5a. Cooling Model - Local'!$B$25 -> 0.0225 | D15: 0.032 | E15: ='5a. Cooling Model - Local'!$B$34*('5a. Cooling Model - Local'!$B$25/B15) -> 2.5865885 | F15: ='5a. Cooling Model - Local'!$B$34 -> 1.7243923 | G15: ='5a. Cooling Model - Local'!$B$34*('5a. Cooling Model - Local'!$B$25/D15) -> 1.2124634 | H15: =MAX(E15,F15,G15)-MIN(E15,F15,G15) -> 1.3741251 | J15: =MIN(E15,F15,G15) -> 1.2124634 | K15: =MAX(0,F15-MIN(E15,G15)) -> 0.51192897 | L15: =MAX(0,MAX(E15,G15)-F15) -> 0.86219617 | M15: =J15+K15+L15 -> 2.5865885 | N15: =20-MAX(E15:G15) -> 17.413412
A16: Model: Cooling realization factor | B16: =0.5*C16 -> 0.1 | C16: ='5a. Cooling Model - Local'!$B$22 -> 0.2 | D16: =2*C16 -> 0.4 | E16: ='5a. Cooling Model - Local'!$B$34*('5a. Cooling Model - Local'!$B$22/B16) -> 3.4487847 | F16: ='5a. Cooling Model - Local'!$B$34 -> 1.7243923 | G16: ='5a. Cooling Model - Local'!$B$34*('5a. Cooling Model - Local'!$B$22/D16) -> 0.86219617 | H16: =MAX(E16,F16,G16)-MIN(E16,F16,G16) -> 2.5865885 | J16: =MIN(E16,F16,G16) -> 0.86219617 | K16: =MAX(0,F16-MIN(E16,G16)) -> 0.86219617 | L16: =MAX(0,MAX(E16,G16)-F16) -> 1.7243923 | M16: =J16+K16+L16 -> 3.4487847 | N16: =20-MAX(E16:G16) -> 16.551215
A17: Model: Survival factor | B17: 0.1 | C17: ='5a. Cooling Model - Local'!$B$5 -> 0.3 | D17: 0.5 | E17: ='5a. Cooling Model - Local'!$B$34*('5a. Cooling Model - Local'!$B$5/B17) -> 5.173177 | F17: ='5a. Cooling Model - Local'!$B$34 -> 1.7243923 | G17: ='5a. Cooling Model - Local'!$B$34*('5a. Cooling Model - Local'!$B$5/D17) -> 1.0346354 | H17: =MAX(E17,F17,G17)-MIN(E17,F17,G17) -> 4.1385416 | J17: =MIN(E17,F17,G17) -> 1.0346354 | K17: =MAX(0,F17-MIN(E17,G17)) -> 0.68975693 | L17: =MAX(0,MAX(E17,G17)-F17) -> 3.4487847 | M17: =J17+K17+L17 -> 5.173177 | N17: =20-MAX(E17:G17) -> 14.826823
A18: Model: W/m2 brightening | B18: =C18*0.5 -> 3.9879368 | C18: ='5a. Cooling Model - Local'!B19 -> 7.9758736 | D18: =C18*2 -> 15.951747

Sheet 5c. Benefit - Local - Reef
A1: Local Benefits: Reef-Wide Brightening (Reef Cooling)
A2: Reef-wide deployment on a chartered seasonal fleet: pay only for the bleaching season. Same-day cooling credit only, no persistence or fleet-mobility bonus. Harrison 2019 below as optimistic gut check.
A3: Local on-target delivery factor | B3: 0.5 | C3: fraction | D3: Fraction of sprayed cooling reaching target reef waters (rest drifts off). Same factor on tab 5d. | G3: Assumption (same factor as 5d).
A4: Our Calculation - Deployment and Cost (Chartered Fleet)
A5: Input | B5: Value | C5: Unit | D5: Source / basis | G5: Sources
A6: Reef area cooled | B6: 30000 | C6: km2 | D6: GBR shallow-reef area, ~3 million ha. Reef-wide domain per Harrison et al. 2019. | G6: Harrison et al. 2019 (T14) reef-wide domain; GBR shallow-reef area ~3 million ha.
A7: Marine heatwave duration | B7: 151 | C7: days | D7: ≈ Harrison's Dec 1 - Apr 30 stress window (151 days ≈ 21.6 weeks). Matches the Zhao tab. Replaces the made-up 12 weeks. | G7: Harrison et al. 2019 (T14), p.39: forcing "accumulated over the entire summer from 1 December to 30 April" (151 days = 21.6 weeks).
A8: Peak per-cloud shortwave reduction | B8: ='5a. Cooling Model - Local'!B19/'5a. Cooling Model - Local'!B16 -> 0.020989141 | C8: fraction | D8: Tab-5a nozzle physics. Per-cloud peak exceeds the reef-wide average under either accounting.
A9: Event-average forcing, our accounting | B9: ='5a. Cooling Model - Local'!B19*'5a. Cooling Model - Local'!B22 -> 1.5951747 | C9: W/m2 | D9: Tab-5a peak x realization factor (daylight x seedable-cloud availability). Same-day credit only.
A10: Bleaching-stress relief implied | B10: =B26*(B9/B35) -> 0.041329527 | C10: fraction | D10: Adopted Harrison relief scaled by dose ratio (our event-average forcing / Harrison anchor forcing). Assumes relief ~linear in dose; only modest extrapolation.
A11: Coverage per tonne | B11: ='5a. Cooling Model - Local'!B11 -> 2910.9272 | C11: km2/tonne | D11: Tab 5a area-per-tonne derivation.
A12: Tonnes per heatwave | B12: =(B6/'5a. Cooling Model - Local'!B11)*(B7/'5a. Cooling Model - Local'!B24)/$B$3 -> 1037.4701 | C12: tonnes | D12: Area / coverage per tonne x 3-day cycles over the heatwave / delivery factor. First-principles event tonnage.
A13: Per-vessel output during event | B13: ='2. Cost Inputs'!$B$15*(B7/365)*'5c-alt. Benefit - Reef (Zhao)'!$B$27 -> 425.77774 | C13: tonnes | D13: Equipment-basis annual production (tab 2 B15, includes 90% availability) x event fraction x 95% spray time within the event (same as 5c-alt B27). Changed 2026-10: was 3a B22 x event fraction, but 3a B22 already carries the dedicated vessel's 33% year-round spray share, so the season was counted twice (6.3 vessels instead of ~2.4).
A14: Vessels required for the event | B14: =B12/B13 -> 2.4366472 | C14: vessels | D14: Event tonnage / per-vessel event output.
A15: Charter rate (bareboat: hull + crew) | B15: ='2. Cost Inputs'!B56/7 -> 21428.571 | C15: $/vessel/day | D15: Tab 2 B56 (weekly) / 7. Hull and crew only; mounted gear is row 22.
A16: Season charter cost | B16: =B14*B7*B15 -> 7884294.1 | C16: $ | D16: Vessels x days x rate.
A17: Temporary mounting & removal | B17: =B14*'3b. Outputs - Ship Piggyback'!B5*2 -> 487329.43 | C17: $ | D17: Tab-3b containerized mounting per vessel, install + removal.
A18: Vessel fuel | B18: =B14*B7*('2. Cost Inputs'!B25+'2. Cost Inputs'!B26)*'2. Cost Inputs'!D25 -> 6192324.6 | D18: Vessels x days x fuel usage (propulsion + hotel) x price
A19: Seasonal operating (spray energy + technicians) | B19: =B12*'2. Cost Inputs'!B24*'2. Cost Inputs'!D24+B14*'3b. Outputs - Ship Piggyback'!B7*(B7/365) -> 9622788.5 | C19: $ | D19: Spray energy + one technician per vessel for the season. Charter includes crew and hull.
A20: Cost per heatwave (chartered, incl. row 22) | B20: =SUM(B16:B19)+B22 -> 25878491 | C20: $ | D20: Pay only for the season: bareboat charter + mounting + fuel + operating + the mounted spray train's capital share (row 22).
A21: Cost per hectare | B21: =B20/(B6*100) -> 8.6261637 | C21: $/ha | D21: Linear in area; same $/ha at any scale.
A22: Mounted spray-train capital (event share) | B22: =B14*B7*'2. Cost Inputs'!B58 -> 1691754.6 | C22: $ | D22: Vessels x days x tab 2 B58 (nozzles, compressors, skid, amortized per vessel-day). Included in row 20.
A23: Reef ROI
A24: Bleaching-stress relief, 2015/16 event | B24: 0.5 | C24: fraction | D24: Harrison et al. 2019, modeled. | G24: Harrison et al. 2019 (T14), p.57: "an average reduction in bleaching stress of ~50 percent in 2015/2016".
A25: Bleaching-stress relief, 2016/17 event | B25: 0.65 | C25: fraction | D25: Harrison et al. 2019, modeled. | G25: Harrison et al. 2019 (T14), p.57: "~65 percent in 2016/2017"
A26: Adopted relief (Harrison) | B26: 0.57 | C26: fraction | D26: Average of the two events. Review 2026-10, not changed: 0.57 is relief on the T14 stress metric. On degree heating weeks, which predict mortality, the same 14 T14 reefs give ~0.45, and coral loss is a threshold function of DHW (Hughes et al. 2018, Nature 556:492, doi:10.1038/s41586-018-0041-2), so the linear scaling of relief into dollars in B10 is not supported. | E26: Calculated: average of the two T14 events (0.5, 0.65).
A27: Reef total asset value | B27: =B31*'2. Cost Inputs'!B8 -> 66.5 | C27: $ billion (USD) | D27: Deloitte Access Economics 2025 'At What Cost?': A$95B GBR valuation at 0.7 USD/AUD.
A28: Value at risk in a severe bleaching event | B28: =B27*10^9*B32 -> 13300000000 | C28: $ | D28: Reef asset value x ~20% at risk in a severe bleaching event. A$95B already blends present + future value; no further discounting.
A29: Value protected | B29: =B28*B10 -> 5.4968271e+08 | C29: $ | D29: Value at risk x implied relief.
A30: ROI: value protected per dollar spent | B30: =B29/B20 -> 21.24091 | C30: x | D30: Per heatwave event, on the chartered-fleet cost. Same-day accounting.
A31: GBR asset valuation (Deloitte Access Economics 2025) | B31: 95 | C31: A$ billion | D31: Deloitte 'At What Cost?' 2025. Converted at tab 2 B8. Until 10/07 typed inside B27.
A32: Share of reef value at risk in a severe bleaching event | B32: 0.2 | C32: fraction | D32: Assumption (~20%). Until 10/07 typed inside B28. Review 2026-10, not changed: no study maps coral-cover loss to asset value. The 2024 event cut regional hard-coral cover 14-30% (AIMS 2025). Severe events have run ~0.6/yr since 2016 (6 in 10 summers), and 20% of the stock per event at that rate would exhaust it in ~8 years, so 20% per event likely overstates value at risk. Deloitte valued the reef at A$56B in 2017.
A33: Gut Check - Harrison et al. 2019 (Published Coupled Model)
A34: Harrison 2019 coupled-model gut check. Credits two effects we exclude: multi-day persistence and a mobile fleet chasing susceptible clouds.
A35: Event-average forcing achieved (Harrison) | B35: 22 | C35: W/m2 | D35: Coupled-model result: ~6.8% reef-wide dimming. RRAP conversion: 5 W/m2 ~ 1.5% reef-wide. | E35: Harrison et al. 2019 (T14), p.57: "reduction of around 6.7 percent of incoming shortwave solar radiation over the latitudinal extent of the Reef". File held.
A36: Deployment scope | B36: Reef-wide fleet | C36: - | D36: Mobile fleet; vessels brighten clouds wherever conditions suit.
A37: Dose ratio (ours / his) | B37: =B9/B35 -> 0.072507942 | C37: fraction | D37: This-deployment forcing / Harrison anchor forcing.
A38: Value protected if his assumptions held | B38: =B28*B26 -> 7581000000 | C38: $ | D38: Value at risk x Harrison adopted relief.
A39: ROI if his assumptions held | B39: =B38/B20 -> 292.94598 | C39: x | D39: Optimistic end of bracket; requires Harrison persistence + mobility assumptions, on the same chartered cost.
A40: =CONCATENATE("Bracket: ",TEXT(B30,"0.0"),"x under our same-day accounting to ",TEXT(B39,"0.0"),"x if Harrison persistence and mobility assumptions hold - both priced on the chartered fleet.") -> Bracket: 21.2x under our same-day accounting to 292.9x if Harrison persistence and mobility assumptions hold - both priced on the chartered fleet.

Sheet 5c-alt. Benefit - Reef (Zhao)
A1: Alternative reef scenario: Zhao 2026 preprint
A2: Input / step | B2: Value | C2: Source cell
A3: Delivery rate (particles/s per W/m2) | B3: =B9/B17 -> 3.2679739e+17
D5: Sources
A6: Station count | B6: 75 | C6: Zhao preprint | D6: Zhao et al. 2026 preprint (doi:10.5194/egusphere-2026-1251), p.6: "75 source points" (EXP20).
A7: Station spacing (km) | B7: 20 | C7: Zhao preprint | D7: Zhao et al. 2026, p.6: source points "distributed at a fine spatial spacing of 20 km".
A8: Emission per station (particles/s) | B8: 1e+16 | C8: Zhao preprint | D8: Zhao et al. 2026, p.6: "aerosol flux of the 1x10^16 particles per second... at each of 75 source points"
A9: Total emission (particles/s) | B9: =B6*B8 -> 7.5e+17
A10: Spray footprint (km2) | B10: =B6*B7^2 -> 30000
A12: Event season length (days), Harrison's window | B12: 151 | C12: T14 report text | D12: Harrison et al. 2019 (T14), p.39: summer window "from 1 December to 30 April" = 151 days.
A13: Zhao's albedo increase (absolute) | B13: =ROUND(0.51-0.48,3) -> 0.03 | C13: Zhao Fig. 8e: CTRL 0.48, EXP20 0.51; '+6.2%' is the relative label. 340 x 0.03 = 10.2 W/m2. | D13: Zhao et al. 2026, Fig. 8e: CTRL 0.48 vs EXP20 0.51 albedo.
A14: Cloud-top shortwave, 24-h average (W/m2) | B14: 340 | D14: Assumption (24-h mean cloud-top shortwave, GBR summer)
A15: Forcing where it works (W/m2) | B15: =B13*B14 -> 10.2
A16: Cloud availability | B16: 0.225 | C16: T14 D0.0676 | D16: Harrison et al. 2019 (T14), scenario D0.0676 basis
A17: Forcing target (W/m2) | B17: =B15*B16 -> 2.295
A19: Harrison SST response (°C per W/m2) | B19: ='5a. Cooling Model - Local'!B25 -> 0.0225 | C19: live: tab 5a (T14 Fig 15)
A20: Cooling (°C) | B20: =B17*B19 -> 0.0516375
A23: One nozzle's output (particles/s) | B23: ='1. Technology Description'!B8 -> 1730000000000 | C23: live: tab 1
A24: In-window fraction | B24: ='1. Technology Description'!B9 -> 0.71 | C24: live: tab 1
A25: Nozzle array per vessel | B25: =$B$8/(B23*B24) -> 8141.3336
A26: Equipment availability | B26: ='2. Cost Inputs'!B5 -> 0.9 | C26: live: tab 2
A27: Spray-time fraction | B27: 0.95 | D27: Assumption (spray uptime within events).
A28: Per-vessel continuous-equivalent (particles/s) | B28: =$B$8*B26*B27 -> 8.55e+15
A29: Season particle count | B29: =B17*B3*B12*86400 -> 9.7848e+24
A30: Per-vessel season particles | B30: =B28*B12*86400 -> 1.1154672e+23
A31: Vessels needed | B31: =B29/B30 -> 87.719298
A32: Fleet identity | B32: =IF(ABS(B31*B30/B29-1)<0.001,"MATCH","MISMATCH") -> MATCH
A34: Power per nozzle (W) | B34: ='1. Technology Description'!B17 -> 512 | C34: live: tab 1
A35: Spray power per vessel (kW) | B35: =B25*B34/1000 -> 4168.3628
A36: Charter rate ($/vessel/day) | B36: ='5c. Benefit - Local - Reef'!B15 -> 21428.571 | C36: live: tab 5c
A37: Weeks in the season | B37: =B12/7 -> 21.571429
A38: Temporary mounting & removal ($/vessel) | B38: ='3b. Outputs - Ship Piggyback'!B5*2 -> 200000 | C38: live: tab 3b (same as tab 5c)
A39: Season charter cost, fleet ($) | B39: =B31*B12*B36 -> 2.8383459e+08
A40: Mounting & removal, fleet ($) | B40: =B31*B38 -> 17543860
A41: Spray-hours per vessel per event | B41: =B12*24*B27*B26 -> 3098.52
A42: Electricity price ($/kWh) | B42: ='2. Cost Inputs'!D24 -> 0.3 | C42: live: tab 2
A43: Spray energy cost, fleet | B43: =B31*B35*B41*B42 -> 3.398883e+08
A44: Technician cost ($/vessel-year) | B44: ='3b. Outputs - Ship Piggyback'!B7 -> 180000 | C44: live: tab 3b
A45: Technician cost, fleet | B45: =B31*B44*((B12/7)/52) -> 6550028.9
A46: Total season cost of chartering and running the fleet (incl. row 47) | B46: =B39+B40+B43+B45+B47 -> 7.0871994e+08
A47: Mounted spray-train capital, fleet ($) | B47: =B31*B12*'2. Cost Inputs'!B58 -> 60903164 | C47: live: tab 2
A48: Harrison anchor forcing (W/m2) | B48: ='5c. Benefit - Local - Reef'!B35 -> 22 | C48: live: tab 5c
A49: Harrison relief at anchor | B49: ='5c. Benefit - Local - Reef'!B26 -> 0.57 | C49: live: tab 5c
A50: Value at risk ($) | B50: ='5c. Benefit - Local - Reef'!B28 -> 13300000000 | C50: live: tab 5c
A51: Relief (fraction of damage averted) | B51: =B17/B48*B49 -> 0.059461364
A52: Damage averted ($) | B52: =B51*B50 -> 7.9083614e+08
A54: Implied price of 10^16 particles ($) | B54: =B46/B29*10^16 -> 0.72430703
A55: ROI | B55: =B52/B46 -> 1.1158655

Sheet 5d. Benefit - Local - City
A1: Local Benefits: Heat-Death Reduction (City Cooling)
A2: Same cooling model as 5c; here a degree buys lives, not bleaching relief. Chartered seasonal fleet. Order-of-magnitude only.
A3: Local on-target delivery factor (applies to both profiles) | B3: 0.5 | C3: fraction | D3: Fraction of sprayed cooling that reaches the target city (rest drifts off). Same factor on tab 5c. | G3: Assumption (same factor as 5c).
A4: Our Calculation - Deployment and Cost (Chartered Fleet)
A5: Heat mortality +5.7% per 1C above threshold (RR 1.057, 326-city study). European heat plans bound the deliverable benefit (~25% reduction).
A6: Input | B6: Value | C6: Unit | D6: Source / basis | G6: Sources
A7: City area to cool | B7: 50000 | C7: hectares | D7: A large metro core (500 km2). | G7: Assumption (large metro core; 50,000 ha = 500 km2).
A8: Cooling under brightened cloud (24-h mean, from 5a) | B8: ='5a. Cooling Model - Local'!B19*'5a. Cooling Model - Local'!B25 -> 0.17945716 | C8: degC | D8: 5a local forcing (24-h mean) x 5a temperature sensitivity (Harrison 2019 T14, 0.0225 degC per W/m2). Changed 2026-10: was a typed 0.8 degC "peak" with no source; the 5a chain gives ~0.18 degC. | G8: Tab 5a chain (Harrison et al. 2019 T14 sensitivity).
A9: Extreme-heat days per year | B9: 14 | C9: days | D9: Average heatwave days (~13.7/yr in 2010s globally). | G9: Assumption (~14 days). Review 2026-10: the "13.7 heatwave days/yr" citation had no source. The P95 definition in Kephart et al. 2022 implies ~18 days/yr.
A10: Coverage per tonne | B10: ='5a. Cooling Model - Local'!B11 -> 2910.9272 | C10: km2/tonne | D10: Tab 5a area-per-tonne derivation.
A11: Tonnes per season | B11: =(B7/100/B10)*(B9/'5a. Cooling Model - Local'!B24)/$B$3 -> 1.6031547 | C11: tonnes | D11: Area / coverage per tonne x 3-day aerosol cycles over the heat days / delivery factor.
A12: Per-vessel output during season | B12: ='2. Cost Inputs'!$B$15*(B9/365)*'5c-alt. Benefit - Reef (Zhao)'!$B$27 -> 39.476082 | C12: tonnes | D12: Equipment-basis annual production (tab 2 B15) x season fraction x 95% in-event spray time (5c-alt B27). Changed 2026-10: was 3a B22 (already x 33% year-round spray share) x season fraction.
A13: Vessels required for the season | B13: =MAX(1,ROUNDUP(B11/B12,0)) -> 1 | C13: vessels | D13: Whole vessels, at least one, chartered for the heat days. Changed 2026-10: was a fraction (0.106 of a vessel for 14 days). Heat days are not known in advance, so a standby charter for the whole hot season would cost several times more.
A14: Charter rate, bareboat workboat class | B14: ='2. Cost Inputs'!B56 -> 150000 | C14: $/vessel/week | D14: Pulled from tab 2 B56. Hull and crew only; mounted gear is row 20. | G14: Assumption: no market quote
A15: Season charter cost | B15: =B13*(B9/7)*B14 -> 300000 | C15: $ | D15: Vessels x weeks of extreme heat x rate.
A16: Temporary mounting & removal | B16: =B13*'3b. Outputs - Ship Piggyback'!B5*2 -> 200000 | C16: $ | D16: Tab-3b containerized mounting per vessel, install + removal.
A17: Seasonal operating (spray energy + technicians) | B17: =B11*'2. Cost Inputs'!B24*'2. Cost Inputs'!D24+B13*'3b. Outputs - Ship Piggyback'!B7*(B9/365) -> 21493.379 | C17: $ | D17: Spray energy + one technician per vessel for the season. Charter includes crew and hull.
A18: Cost per season (chartered, incl. row 20) | B18: =SUM(B15:B17)+B20 -> 585865.2 | C18: $ | D18: Pay only for the season: charter + mounting + seasonal operating. Same chartered-fleet frame as 5c.
A19: Cost per hectare | B19: =B18/B7 -> 11.717304 | C19: $/ha | D19: Linear in area; same $/ha at any scale.
A20: Mounted spray-train capital (season share) | B20: =B13*B9*'2. Cost Inputs'!B58 -> 64371.821 | C20: $ | D20: Vessels x heat days x tab 2 B58. Included in row 18. Until 10/07 the city fleet carried no spray-train capital at all.
A21: City ROI
A22: City population | B22: 2000000 | C22: people | D22: A mid-large city. | G22: Assumption (mid-large city).
A23: Baseline heat deaths / extreme season | B23: 200 | C23: deaths | D23: Excess deaths in the city during the dangerous season, pre-intervention. | G23: Assumption (200 excess deaths). Review 2026-10: published heat burdens for a 2M city give ~63-205, central ~100-137: Kephart et al. 2022 heat excess-death fraction 0.67% -> ~101; Zhao et al. 2021 (Lancet Planet. Health, doi:10.1016/S2542-5196(21)00081-4) 0.91% -> ~137; Gasparrini et al. 2015 (Lancet) -> ~63. 200 is at the top of the range.
A24: Mortality rise per degC | B24: 0.057 | C24: per degC | D24: RR 1.057 per 1C above threshold (326-city study). | G24: Kephart et al. 2022, Nat. Med. 28:1700-1705 (doi:10.1038/s41591-022-01872-6): RR 1.057 (95% CI 1.046-1.067) per 1 degC of daily mean above the city P95, 326 Latin American cities.
A25: Daily-mean realized cooling (RR basis) | B25: =B8*'5a. Cooling Model - Local'!B21 -> 0.035891431 | C25: degC | D25: 24-h mean cooling under brightened cloud x cloud availability (5a B21). The 5a forcing is a 24-h mean, so no peak-to-mean conversion (B30) is needed. Changed 2026-10: was 0.8 x 0.44 with no cloud availability.
A26: Deaths averted per season | B26: =B40*(1-1/(1+B24)^B25) -> 1.5487356 | C26: deaths | D26: All deaths on the heat days (B40) x mortality reduction at the realized daily-mean cooling. The RR is per degC on all-cause deaths, so it multiplies every death that day, not only the excess. Changed 2026-10: was applied to the 200 excess deaths only (conservative), and the old note said cloud availability was already inside 5a, which was not true for this tab.
A27: Value of a statistical life | B27: 10000000 | C27: $/life | D27: Assumption: US federal range. | G27: Assumption (US-federal-range VSL). Review 2026-10: EPA central $7.4M (2006$, updated to analysis year); DOT $13.2M (2023$). Fits US cities only; income-adjusted values for lower-income cities are far lower (Viscusi & Masterman 2017, doi:10.1017/bca.2017.12).
A28: Value protected | B28: =B26*B27 -> 15487356 | C28: $ | D28: Deaths averted x statistical-life value.
A29: ROI: value protected per dollar spent | B29: =B28/B18 -> 26.435017 | C29: x | D29: Per extreme-heat season, on the chartered-fleet cost.
A30: Peak to daily-mean conversion | B30: 0.44 | C30: fraction | D30: Not used since 2026-10: the 5a forcing is now a 24-h mean, so the 5a chain already gives a daily-mean dose. Kept for reference. Until 10/07 typed inside B25.
A31: Gut Check - Comparison Anchors
A32: No published targeted city cooling by MCB; first-of-kind profile. Two anchors bracket below: urban cooling economics; geoengineering epidemiology.
A33: Input | B33: Value | C33: Unit | D33: Source / basis
A34: Urban passive cooling, benefit-cost range | B34: 1.5 - 15.2 | C34: $ per $1 | D34: Estrada et al. 2017 (1,692 cities), via World Bank Cool Cities primer. Net benefit per $1 of passive cooling. | G34: Estrada et al. 2017, Nat. Clim. Change 7:403-406, p.2: Policy B BCR &quot;ranging from US$6.00 without GCC to US$15.24 under RCP8.5&quot;; Policy D &quot;between US$1.59 and US$3.96&quot;. Via World Bank Cool Cities primer. Primer link: https://openknowledge.worldbank.org/handle/10986/34218
A35: Solar geoengineering mortality benefit:risk | B35: 13 | C35: x | D35: Harding, Keith, Vecchi & Yang 2024 (PNAS): stratospheric sulfate, mortality benefits vs risks. Only other published cooling-for-lives number. | G35: Harding, Vecchi, Yang & Keith 2024, PNAS 121(52):e2401801121 (doi:10.1073/pnas.2401801121). Review 2026-10: 13x is mortality benefit vs risk for stratospheric sulfate (61% probability), not benefit vs cost, and not MCB.
A36: This profile, benefit-cost at $10M statistical life | B36: =B29 -> 26.435017 | C36: x | D36: Benefit-cost at $10M per statistical life, on the daily-mean realized dose and the chartered cost.
A37: ="This profile ("&TEXT(B29,"0.0")&"x on the daily-mean realized dose, whole-vessel charter) compares with 1.5-15.2x for urban passive cooling (Estrada et al. 2017). The 13x geoengineering anchor is benefit vs risk, not benefit vs cost, so it is not a like-for-like comparison." -> This profile (26.4x on the daily-mean realized dose, whole-vessel charter) compares with 1.5-15.2x for urban passive cooling (Estrada et al. 2017). The 13x geoengineering anchor is benefit vs risk, not benefit vs cost, so it is not a like-for-like comparison.
A39: Crude death rate (added 2026-10) | B39: 7.55 | C39: per 1,000 per yr | D39: Converts population to all-cause deaths on heat days for the RR in B26. City age structure can move this +/-50%. | G39: World Bank WDI, Death rate, crude (SP.DYN.CDRT.IN), World 2024: 7.55 per 1,000.
A40: All-cause deaths on heat days | B40: =B22*B39/1000*B9/365+B23 -> 779.17808 | C40: deaths | D40: Expected deaths on the heat days at the baseline rate, plus the heat excess in B23. B26 applies the RR to this.

Sheet 6a. Cooling Model - Global
A1: Global Cooling Model: Tonnage to Cooling via Earth-System Models
A2: Tonnes of sea salt per year into global cooling, via published regional simulations from three ESMs seeding real ocean regions. Includes cloud adjustments and feedbacks the bottom-up model omits.
A3: Basis conversion: CESM2/E3SMv2 emit 94.2 nm, UKESM1 171.8 nm volume-mean diameter (Hirasawa 2026 preprint, Table 1; the J. Climate text rounds these to 90/172 nm). Restate tonnages at our 150 nm by (d_ours/d_model)^3 x (model CCN fraction / our CCN fraction), both CCN fractions taken as the share activating at 0.1% supersaturation, so we match cloud droplets, not raw particle counts. Then gross up for near-source plume loss; ESMs emit diffuse fluxes, ours is a point source. Assumes (1) forcing is mostly cloud forcing, roughly true for CESM2 (direct scattering is ~40% of forcing in E3SMv2 and ~59% in UKESM1 at -2 W/m2, Hirasawa preprint Table 2), and (2) our 150 nm and the models' 94/172 nm particles stay airborne equally long.
A4: A. Published region-to-global conversion
A5: Hirasawa et al. 2026, J. Climate 39(2): 14 regions, 3 models, equal-forcing emissions. Midlatitude oceans beat the classic subtropical stratocumulus trio in all three models: stronger forcing per ton, better feedbacks, no remote warming patches.
A6: Strategy | B6: Model | C6: Emission (Tg/yr) | D6: Global cooling (K) | E6: Efficiency (K per Tg/yr) | G6: Notes
A7: Subtropical (3 regions) | B7: CESM2 | C7: 7.5 | D7: -1.042 | E7: -0.14 | G7: Optimistic end. CESM2 sits at the upper end of CMIP6 aerosol-cloud forcing.
A8: Subtropical (3 regions) | B8: E3SMv2 | C8: 49.5 | D8: -1.145 | E8: -0.0231 | G8: Middle of the envelope.
A9: Subtropical (3 regions) | B9: UKESM1.0 | C9: 150 | D9: -1.134 | E9: -0.00756 | G9: Pessimistic end. Emits 172nm particles, closest to our 150nm design point.
A10: Midlatitude (5 regions) | B10: CESM2 | C10: 12.5 | D10: -2.948 | E10: -0.231 | G10: Strongest efficiency in the study. Hirasawa et al. 2026 J. Climate reports 0.231 K per Tg/yr; D10/C10 rounds to 0.236. Changed 2026-10 from a typed 0.236.
A11: Midlatitude (5 regions) | B11: E3SMv2 | C11: 82.5 | D11: -3.065 | E11: -0.0372
A12: Midlatitude (5 regions) | B12: UKESM1.0 | C12: 250 | D12: -1.886 | E12: -0.00754
A13: Midlatitude (5 regions) | B13: CESM2-Ghosh | C13: =C10 -> 12.5 | D13: =E10*C13*(3.34/2.62) -> -3.6810115 | E13: =D13/C13 -> -0.29448092 | G13: Scaled from CESM2 (E10 x C13) by the equal-tonnage forcing ratio at 30 Tg/yr: ERFtot -3.34 (CESM2-Ghosh) vs -2.62 W/m2 (CESM2), 1.27x (Hirasawa 2026 preprint, Table 2). Was 12.9/7.21 = 1.79x, the equal-forcing mass ratio, which overstates the gain at fixed tonnage because ERFaci is log-shaped. Table 2 is a subtropical experiment, applied here to midlatitude seeding. Same model and particles, newer activation scheme (Ghosh et al. 2025, GMD 18:4899). Cooling is scaled, not a simulated run. Changed 2026-10.
A14: B. The 20-30x climate model spread
A15: Models disagree ~order-of-magnitude on tons for equal forcing (2.5 vs 50 Tg/yr per region). Part cloud susceptibility, part particle size: count per ton scales 1/d^3.
A16: CESM2 emitted size | B16: 94.2 | C16: nm | D16: 0.157 | E16: CCN fraction | G16: CCN fraction at S=0.1%: Hirasawa 2026 preprint, Table 1. Size: volume-mean diameter 94.2 nm (2 x iSSA volume radius, same Table 1), the right basis for particles per tonne. Was 90 nm, closer to a count median. Changed 2026-10.
A17: CESM2-Ghosh emitted size | B17: 94.2 | C17: nm | D17: 0.157 | E17: CCN fraction | G17: CCN fraction at S=0.1%: Hirasawa 2026 preprint, Table 1. Size: volume-mean diameter 94.2 nm (2 x iSSA volume radius, same Table 1), the right basis for particles per tonne. Was 90 nm, closer to a count median. Changed 2026-10.
A18: E3SMv2 emitted size | B18: 94.2 | C18: nm | D18: 0.131 | E18: CCN fraction | G18: CCN fraction at S=0.1%: Hirasawa 2026 preprint, Table 1. Size: volume-mean diameter 94.2 nm (2 x iSSA volume radius, same Table 1), the right basis for particles per tonne. Was 90 nm, closer to a count median. Changed 2026-10.
A19: UKESM1.0 emitted size | B19: 171.8 | C19: nm | D19: 0.805 | E19: CCN fraction | G19: CCN fraction at S=0.1%: Hirasawa 2026 preprint, Table 1. Size: volume-mean diameter 171.8 nm (2 x iSSA volume radius). Was 172. Changed 2026-10.
A20: Our design point | B20: ='1. Technology Description'!B10 -> 150 | C20: nm | D20: 0.22 | E20: CCN fraction (activated at S=0.1%, estimate) | G20: Estimate, review 2026-10. Same definition as D16:D19: share of particles that activate at 0.1% supersaturation. Hirasawa 2026 preprint Table 1 back-solves to a dry cutoff of ~108.5 nm across CESM2/E3SMv2/UKESM1. Fitting a lognormal to our nozzle: (a) 71% in 30-1000 nm and 150 nm volume-mean gives sigma_g 2.38, CMD 48.5 nm, 18% above 108.5 nm; (b) 40 nm count mode (CS-06 p.24) and 150 nm volume-mean gives sigma_g 2.07, CMD 67.9 nm, 26%. 0.22 is the midpoint. Was 0.71 (tab 1 B9), the share in the 30-1000 nm production window, which is a looser size cut than the models use.
A22: C. Bottom up gut check
A23: Our bottom-up chain implies a global forcing per Tg/yr. Compare with each model's per-region efficiency (about -0.6 W/m2 per region at nominal):
A24: Our forcing per Tg/yr (delivery- and activation-adjusted) | B24: =('5a. Cooling Model - Local'!B19*'5a. Cooling Model - Local'!B11*10^6/(5.1*10^14)*('5a. Cooling Model - Local'!B24/365)*10^6)*'5a. Cooling Model - Local'!B22 -> 0.074833803 | C24: ESM restated at our basis | G24: Local forcing x area / Earth area x lifetime. Now includes the realization factor, so apples-to-apples with the published all-weather efficiencies.
A25: CESM2 implied forcing efficiency | B25: 0.24 | C25: =B25*($B$16/$B$20)^3*$D$20/D16 -> 0.083293901 | D25: x (d_model/d_ours)^3 x (our CCN fraction / model CCN fraction): a tonne of 94.2 nm holds (150/94.2)^3 = 4.0x more particles than 150 nm, and 15.7% of CESM2's activate at 0.1% S vs ~22% of ours.
A26: E3SMv2 implied forcing efficiency | B26: 0.0364 | C26: =B26*($B$18/$B$20)^3*$D$20/D18 -> 0.015140203
A27: UKESM1.0 implied forcing efficiency | B27: 0.019 | C27: =B27*($B$19/$B$20)^3*$D$20/D19 -> 0.0078014639 | D27: Rasch et al. 2024 GMD (doi:10.5194/gmd-17-7963-2024): Table A1 -2.42 W/m2 at 50 Tg/yr/region -> 0.016; Table 5 -1.7 W/m2 at 25 Tg/yr/region -> 0.023; Hirasawa preprint 2/95.7 = 0.021. 0.019 is the midpoint of the Rasch range. Was 0.012 (1.8/150). Gut check only, does not feed the BCRs. Changed 2026-10.
A29: D. Aerosol required for 1 K of global cooling | H29: Sources
A30: Targeted spraying bonus | B30: 1 | C30: fraction | D30: 100% is neutral. The study assume even spraying over the region. There is likely some benefit of targeted spraying. | H30: Structural default (neutral; no targeting bonus).
A31: Target global cooling | B31: 1 | C31: K | H31: Structural default (target cooling 1 K).
A32: Plume survival to cloud base (scenario) | B32: 0.3 | C32: fraction | D32: Near-source plume loss only: in-plume coagulation and deposition before cloud base, which ESMs do not simulate (same basis as tab 5a B5; Stuart et al. 2013, doi:10.5194/acp-13-10385-2013). Activation (particles too small to become droplets) is handled by the CCN fraction in D20, so it is not counted here. Range 0.1-0.5, an assumption. | J32: Hot-model sensitivity (added 2026-10, not applied to the headline)
A33: Model | B33: Efficiency (K per Tg/yr) | C33: Tg/yr (model size basis) | D33: Tons/yr (model basis) | E33: Emitted size (nm) | F33: Size factor (150/d)^3 x CCN ratio | G33: Tg/yr at our basis | H33: Tg/yr / survival | I33: Tons/yr (our basis) | J33: Model TCR (K) | K33: AR6 TCR / model TCR | L33: Tons/yr if cooling rescaled to AR6 TCR | M33: Source
A34: CESM2 | B34: =-E10 -> 0.231 | C34: =$B$31/B34/$B$30 -> 4.3290043 | D34: =C34*10^6 -> 4329004.3 | E34: =$B$16 -> 94.2 | F34: =($B$20/E34)^3*D16/$D$20 -> 2.8813634 | G34: =C34*F34 -> 12.473435 | H34: =G34/$B$32 -> 41.578116 | I34: =H34*10^6 -> 41578116 | J34: 2 | K34: =$B$50/J34 -> 0.9 | L34: =I34/K34 -> 46197907 | M34: Meehl et al. 2020 Sci. Adv. (doi:10.1126/sciadv.aba1981): CESM2 TCR ~2.0 K
A35: CESM2-Ghosh | B35: =-E13 -> 0.29448092 | C35: =$B$31/B35/$B$30 -> 3.3958058 | D35: =C35*10^6 -> 3395805.8 | E35: =$B$17 -> 94.2 | F35: =($B$20/E35)^3*D17/$D$20 -> 2.8813634 | G35: =C35*F35 -> 9.7845506 | H35: =G35/$B$32 -> 32.615169 | I35: =H35*10^6 -> 32615169 | J35: =J34 -> 2 | K35: =$B$50/J35 -> 0.9 | L35: =I35/K35 -> 36239076 | M35: Same model as CESM2
A36: E3SMv2 | B36: =-E11 -> 0.0372 | C36: =$B$31/B36/$B$30 -> 26.88172 | D36: =C36*10^6 -> 26881720 | E36: =$B$18 -> 94.2 | F36: =($B$20/E36)^3*D18/$D$20 -> 2.404195 | G36: =C36*F36 -> 64.628897 | H36: =G36/$B$32 -> 215.42966 | I36: =H36*10^6 -> 2.1542966e+08 | J36: 2.4 | K36: =$B$50/J36 -> 0.75 | L36: =I36/K36 -> 2.8723954e+08 | M36: Golaz et al. 2022 JAMES (doi:10.1029/2022MS003156): E3SMv2 ECS 4.0 K; TCR 2.4 K used here (review estimate)
A37: UKESM1.0 | B37: =-E12 -> 0.00754 | C37: =$B$31/B37/$B$30 -> 132.62599 | D37: =C37*10^6 -> 1.3262599e+08 | E37: =$B$19 -> 171.8 | F37: =($B$20/E37)^3*D19/$D$20 -> 2.4354404 | G37: =C37*F37 -> 323.0027 | H37: =G37/$B$32 -> 1076.6757 | I37: =H37*10^6 -> 1.0766757e+09 | J37: 2.8 | K37: =$B$50/J37 -> 0.64285714 | L37: =I37/K37 -> 1.6748288e+09 | M37: Meehl et al. 2020: UKESM1 TCR ~2.8 K
A39: Note: Not accounting for direct aerosol forcing scales with salt mass, not droplets; significant above ~50 Tg/yr, dominant above ~200 Tg/yr.
A41: D. What a degree-year of cooling is worth (inputs; tabs 6b and 6c read these)
A42: Global GDP | B42: 110 | C42: $ trillion | G42: World GDP ~$110T (2025).
A43: Damage: low (older IAM / Nordhaus-style) | B43: 0.6 | C43: % GDP per degC | G43: DICE-2016R (Nordhaus 2017, w22933): 0.227% GDP per degC^2 ≈ 3.6% at 4C
A44: Damage: central (statistical class; Burke et al. 2015 anchor) | B44: 3.3 | C44: % GDP per degC | G44: Central 3.3%/degC has no single source; it sits inside Kalkuhl & Wenz 2020 (JEEM 103:102360, doi:10.1016/j.jeem.2020.102360), 2-4%/degC for a permanent level effect. Burke, Hsiang & Miguel 2015 (Nature 527:235) implies ~6%/degC; Kahn et al. 2021 ~2.5%. Replaces Kotz 2024, retracted Dec 2025. All anchors are long-run losses from lasting warming, not annual flows per degree-year. Updated 2026-10.
A45: Damage: high (Bilal-Kanzig 2026) | B45: 14 | C45: % GDP per degC | G45: Bilal & Kanzig, Quarterly Journal of Economics (2026); numbers from NBER w32450 rev. Jan 2026 (doi:10.3386/w32450): peak GDP loss 14% (95% CI 6-22%) six years after a 1 degC global temperature shock; permanent 1 degC warming 20-34% long run; a one-off transitory 1 degC ~4%. The transitory 4% is the closest analogue to one degree-year of cooling. Was 12% (2024 version). Updated 2026-10.
A46: Response lag factor (added 2026-10) | B46: 1 | C46: fraction | G46: 1.0 = no lag (the original basis). With a ~4-yr e-folding ocean response over a 50-yr program the realized share is 0.86 at a 3% discount rate and 0.72 at 10% (0.75-0.93 for 2-8 yr e-folding; computed in review). Termination: aerosol lifetime is days, so stopping returns most of the masked warming within ~5-10 yr (Parker & Irvine 2018, Earth's Future, doi:10.1002/2017EF000735). A spare fleet for redundancy is not costed. Multiplies the value of cooling in 6b/6c.
A47: SAI cost per degree-year (comparison) | B47: 18 | C47: $B per K per yr | G47: Smith 2020, Environ. Res. Lett. 15:114004 (doi:10.1088/1748-9326/aba7e7): ~$18B/yr per degC of warming avoided (2020 USD). Used only for the comparison column in 6b/6c.
A48: World merchant fleet (comparison) | B48: 109000 | C48: vessels | G48: UNCTAD Review of Maritime Transport 2024: ~109,000 ships of 100 GT and above. Used only for the feasibility block in 6b.
A49: World shipping CO2 (comparison) | B49: 1056 | C49: Mt CO2/yr | G49: IMO Fourth GHG Study 2020: total shipping emissions 1,056 Mt CO2 in 2018.
A50: IPCC AR6 assessed TCR (sensitivity) | B50: 1.8 | C50: K | G50: IPCC AR6 WG1 Ch. 7 (Forster et al. 2021, doi:10.1017/9781009157896.009): TCR 1.8 K, likely 1.4-2.2. Used only for the hot-model sensitivity in J33:L37 and the sensitivity column in 6b/6c.

Sheet 6b. Benefit - Global - Vessel
A1: Global Cooling via Dedicated Vessel: Cost and Benefit-Cost
A2: One cost basis here: the dedicated spray vessel, levelized on 3a. Tonnage from 6a; the cheaper piggyback case is 6c.
A4: A. Cost to cool the planet (dedicated vessel)
A5: Target global cooling | B5: ='6a. Cooling Model - Global'!B31 -> 1 | C5: K
A6: Cost per tonne (dedicated vessel, tab 3a base) | B6: ='3a. Outputs - Dedicated Vessel'!G5 -> 54047.979 | C6: $/tonne
A7: Tonnage per model from 6a (midlatitude), restated at 150 nm and grossed up for survival; cost at 3a dedicated-vessel levelized.
A9: Model | B9: Efficiency (K per Tg/yr) | C9: Tg/yr (150 nm basis) | D9: Tons/yr (150 nm, post-survival) | E9: $/yr | F9: Diesel CO2 at tab 2 carbon price ($/yr)
A10: CESM2 | B10: ='6a. Cooling Model - Global'!B34 -> 0.231 | C10: ='6a. Cooling Model - Global'!G34 -> 12.473435 | D10: ='6a. Cooling Model - Global'!I34 -> 41578116 | E10: =D10*$B$6 -> 2.2472131e+12 | F10: =D10*'3a. Outputs - Dedicated Vessel'!$G$15*'2. Cost Inputs'!$B$63 -> 2.8714091e+11
A11: CESM2-Ghosh | B11: ='6a. Cooling Model - Global'!B35 -> 0.29448092 | C11: ='6a. Cooling Model - Global'!G35 -> 9.7845506 | D11: ='6a. Cooling Model - Global'!I35 -> 32615169 | E11: =D11*$B$6 -> 1.7627839e+12 | F11: =D11*'3a. Outputs - Dedicated Vessel'!$G$15*'2. Cost Inputs'!$B$63 -> 2.2524227e+11
A12: E3SMv2 | B12: ='6a. Cooling Model - Global'!B36 -> 0.0372 | C12: ='6a. Cooling Model - Global'!G36 -> 64.628897 | D12: ='6a. Cooling Model - Global'!I36 -> 2.1542966e+08 | E12: =D12*$B$6 -> 11643537471727 | F12: =D12*'3a. Outputs - Dedicated Vessel'!$G$15*'2. Cost Inputs'!$B$63 -> 1.4877699e+12
A13: UKESM1.0 | B13: ='6a. Cooling Model - Global'!B37 -> 0.00754 | C13: ='6a. Cooling Model - Global'!G37 -> 323.0027 | D13: ='6a. Cooling Model - Global'!I37 -> 1.0766757e+09 | E13: =D13*$B$6 -> 5.8192143e+13 | F13: =D13*'3a. Outputs - Dedicated Vessel'!$G$15*'2. Cost Inputs'!$B$63 -> 7.4355854e+12
A14: B. What a degree-year of cooling is worth
A15: Damage-function lookup: do not reinvent, look up damage per degree and multiply. Low/central/high band: the three anchors are different kinds of quantity, so read the band as scenario spread, not a confidence interval. Break-even depends on the cost scenario.
A16: Global GDP | B16: ='6a. Cooling Model - Global'!$B$42 -> 110 | C16: $ trillion | E16: Pulled from tab 6a (B42).
A17: Target global cooling (from A above) | B17: =B5 -> 1 | C17: K
A19: Damage estimate | B19: % GDP per degC | C19: $B/degC-yr | D19: Value of target cooling ($B/yr) | E19: Source
A20: Low (older IAM / Nordhaus-style) | B20: ='6a. Cooling Model - Global'!$B$43 -> 0.6 | C20: =B16*1000*B20/100 -> 660 | D20: =C20*B17*'6a. Cooling Model - Global'!$B$46 -> 660 | E20: Pulled from tab 6a (B43); source there.
A21: Central (statistical class; Burke et al. 2015 anchor) | B21: ='6a. Cooling Model - Global'!$B$44 -> 3.3 | C21: =B16*1000*B21/100 -> 3630 | D21: =C21*B17*'6a. Cooling Model - Global'!$B$46 -> 3630 | E21: Pulled from tab 6a (B44); source there.
A22: High (Bilal-Kanzig 2026) | B22: ='6a. Cooling Model - Global'!$B$45 -> 14 | C22: =B16*1000*B22/100 -> 15400 | D22: =C22*B17*'6a. Cooling Model - Global'!$B$46 -> 15400 | E22: Pulled from tab 6a (B45); source there.
A23: All values $B/yr: global GDP ($110T) x damage %/degC. One degree-year ~ $700B low, $3,600B central, $15,400B high. Central 3.3%/degC sits within Kalkuhl & Wenz 2020 (2-4%), post-Kotz retraction. Value column multiplies by the response lag factor (6a B46, default 1.0).
A25: C. Benefit-cost ratio
A26: Value of the cooling (section B, central damage estimate) divided by its cost (section A).
A28: Cost case (model) | B28: Cost ($B/yr) | C28: Value ($B/yr, central damage) | D28: Benefit-cost ratio | E28: BCR excl. diesel CO2 | F28: BCR if cooling rescaled to AR6 TCR (sensitivity)
A29: CESM2 (optimistic) | B29: =E10+F10 -> 2.534354e+12 | C29: =$D$21*10^9 -> 3630000000000 | D29: =C29/B29 -> 1.4323176 | E29: =C29/E10 -> 1.6153341 | F29: =D29*'6a. Cooling Model - Global'!K34 -> 1.2890859
A30: CESM2-Ghosh (most optimistic) | B30: =E11+F11 -> 1.9880262e+12 | C30: =$D$21*10^9 -> 3630000000000 | D30: =C30/B30 -> 1.8259317 | E30: =C30/E11 -> 2.0592427 | F30: =D30*'6a. Cooling Model - Global'!K35 -> 1.6433385
A31: E3SMv2 (central) | B31: =E12+F12 -> 1.3131307e+13 | C31: =$D$21*10^9 -> 3630000000000 | D31: =C31/B31 -> 0.27643858 | E31: =C31/E12 -> 0.31176092 | F31: =D31*'6a. Cooling Model - Global'!K36 -> 0.20732894
A32: UKESM1 (pessimistic, our size) | B32: =E13+F13 -> 6.5627729e+13 | C32: =$D$21*10^9 -> 3630000000000 | D32: =C32/B32 -> 0.055311986 | E32: =C32/E13 -> 0.062379555 | F32: =D32*'6a. Cooling Model - Global'!K37 -> 0.035557705
A33: Benefit-cost at the dedicated-vessel cost from tab 3a plus diesel CO2 at the tab 2 carbon price (column E leaves it out). Column F rescales cooling to the IPCC AR6 TCR (6a J33:L37). Piggyback scenario and fleet numbers on 6c. Feasibility and SAI comparison in section D.
A35: D. Feasibility and comparison (added 2026-10)
A36: What 1 K takes with dedicated vessels, and cost per degree-year vs stratospheric aerosol injection (SAI). MCB's benefit-cost above is against doing nothing, not against SAI.
A37: Model | B37: Vessels needed | C37: Share of world fleet | D37: Diesel fuel (Mt/yr) | E37: Diesel CO2 (Gt/yr) | F37: Spray energy (TWh/yr) | G37: Fleet capex ($T) | H37: Cost per K-yr vs SAI (x)
A38: CESM2 | B38: =D10/'3a. Outputs - Dedicated Vessel'!$G$6 -> 105061.52 | C38: =B38/'6a. Cooling Model - Global'!$B$48 -> 0.96386713 | D38: =D10*'3a. Outputs - Dedicated Vessel'!$G$15/'2. Cost Inputs'!$B$61/10^6 -> 471.38738 | E38: =D10*'3a. Outputs - Dedicated Vessel'!$G$15/10^9 -> 1.5112679 | F38: =D10*'2. Cost Inputs'!$B$24/10^9 -> 1261.2514 | G38: =B38*'2. Cost Inputs'!$B$53/10^12 -> 7.6448033 | H38: =(B29/10^9/$B$5)/'6a. Cooling Model - Global'!$B$47 -> 140.79745
A39: CESM2-Ghosh | B39: =D11/'3a. Outputs - Dedicated Vessel'!$G$6 -> 82413.525 | C39: =B39/'6a. Cooling Model - Global'!$B$48 -> 0.75608739 | D39: =D11*'3a. Outputs - Dedicated Vessel'!$G$15/'2. Cost Inputs'!$B$61/10^6 -> 369.77094 | E39: =D11*'3a. Outputs - Dedicated Vessel'!$G$15/10^9 -> 1.1854856 | F39: =D11*'2. Cost Inputs'!$B$24/10^9 -> 989.36488 | G39: =B39*'2. Cost Inputs'!$B$53/10^12 -> 5.9968218 | H39: =(B30/10^9/$B$5)/'6a. Cooling Model - Global'!$B$47 -> 110.4459
A40: E3SMv2 | B40: =D12/'3a. Outputs - Dedicated Vessel'!$G$6 -> 544357.67 | C40: =B40/'6a. Cooling Model - Global'!$B$48 -> 4.9941071 | D40: =D12*'3a. Outputs - Dedicated Vessel'!$G$15/'2. Cost Inputs'!$B$61/10^6 -> 2442.4104 | E40: =D12*'3a. Outputs - Dedicated Vessel'!$G$15/10^9 -> 7.8303677 | F40: =D12*'2. Cost Inputs'!$B$24/10^9 -> 6534.9512 | G40: =B40*'2. Cost Inputs'!$B$53/10^12 -> 39.610197 | H40: =(B31/10^9/$B$5)/'6a. Cooling Model - Global'!$B$47 -> 729.51707
A41: UKESM1.0 | B41: =D13/'3a. Outputs - Dedicated Vessel'!$G$6 -> 2720594.1 | C41: =B41/'6a. Cooling Model - Global'!$B$48 -> 24.959579 | D41: =D13*'3a. Outputs - Dedicated Vessel'!$G$15/'2. Cost Inputs'!$B$61/10^6 -> 12206.694 | E41: =D13*'3a. Outputs - Dedicated Vessel'!$G$15/10^9 -> 39.13466 | F41: =D13*'2. Cost Inputs'!$B$24/10^9 -> 32660.419 | G41: =B41*'2. Cost Inputs'!$B$53/10^12 -> 197.96409 | H41: =(B32/10^9/$B$5)/'6a. Cooling Model - Global'!$B$47 -> 3645.9849
A42: Context: all world shipping emitted ~1,056 Mt CO2 in 2018 (IMO 4th GHG Study, 6a B49); the world fleet is ~109,000 ships (UNCTAD 2024, 6a B48). SAI ~$18B/yr per K (Smith 2020, 6a B47). MCB is cheaper than removing the ~2,200 Gt CO2 that 1 K corresponds to (AR6 TCRE 0.45 K per 1,000 Gt) but removes no CO2.

Sheet 6c. Benefit - Global Piggyback
A1: Global Cooling via Container-Ship Piggyback: Cost and Benefit-Cost
A2: One cost basis here: the container-ship piggyback from tab 3b, read directly the way 6b reads 3a. Tonnage from 6a. Every input traces to tabs 1, 2 and 3b.
A4: A. Cost to cool the planet (container-ship piggyback)
A5: Target global cooling | B5: ='6a. Cooling Model - Global'!B31 -> 1 | C5: K
A6: Cost per tonne (container-ship piggyback, tab 3b) | B6: ='3b. Outputs - Ship Piggyback'!C32 -> 21674.005 | C6: $/tonne | D6: Reads tab 3b directly. Until 10/07 this section costed its own optimistic case (0.1x power, best-case prices, 43% utilization).
A17: Model | B17: Efficiency (K per Tg/yr) | C17: Tg/yr (150 nm basis) | D17: Tons/yr (150 nm, post-survival) | E17: $/yr | F17: Diesel CO2 at tab 2 carbon price ($/yr)
A18: CESM2 | B18: ='6a. Cooling Model - Global'!B34 -> 0.231 | C18: ='6a. Cooling Model - Global'!G34 -> 12.473435 | D18: ='6a. Cooling Model - Global'!I34 -> 41578116 | E18: =D18*$B$6 -> 9.011643e+11 | F18: =D18*'3b. Outputs - Ship Piggyback'!$B$44*'2. Cost Inputs'!$B$63 -> 1.5365574e+11
A19: CESM2-Ghosh | B19: ='6a. Cooling Model - Global'!B35 -> 0.29448092 | C19: ='6a. Cooling Model - Global'!G35 -> 9.7845506 | D19: ='6a. Cooling Model - Global'!I35 -> 32615169 | E19: =D19*$B$6 -> 7.0690133e+11 | F19: =D19*'3b. Outputs - Ship Piggyback'!$B$44*'2. Cost Inputs'!$B$63 -> 1.2053234e+11
A20: E3SMv2 | B20: ='6a. Cooling Model - Global'!B36 -> 0.0372 | C20: ='6a. Cooling Model - Global'!G36 -> 64.628897 | D20: ='6a. Cooling Model - Global'!I36 -> 2.1542966e+08 | E20: =D20*$B$6 -> 4.6692235e+12 | F20: =D20*'3b. Outputs - Ship Piggyback'!$B$44*'2. Cost Inputs'!$B$63 -> 7.9614003e+11
A21: UKESM1.0 | B21: ='6a. Cooling Model - Global'!B37 -> 0.00754 | C21: ='6a. Cooling Model - Global'!G37 -> 323.0027 | D21: ='6a. Cooling Model - Global'!I37 -> 1.0766757e+09 | E21: =D21*$B$6 -> 2.3335874e+13 | F21: =D21*'3b. Outputs - Ship Piggyback'!$B$44*'2. Cost Inputs'!$B$63 -> 3.9789536e+12
A23: B. What a degree-year of cooling is worth
A24: Damage-function lookup: do not reinvent, look up damage per degree and multiply. Low/central/high band: the three anchors are different kinds of quantity, so read the band as scenario spread, not a confidence interval. Break-even depends on the cost scenario.
A25: Global GDP | B25: ='6a. Cooling Model - Global'!$B$42 -> 110 | C25: $ trillion | E25: Pulled from tab 6a (B42).
A26: Target global cooling (from A above) | B26: =B5 -> 1 | C26: K
A28: Damage estimate | B28: % GDP per degC | C28: $B/degC-yr | D28: Value of target cooling ($B/yr) | E28: Source
A29: Low (older IAM / Nordhaus-style) | B29: ='6a. Cooling Model - Global'!$B$43 -> 0.6 | C29: =B25*1000*B29/100 -> 660 | D29: =C29*B26*'6a. Cooling Model - Global'!$B$46 -> 660 | E29: Pulled from tab 6a (B43); source there.
A30: Central (statistical class; Burke et al. 2015 anchor) | B30: ='6a. Cooling Model - Global'!$B$44 -> 3.3 | C30: =B25*1000*B30/100 -> 3630 | D30: =C30*B26*'6a. Cooling Model - Global'!$B$46 -> 3630 | E30: Pulled from tab 6a (B44); source there.
A31: High (Bilal-Kanzig 2026) | B31: ='6a. Cooling Model - Global'!$B$45 -> 14 | C31: =B25*1000*B31/100 -> 15400 | D31: =C31*B26*'6a. Cooling Model - Global'!$B$46 -> 15400 | E31: Pulled from tab 6a (B45); source there.
A32: All values $B/yr: global GDP ($110T) x damage %/degC. One degree-year ~ $700B low, $3,600B central, $15,400B high. Central 3.3%/degC sits within Kalkuhl & Wenz 2020 (2-4%), post-Kotz retraction. Value column multiplies by the response lag factor (6a B46, default 1.0).
A34: C. Benefit-cost ratio
A35: Value of the cooling (section B, central damage estimate) divided by its cost (section A).
A37: Cost case (model) | B37: Cost ($B/yr) | C37: Value ($B/yr, central damage) | D37: Benefit-cost ratio | E37: BCR excl. diesel CO2 | F37: BCR if cooling rescaled to AR6 TCR (sensitivity)
A38: CESM2 (optimistic) | B38: =E18+F18 -> 1.05482e+12 | C38: =$D$30*10^9 -> 3630000000000 | D38: =C38/B38 -> 3.4413453 | E38: =C38/E18 -> 4.0281223 | F38: =D38*'6a. Cooling Model - Global'!K34 -> 3.0972108
A39: CESM2-Ghosh (most optimistic) | B39: =E19+F19 -> 8.2743368e+11 | C39: =$D$30*10^9 -> 3630000000000 | D39: =C39/B39 -> 4.3870586 | E39: =C39/E19 -> 5.1350872 | F39: =D39*'6a. Cooling Model - Global'!K35 -> 3.9483527
A40: E3SMv2 (central) | B40: =E20+F20 -> 5.4653635e+12 | C40: =$D$30*10^9 -> 3630000000000 | D40: =C40/B40 -> 0.66418272 | E40: =C40/E20 -> 0.7774312 | F40: =D40*'6a. Cooling Model - Global'!K36 -> 0.49813704
A41: UKESM1 (pessimistic, our size) | B41: =E21+F21 -> 2.7314827e+13 | C41: =$D$30*10^9 -> 3630000000000 | D41: =C41/B41 -> 0.13289485 | E41: =C41/E21 -> 0.15555449 | F41: =D41*'6a. Cooling Model - Global'!K37 -> 0.085432406
A42: ="Benefit-cost at the piggyback cost from tab 3b ("&TEXT($B$6,"$#,##0")&"/t) plus the ships' genset diesel CO2 at the tab 2 carbon price (column E leaves it out). Column F rescales cooling to the IPCC AR6 TCR. Dedicated-vessel case is 6b; fleet numbers in section D." -> Benefit-cost at the piggyback cost from tab 3b ($21,674/t) plus the ships' genset diesel CO2 at the tab 2 carbon price (column E leaves it out). Column F rescales cooling to the IPCC AR6 TCR. Dedicated-vessel case is 6b; fleet numbers in section D.
A44: D. Fleet scale and power sensitivity
A45: Piggyback-only question: how many ships, and what is the nozzle power draw worth?
A47: Per-ship aerosol output (tab 3b host-ship train) | B47: ='3b. Outputs - Ship Piggyback'!B43 -> 427.2363 | C47: t/yr | D47: Pulled from tab 3b (B43): the train sized to the ship's own 4.5 MW. Until 10/07 this assumed 2 MW from the host while 3b priced a 4.2 MW train.
A48: Annual fuel for own generation (t) | B48: ='3b. Outputs - Ship Piggyback'!B41*24*'3b. Outputs - Ship Piggyback'!B16*B50/1000 -> 2592 | C48: t/yr
A49: Own gensets burn ~200 g fuel/kWh (B50); the fuel is already priced inside the tab-2 energy rate. This row is for bunkering logistics only.
A50: Generator fuel rate | B50: 0.2 | C50: kg per kWh | D50: Until 10/07 typed inside B48.
A51: Fleet reference
A52: Fully cellular container ships (Alphaliner, Apr 2026) | B52: 6706 | C52: ships
A53: Sources: Alphaliner Apr 2026 (6,706 container ships); MDS Transmodal Apr 2025 via UNCTAD RMT 2025 (6,033); Alphaliner Monthly Monitor Jul 2024 size table (954 of 6,206 ships under 1,000 TEU).
A54: Eligible host ships (1,000 TEU and up) | B54: =ROUND(B52*D54,0) -> 5700 | C54: ships | D54: 0.85 | E54: D54 = share of the fleet of 1,000 TEU and up, 85% by count (Alphaliner Jul 2024). A 4.5 MW own-generation train needs ~30 TEU of slots, so feeders qualify; only the smallest class is excluded.
A55: Climate model | B55: Aerosol for 1K (t/yr) | C55: Vessels needed | D55: % of eligible fleet | E55: ="Cost at tab-1 power, "&TEXT($B$6,"$#,##0")&"/t ($B/yr)" -> Cost at tab-1 power, $21,674/t ($B/yr) | F55: Genset fuel (Mt/yr) | G55: Genset CO2 (Gt/yr) | H55: Spray energy (TWh/yr) | I55: Max K with all eligible ships | J55: Cost per K-yr vs SAI (x)
A56: CESM2 (optimistic) | B56: ='6a. Cooling Model - Global'!I34 -> 41578116 | C56: =B56/$B$47 -> 97318.781 | D56: =C56/$B$54 -> 17.07347 | E56: =B56*$B$6/10^9 -> 901.1643 | F56: =C56*$B$48/10^6 -> 252.25028 | G56: =B56*'3b. Outputs - Ship Piggyback'!$B$44/10^9 -> 0.8087144 | H56: =B56*'2. Cost Inputs'!$B$24/10^9 -> 1261.2514 | I56: =$B$5*$B$54*$B$47/B56 -> 0.058570401 | J56: =(B38/10^9/$B$5)/'6a. Cooling Model - Global'!$B$47 -> 58.601113
A57: CESM2-Ghosh | B57: ='6a. Cooling Model - Global'!I35 -> 32615169 | C57: =B57/$B$47 -> 76339.882 | D57: =C57/$B$54 -> 13.392962 | E57: =B57*$B$6/10^9 -> 706.90133 | F57: =C57*$B$48/10^6 -> 197.87298 | G57: =B57*'3b. Outputs - Ship Piggyback'!$B$44/10^9 -> 0.63438076 | H57: =B57*'2. Cost Inputs'!$B$24/10^9 -> 989.36488 | I57: =$B$5*$B$54*$B$47/B57 -> 0.074666083 | J57: =(B39/10^9/$B$5)/'6a. Cooling Model - Global'!$B$47 -> 45.968538
A58: E3SMv2 (central) | B58: ='6a. Cooling Model - Global'!I36 -> 2.1542966e+08 | C58: =B58/$B$47 -> 504240.06 | D58: =C58/$B$54 -> 88.463168 | E58: =B58*$B$6/10^9 -> 4669.2235 | F58: =C58*$B$48/10^6 -> 1306.9902 | G58: =B58*'3b. Outputs - Ship Piggyback'!$B$44/10^9 -> 4.1902107 | H58: =B58*'2. Cost Inputs'!$B$24/10^9 -> 6534.9512 | I58: =$B$5*$B$54*$B$47/B58 -> 0.01130414 | J58: =(B40/10^9/$B$5)/'6a. Cooling Model - Global'!$B$47 -> 303.63131
A59: UKESM1.0 (pessimistic) | B59: ='6a. Cooling Model - Global'!I37 -> 1.0766757e+09 | C59: =B59/$B$47 -> 2520094.1 | D59: =C59/$B$54 -> 442.12177 | E59: =B59*$B$6/10^9 -> 23335.874 | F59: =C59*$B$48/10^6 -> 6532.0839 | G59: =B59*'3b. Outputs - Ship Piggyback'!$B$44/10^9 -> 20.941861 | H59: =B59*'2. Cost Inputs'!$B$24/10^9 -> 32660.419 | I59: =$B$5*$B$54*$B$47/B59 -> 0.0022618203 | J59: =(B41/10^9/$B$5)/'6a. Cooling Model - Global'!$B$47 -> 1517.4904
A60: Review 2026-10: columns F-J. Max K = target x (eligible ships x per-ship output) / tonnes needed. Genset fuel is on top of the ships' own propulsion. SAI comparison uses Smith 2020 (~$18B/yr per K, 6a B47).
A61: Nozzle power sensitivity
A62: To see this tab at a different nozzle power, change the selector on tab 1 (H17). Tab 3b re-sizes the train to the same 4.5 MW and every row above follows. Until 10/07 an energy-only approximation lived here.

Sheet References
A1: References: academic publications cited in this workbook
A2: Ref as cited | B2: Full citation | C2: Where used | D2: DOI / link
A3: Harrison et al. 2025 | B3: Harrison, L. P., Medcraft, C., & Harrison, D. P. (2025). Effervescent nozzle design to enable outdoor marine cloud brightening experimentation. Environmental Science: Atmospheres, 5(10), 1071-1080. | C3: Tabs 1 (particle output, CCN window, particle size, power, energy per tonne), 2 | D3: https://doi.org/10.1039/d5ea00073d
A4: Harrison et al. 2019 / T14 | B4: Harrison, D. P., Baird, M., Harrison, L., Utembe, S., Schofield, R., Escobar Correa, R., Mongin, M., & Rizwi, F. (2019). Environmental Modelling of Large Scale Solar Radiation Management. RRAP T14 Final Report (83 pp). | C4: 5a (local temperature sensitivity), 5c-alt (T14 scenarios, Fig 15) | D4: https://gbrrestoration.org/wp-content/uploads/2020/09/T14-Environmental-Modelling-of-Large-Scale-SRM_v3.03-3.pdf
A5: Zhao et al. 2026 (preprint) | B5: Zhao, W., Huang, Y., Siems, S., & Harrison, D. (2026). Sensitivity of Marine Cloud Brightening over the Great Barrier Reef to Spatial Variability in Aerosol Forcing: A Case Study using convection-permitting model. EGUsphere preprint, discussion started 23 March 2026. | C5: 5c-alt (main cooling basis), 5c | D5: https://doi.org/10.5194/egusphere-2026-1251
A6: Hernandez-Jaramillo et al. 2025 (ERL) | B6: Hernandez-Jaramillo, D. C., Harrison, L., Gunner, G., McGrath, A., Junkermann, W., Lieff, W., Hacker, J., Rosenfeld, D., Kelaher, B., & Harrison, D. P. (2025). First generation outdoor marine cloud brightening trial increases aerosol concentration at cloud base height. Environmental Research Letters, 20(5), 054065. | C6: Tab 1 (particle size, particles per tonne, energy notes), 6a (plume to cloud base) | D6: https://doi.org/10.1088/1748-9326/adccd7
A7: Hernandez-Jaramillo et al. 2025a (plume review) | B7: Hernandez-Jaramillo, D., Kelaher, B., & Harrison, D. (2025). A review of plume dispersion and measurement techniques applicable to marine cloud brightening. Frontiers in Marine Science, 12, 1450175. | C7: 5a and 6a plume survival context (open research gap; the review gives no numeric survival fraction or activation diameter, so the 0.1-0.5 range is an assumption) | D7: https://doi.org/10.3389/fmars.2025.1450175
A8: CS-01 2025 (RRAP report) | B8: Harrison, D., Ristovski, Z., Ryan, R., Zhao, W., Sulo, J., Horchler, J., Huang, Y., Schofield, R., Deschaseaux, E., Harrison, L., Holloway, C., Braga, R., Rosenfeld, D., & Siems, S. (2025). Reef Restoration and Adaptation Program - GBR Atmospheric Survey (CS-01) Final Report 2025 (33 pp). | C8: 5a (cloud availability 0.2; p.11) | D8: https://gbrrestoration.org/wp-content/uploads/2026/06/RRAP-CS-01_FINAL-REPORT-2025.pdf
A9: CS-06 2025 (RRAP report) | B9: Harrison, D. P., Ristovski, Z., Rosenfeld, D., Holloway, C., Cleary, M., Kourmatzis, A., Harrison, L., Braga, R. C., Medcraft, C., Hernandez-Jaramillo, D. C., et al. (2025). Reef Restoration and Adaptation Program - Cloud and Sky Brightening Development (CS-06) Final Report 2025 (56 pp). | C9: Tab 1 (particle size, power), 5a (survival, mixing depth, background droplets p.34, droplet enhancement), 3a | D9: https://gbrrestoration.org/wp-content/uploads/2026/06/RRAP-CS-06_FINAL-REPORT-2025.pdf
A10: Latham et al. 2012 | B10: Latham, J., Bower, K., Choularton, T., Coe, H., Connolly, P., Cooper, G., Craft, T., Foster, J., Gadian, A., et al. (2012). Marine cloud brightening. Philosophical Transactions of the Royal Society A, 370, 4217-4262. | C10: Tab 2 (required flux), foundational MCB concept | D10: https://doi.org/10.1098/rsta.2012.0086
A11: Hirasawa et al. 2026 | B11: Hirasawa, H., Henry, M., Mason, E., Rasch, P. J., Doherty, S. J., Wood, R., Haywood, J., & von Salzen, K. (2026). Forcing Susceptibility and Climate Sensitivity to Midlatitude Marine Cloud Brightening. Journal of Climate, 39(2), 769-784. | C11: 6a (section A regional efficiencies, E10 0.231 K per Tg/yr) | D11: https://doi.org/10.1175/JCLI-D-25-0337.1
A12: Estrada et al. 2017 | B12: Estrada, F., Botzen, W. J. W., & Tol, R. S. J. (2017). A global economic assessment of city policies to reduce climate change impacts. Nature Climate Change, 7, 403-406. | C12: 5d (urban passive cooling benefit-cost) | D12: https://doi.org/10.1038/nclimate3301
A13: Burke et al. 2015 | B13: Burke, M., Hsiang, S. M., & Miguel, E. (2015). Global non-linear effect of temperature on economic production. Nature, 527, 235-239. | C13: 6b, 6c (value of a degree of cooling, central damage estimate) | D13: https://doi.org/10.1038/nature15725
A14: Hirasawa et al. 2026 (preprint) | B14: Hirasawa, H., von Salzen, K., Henry, M., Smith, J., Bender, F. A.-M., Wang, C., Doherty, S., Wood, R., Rasch, P. J., and Haywood, J. (2026). On the Range of Marine Cloud Brightening Radiative Forcing across Earth System Models. EGUsphere preprint. | C14: 6a (model CCN fractions and volume-mean sizes, Table 1; CESM2-Ghosh equal-tonnage ratio and forcing efficiencies, Table 2) | D14: https://doi.org/10.5194/egusphere-2026-5460
A15: Supporting files (not directly cited)
A16: ARIA proposal 2025 (Woodhouse et al.) | B16: Woodhouse, Middleton, Fitzgerald, Hunt, Hoffmann, Ristovski, Miljevic, Harrison, D. P., & Lemckert (2025). Marine Cloud Brightening in a complex world - moving beyond the Twomey effect. Proposal to the Advanced Research + Invention Agency: Exploring Climate Cooling Programme. Southern Cross University. (Funding proposal, not peer reviewed.) | C16: Corroborates tab-1 nozzle specs (640 nozzles, ~10^15/s) | D16: https://doi.org/10.25918/misc.469
A17: PhD thesis 2024 | B17: Hernandez Jaramillo, D. C. (2024). Characterisation and dispersion of particle emissions for marine cloud brightening over the Great Barrier Reef. PhD thesis, Southern Cross University. | C17: Background on sprayer generations and plume measurements | D17: https://doi.org/10.25918/thesis.426
A18: Non-academic sources (websites, not downloaded)
A19: Nozzle price listing | B19: Alibaba product listing for effervescent nozzle hardware. | C19: Tab 2 (nozzle price) | D19: https://www.alibaba.com/product-detail/Two-fluid-Nozzle-Fuel-Burner-Gas_1601145712214.html
A20: Vessel charter / ship sizing | B20: Charter-market and vessel-spec websites used for ship sizing and charter rates. | C20: Tab 2, 3a-3d | D20: https://horizonoffshoreservices.com/wp-content/uploads/2024/07/HOS269.pdf ; https://www.rivieramm.com/news-content-hub/sticker-shock-price-of-psv-newbuildings-up-68-since-2016-79964
A21: World Bank Cool Cities primer | B21: Energy Sector Management Assistance Program / World Bank (2020). Primer for Cool Cities: Reducing Excessive Urban Heat - With a Focus on Passive Measures. doi:10.1596/34218. | C21: 5d (urban passive cooling benefit-cost) | D21: https://openknowledge.worldbank.org/handle/10986/34218
A23: Added in review 2026-10
A24: RRAP CS-07 2025 | B24: RRAP (2025). Cloud and Sky Brightening: Fogging Development (CS-07) Final Report 2025. Reef Restoration and Adaptation Program. | C24: Tab 2 (nozzle cost bracket $10-$1,000, p.31; MeeFog $50/nozzle, p.35) | D24: https://gbrrestoration.org/wp-content/uploads/2026/06/RRAP-CS-07_FINAL-REPORT-2025.pdf
A25: Deloitte 2025, 2017 | B25: Deloitte Access Economics (2025). At What Cost? Safeguarding the Great Barrier Reef's Role in Australia's Economy. Great Barrier Reef Foundation. Earlier: Deloitte Access Economics (2017). At what price? The economic, social and icon value of the Great Barrier Reef. | C25: 5c (A$95B reef value; 2017 figure A$56B) | D25: https://globalfundcoralreefs.org/reef-plus/knowledge/at-what-cost-safeguarding-the-great-barrier-reef-s-role-in-australia-s-economy/
A26: AIMS 2025 | B26: Australian Institute of Marine Science (2025). Annual Summary Report of Coral Reef Condition 2024/2025. | C26: 5c (event frequency, 2024 coral-cover loss) | D26: https://web.archive.org/web/20260101034222/https://www.aims.gov.au/monitoring-great-barrier-reef/gbr-condition-summary-2024-25
A27: Hughes et al. 2018 | B27: Hughes, T. P., Kerry, J. T., Baird, A. H., Connolly, S. R., et al. (2018). Global warming transforms coral reef assemblages. Nature, 556, 492-496. | C27: 5c (DHW threshold note) | D27: https://doi.org/10.1038/s41586-018-0041-2
A28: Harding et al. 2024 | B28: Harding, A. R., Vecchi, G. A., Yang, W., & Keith, D. W. (2024). Impact of solar geoengineering on temperature-attributable mortality. PNAS, 121(52), e2401801121. | C28: 5d (13x benefit:risk anchor) | D28: https://doi.org/10.1073/pnas.2401801121
A29: Kephart et al. 2022 | B29: Kephart, J. L., Sanchez, B. N., Moore, J., Schinasi, L. H., et al. (2022). City-level impact of extreme temperatures and mortality in Latin America. Nature Medicine, 28, 1700-1705. | C29: 5d (RR 1.057 per degC, 326 cities; baseline deaths) | D29: https://doi.org/10.1038/s41591-022-01872-6
A30: Zhao Q. et al. 2021; Gasparrini et al. 2015 | B30: Zhao, Q., Guo, Y., Ye, T., Gasparrini, A., et al. (2021). Lancet Planetary Health, 5, e415-e425. Gasparrini, A., Guo, Y., Hashizume, M., et al. (2015). Lancet, 386, 369-375. | C30: 5d (baseline heat-death range) | D30: https://doi.org/10.1016/S2542-5196(21)00081-4 ; https://doi.org/10.1016/S0140-6736(14)62114-0
A31: World Bank WDI; EPA/DOT VSL | B31: World Bank, World Development Indicators, SP.DYN.CDRT.IN (2024). US EPA, Mortality Risk Valuation. US DOT (2024), Departmental Guidance on Valuation of a Statistical Life. Viscusi & Masterman (2017), J. Benefit-Cost Analysis 8:226-250. | C31: 5d (crude death rate, VSL) | D31: https://api.worldbank.org/v2/country/WLD/indicator/SP.DYN.CDRT.IN ; https://doi.org/10.1017/bca.2017.12
A32: Nordhaus 2016 (DICE-2016R) | B32: Nordhaus, W. D. (2016). Projections and Uncertainties About Climate Change in an Era of Minimal Climate Policies. NBER Working Paper 22933. | C32: 6a (low damage, 0.227% GDP per degC^2) | D32: https://doi.org/10.3386/w22933
A33: Bilal & Kanzig 2026 | B33: Bilal, A., & Kanzig, D. R. (2026). The Macroeconomic Impact of Climate Change: Global vs. Local Temperature. Quarterly Journal of Economics (NBER Working Paper 32450, rev. Jan 2026). | C33: 6a (high damage, 14% peak) | D33: https://doi.org/10.3386/w32450
A34: Kalkuhl & Wenz 2020 | B34: Kalkuhl, M., & Wenz, L. (2020). The impact of climate conditions on economic production. Evidence from a global panel of regions. Journal of Environmental Economics and Management, 103, 102360. | C34: 6a (central damage range 2-4%/degC) | D34: https://doi.org/10.1016/j.jeem.2020.102360
A35: Kahn et al. 2021 | B35: Kahn, M. E., Mohaddes, K., Ng, R. N. C., Pesaran, M. H., Raissi, M., & Yang, J.-C. (2021). Long-term macroeconomic effects of climate change: A cross-country analysis. Energy Economics (NBER w26167). | C35: 6a (central damage context) | D35: https://doi.org/10.3386/w26167
... A50: Compressor listing; Riviera/Clarksons; Hornbeck UT 755L; Vianna et al. 2025 | B50: Used Ariel JGQ/2 200 hp compressor package listing (freeoilfieldquote.com). Riviera Maritime Media (14 Mar 2024), Sticker shock: price of PSV newbuildings up 68% since 2016 (Clarksons). Hornbeck Offshore HOS269 UT 755L spec sheet. Vianna et al. (2025), J. Mar. Sci. Eng. 13(4):686. | C50: Tab 2 (compressor $/kW, vessel price, fuel burn) | D50: https://www.rivieramm.com/news-content-hub/sticker-shock-price-of-psv-newbuildings-up-68-since-2016-79964 ; https://www.mdpi.com/2077-1312/13/4/686

Sheet Review changes 2026-10
A1: Review changes 2026-10: every cell changed in this revision
A2: One row per changed cell. "Old" is the formula or value before the change, with its computed value. "New value (live)" links to the cell, so it stays current. Finding IDs refer to review/claims_and_citations_2026-10.xlsx in the repo. Headline before/after table at the bottom.
A4: Sheet | B4: Cell | C4: Finding | D4: Old formula or value | E4: Old computed value | F4: New formula or value | G4: New value (live) | H4: Reason | I4: Source
A5: 5a. Cooling Model - Local | B5: A16 | C5: F02 | D5: Cloud-top shortwave (daytime) | F5: Cloud-top shortwave, 24-h mean | H5: Label: B16 is a 24-h mean, not a daytime value.
A6: 5a. Cooling Model - Local | B6: B16 | C6: F02 | D6: 475 | E6: 475 | F6: 380 | G6: ='5a. Cooling Model - Local'!B16 -> 380 | H6: 475 was the DJF 24-h mean at the top of the atmosphere; at cloud top the 24-h mean is ~380. Paired with B20 = 1.0 so the diurnal cycle is counted once. | I6: Wood 2021 ACP doi:10.5194/acp-21-14507-2021; NASA POWER CERES SYN1deg TOA_SW_DWN; solar geometry computed
A7: 5a. Cooling Model - Local | B7: D16 | C7: F02 | D7: Downwelling SW at cloud top, daytime marine. 24h-mean is lower; this is the active-cooling value. | F7: 24-h mean downwelling SW at cloud top, GBR Dec-Apr. 475 was the DJF 24-h mean at the top of the atmosphere (CERES via NASA POWER: 460-491 at three GBR points), not a daytime value. x ~0.8 free-troposphere transmission (Wood 2021) gives ~380. Solar-geometry check, 14-22S, 1 Dec-30 Apr: 442 W/m2 24-h TOA, 376-385 at cloud top. Changed 2026-10 from 475, which was then multiplied by a 0.4 day/night factor in B20, counting the diurnal cycle twice. | H7: Note rewritten to match the new value.
A8: 5a. Cooling Model - Local | B8: H16 | C8: F02 | D8: Assumption (daytime marine cloud-top shortwave) | F8: Wood 2021, ACP 21:14507 (doi:10.5194/acp-21-14507-2021), Sect. 2.1: day+night-mean irradiance, free-troposphere transmissivity 0.8, no separate diurnal factor. NASA POWER CERES SYN1deg TOA_SW_DWN climatology. Daily-mean insolation computed from solar geometry in review. | H8: Source for B16.
A9: 5a. Cooling Model - Local | B9: A20 | C9: F02 | D9: Daytime averaging | F9: Diurnal factor | H9: Label.
A10: 5a. Cooling Model - Local | B10: B20 | C10: F02 | D10: 0.4 | E10: 0.4 | F10: 1 | G10: ='5a. Cooling Model - Local'!B20 -> 1 | H10: B16 is already a 24-h mean, so no extra day/night factor. Was 0.4 (double count). | I10: Wood 2021 ACP doi:10.5194/acp-21-14507-2021
A11: 5a. Cooling Model - Local | B11: D20 | C11: F02 | D11: Daytime averaging ~0.4: brightening only reflects sun by day, so 24-h forcing is ~0.3-0.5 of peak. | F11: 1.0 because B16 is already a 24-h mean. Was 0.4 on top of a 24-h mean, which counted the diurnal cycle twice. If you prefer a daytime B16 (~720-740 W/m2 at cloud top), set this to the daylight fraction, ~0.52 for 14-22S Dec-Apr. | H11: Note rewritten.
A12: 5a. Cooling Model - Local | B12: H20 | C12: F02 | D12: Assumption (daytime-averaging factor ~0.4). | F12: Wood 2021 (doi:10.5194/acp-21-14507-2021): no separate diurnal factor with day+night-mean irradiance. Daylight fraction 0.52 for 14-22S Dec-Apr computed in review. | H12: Source.
A13: 5a. Cooling Model - Local | B13: D22 | C13: F02 | D13: Daytime averaging x cloud availability | F13: Diurnal factor (1.0) x cloud availability | H13: Label follows B20.
A14: 5a. Cooling Model - Local | B14: D10 | C14: F20 | D14: Spray up to the measured ceiling: 200 total - 100 background = add 100/cm3. Ceiling measured, CS-06 p.34. | F14: (Droplet-number enhancement - 1) x background: 0.3 x 100 = add 30/cm3 at the 1.3x base. The measured ceiling (CS-06 p.34) is ~200/cm3 total, i.e. at most +100/cm3 (2.0x). | H14: Stale note said +100/cm3; the cell gives +30.
A15: 5a. Cooling Model - Local | B15: D17 | C15: F20 | D15: Stratocumulus deck albedo, ~0.5. | F15: Cloud albedo 0.4 (author choice, kept). Stratocumulus decks run ~0.5-0.6 (Wood 2021). GBR summer trade cumulus is lower: 0.1-0.3 domain average (Harrison et al. 2019 T14, pp.64-65), which would cut the Twomey term A(1-A) from 0.24 to 0.09-0.21. | H15: Stale note said ~0.5; cell is 0.4. Added the GBR range (F21). | I15: Harrison et al. 2019 RRAP T14 report (gbrrestoration.org); Wood 2021 ACP doi:10.5194/acp-21-14507-2021
A16: 5a. Cooling Model - Local | B16: D18 | C16: F20/F24 | D16: Droplet-number enhancement vs background, capped at the measured ~200/cm3 ceiling (CS-06 p.34) = 200/background = 2.0x here. | F16: 1.3x over a 100/cm3 background (+30/cm3). Zhao et al. 2026 GBR modelling: domain-mean droplet increase 1.14-1.73x (central 1.32). Measured ceiling ~200/cm3, i.e. at most 2.0x (CS-06 p.34). Cooling per tonne scales as ln(r)/(r-1), so a higher ratio lowers cooling per tonne. | H16: Stale note said 2.0x; the cell is 1.3. | I16: Zhao et al. 2026 EGUsphere preprint doi:10.5194/egusphere-2026-1251
A17: 5b. Cooling-Value Sensitivity | B17: B12 | C17: F02 | D17: 400 | E17: 400 | F17: 340 | G17: ='5b. Cooling-Value Sensitivity'!B12 -> 340 | H17: Bounds re-centred on the 24-h mean (380): 340 (5c-alt basis) to 420.
A18: 5b. Cooling-Value Sensitivity | B18: D12 | C18: F02 | D18: 550 | E18: 550 | F18: 420 | G18: ='5b. Cooling-Value Sensitivity'!D12 -> 420 | H18: Upper bound: DJF TOA 475-491 x 0.85-0.87.
A19: 5b. Cooling-Value Sensitivity | B19: I12 | C19: F02 | D19: Sensitivity bounds around the tab 5a base cloud-top shortwave; see tab 5a Sources. | F19: Bounds on the 24-h mean cloud-top SW (5a B16 = 380): 340 (the 5c-alt basis) to 420 (DJF TOA 475-491 x 0.85-0.87 transmission). Were 400/550 around the old 475. Changed 2026-10. | H19: Note.
A20: 5b. Cooling-Value Sensitivity | B20: B13 | C20: F24 | D20: 2 | E20: 2 | F20: 1.14 | G20: ='5b. Cooling-Value Sensitivity'!B13 -> 1.14 | H20: Zhao 2026 low end; old bounds (2, 4) both sat above the 1.3 base. | I20: Zhao et al. 2026 EGUsphere preprint doi:10.5194/egusphere-2026-1251
A21: 5b. Cooling-Value Sensitivity | B21: D13 | C21: F24 | D21: 4 | E21: 4 | F21: 1.73 | G21: ='5b. Cooling-Value Sensitivity'!D13 -> 1.73 | H21: Zhao 2026 high end. | I21: Zhao et al. 2026 EGUsphere preprint doi:10.5194/egusphere-2026-1251
A22: 5b. Cooling-Value Sensitivity | B22: E13 | C22: F24 | D22: ='5a. Cooling Model - Local'!$B$34*(LN('5a. Cooling Model - Local'!$B$18)/LN(B13)) | E22: 1.3054051 | F22: ='5a. Cooling Model - Local'!$B$34*((LN('5a. Cooling Model - Local'!$B$18)/('5a. Cooling Model - Local'!$B$18-1))/(LN(B13)/(B13-1))) | G22: ='5b. Cooling-Value Sensitivity'!E13 -> 1.6113228 | H22: Include the area-per-tonne term (5a B11 ~ 1/(r-1)); cooling per tonne scales as ln(r)/(r-1), not ln(r).
A23: 5b. Cooling-Value Sensitivity | B23: G13 | C23: F24 | D23: ='5a. Cooling Model - Local'!$B$34*(LN('5a. Cooling Model - Local'!$B$18)/LN(D13)) | E23: 0.65270254 | F23: ='5a. Cooling Model - Local'!$B$34*((LN('5a. Cooling Model - Local'!$B$18)/('5a. Cooling Model - Local'!$B$18-1))/(LN(D13)/(D13-1))) | G23: ='5b. Cooling-Value Sensitivity'!G13 -> 2.0084712 | H23: Same as E13 for the upper bound.
A24: 5b. Cooling-Value Sensitivity | B24: I13 | C24: F24 | D24: (empty) | F24: Zhao et al. 2026 GBR range 1.14-1.73x (doi:10.5194/egusphere-2026-1251). Formula includes the area-per-tonne term (5a B11 ~ 1/(r-1)), so cost scales with (r-1)/ln(r). Was 2 and 4 (both above the 1.3 base) with ln(r) only, which showed losses as gains. Changed 2026-10. | H24: Note.
A25: 5c. Benefit - Local - Reef | B25: B13 | C25: F03 | D25: ='3a. Outputs - Dedicated Vessel'!$B$22*(B7/365) | E25: 163.72131 | F25: ='2. Cost Inputs'!$B$15*(B7/365)*'5c-alt. Benefit - Reef (Zhao)'!$B$27 | G25: ='5c. Benefit - Local - Reef'!B13 -> 425.77774 | H25: Per-vessel event output from equipment-basis production x event fraction x 95% in-event spray time. 3a B22 already carries the 33% year-round spray share, so the season was counted twice.
A26: 5c. Benefit - Local - Reef | B26: D13 | C26: F03 | D26: Annual per-vessel-unit production (3a, 33% utilization) x event fraction. Vessel-unit = tab-2 layout (~5,780 nozzles). | F26: Equipment-basis annual production (tab 2 B15, includes 90% availability) x event fraction x 95% spray time within the event (same as 5c-alt B27). Changed 2026-10: was 3a B22 x event fraction, but 3a B22 already carries the dedicated vessel's 33% year-round spray share, so the season was counted twice (6.3 vessels instead of ~2.4). | H26: Note.
A27: 5c. Benefit - Local - Reef | B27: D26 | C27: F26 | D27: Average of the two events. | F27: Average of the two events. Review 2026-10, not changed: 0.57 is relief on the T14 stress metric. On degree heating weeks, which predict mortality, the same 14 T14 reefs give ~0.45, and coral loss is a threshold function of DHW (Hughes et al. 2018, Nature 556:492, doi:10.1038/s41586-018-0041-2), so the linear scaling of relief into dollars in B10 is not supported. | H27: Caveat on the relief-to-dollars mapping. | I27: Harrison et al. 2019 RRAP T14 report (gbrrestoration.org); Hughes et al. 2018 doi:10.1038/s41586-018-0041-2
A28: 5c. Benefit - Local - Reef | B28: D32 | C28: F25 | D28: Assumption (~20%). Until 10/07 typed inside B28. | F28: Assumption (~20%). Until 10/07 typed inside B28. Review 2026-10, not changed: no study maps coral-cover loss to asset value. The 2024 event cut regional hard-coral cover 14-30% (AIMS 2025). Severe events have run ~0.6/yr since 2016 (6 in 10 summers), and 20% of the stock per event at that rate would exhaust it in ~8 years, so 20% per event likely overstates value at risk. Deloitte valued the reef at A$56B in 2017. | H28: Caveat on value at risk. | I28: AIMS Annual Summary Report of Coral Reef Condition 2024/25; Deloitte Access Economics 2017, 2025
A29: 5d. Benefit - Local - City | B29: A8 | C29: F01 | D29: Peak cooling delivered | F29: Cooling under brightened cloud (24-h mean, from 5a) | H29: Label.
A30: 5d. Benefit - Local - City | B30: B8 | C30: F01 | D30: 0.8 | E30: 0.8 | F30: ='5a. Cooling Model - Local'!B19*'5a. Cooling Model - Local'!B25 | G30: ='5d. Benefit - Local - City'!B8 -> 0.17945716 | H30: Derive cooling from the 5a chain (24-h mean forcing x temperature sensitivity) instead of a typed 0.8 degC with no source. | I30: Harrison et al. 2019 RRAP T14 report (gbrrestoration.org)
A31: 5d. Benefit - Local - City | B31: D8 | C31: F01 | D31: Temperature shaved off the hottest part of extreme days. | F31: 5a local forcing (24-h mean) x 5a temperature sensitivity (Harrison 2019 T14, 0.0225 degC per W/m2). Changed 2026-10: was a typed 0.8 degC "peak" with no source; the 5a chain gives ~0.18 degC. | H31: Note.
A32: 5d. Benefit - Local - City | B32: G8 | C32: F01 | D32: Assumption (peak cooling shaved on hottest days). | F32: Tab 5a chain (Harrison et al. 2019 T14 sensitivity). | H32: Source.
A33: 5d. Benefit - Local - City | B33: G9 | C33: F28/F30 | D33: Literature-scale value: ~13.7 heatwave days/yr global average in 2010s (). | F33: Assumption (~14 days). Review 2026-10: the "13.7 heatwave days/yr" citation had no source. The P95 definition in Kephart et al. 2022 implies ~18 days/yr. | H33: Unsourced citation flagged. | I33: Kephart et al. 2022 Nat. Med. doi:10.1038/s41591-022-01872-6
A34: 5d. Benefit - Local - City | B34: B12 | C34: F03 | D34: ='3a. Outputs - Dedicated Vessel'!$B$22*(B9/365) | E34: 15.17946 | F34: ='2. Cost Inputs'!$B$15*(B9/365)*'5c-alt. Benefit - Reef (Zhao)'!$B$27 | G34: ='5d. Benefit - Local - City'!B12 -> 39.476082 | H34: Same season double count as 5c B13.
A35: 5d. Benefit - Local - City | B35: D12 | C35: F03 | D35: Annual per-vessel production (tab 2, at 33% utilization) x season fraction of year. | F35: Equipment-basis annual production (tab 2 B15) x season fraction x 95% in-event spray time (5c-alt B27). Changed 2026-10: was 3a B22 (already x 33% year-round spray share) x season fraction. | H35: Note.
A36: 5d. Benefit - Local - City | B36: B13 | C36: F01 | D36: =B11/B12 | E36: 0.10561343 | F36: =MAX(1,ROUNDUP(B11/B12,0)) | G36: ='5d. Benefit - Local - City'!B13 -> 1 | H36: Charter whole vessels, at least one. Was 0.106 of a vessel.
A37: 5d. Benefit - Local - City | B37: D13 | C37: F01 | D37: Season tonnage / per-vessel season output. | F37: Whole vessels, at least one, chartered for the heat days. Changed 2026-10: was a fraction (0.106 of a vessel for 14 days). Heat days are not known in advance, so a standby charter for the whole hot season would cost several times more. | H37: Note.
A38: 5d. Benefit - Local - City | B38: A25 | C38: F01 | D38: Daily-mean realized cooling (RR basis) | F38: Daily-mean realized cooling (RR basis) | H38: Label unchanged in meaning.
A39: 5d. Benefit - Local - City | B39: B25 | C39: F01 | D39: =B8*B30 | E39: 0.352 | F39: =B8*'5a. Cooling Model - Local'!B21 | G39: ='5d. Benefit - Local - City'!B25 -> 0.035891431 | H39: 24-h mean cooling x cloud availability (5a B21). Cloud availability was never applied on this tab.
A40: 5d. Benefit - Local - City | B40: D25 | C40: F01 | D40: RR 1.057 is against daily-mean temperature, not peak. 0.44 converts peak shaving to the daily-mean dose the epidemiology sees. | F40: 24-h mean cooling under brightened cloud x cloud availability (5a B21). The 5a forcing is a 24-h mean, so no peak-to-mean conversion (B30) is needed. Changed 2026-10: was 0.8 x 0.44 with no cloud availability. | H40: Note.
A41: 5d. Benefit - Local - City | B41: A26 | C41: F28 | D41: Deaths averted per season | F41: Deaths averted per season | H41: Label.
A42: 5d. Benefit - Local - City | B42: B26 | C42: F28 | D42: =B23*(1-1/(1+B24)^B25) | E42: 3.864774 | F42: =B40*(1-1/(1+B24)^B25) | G42: ='5d. Benefit - Local - City'!B26 -> 1.5487356 | H42: RR per degC applies to all deaths on the heat days, not only the excess deaths. | I42: Kephart et al. 2022 Nat. Med. doi:10.1038/s41591-022-01872-6
A43: 5d. Benefit - Local - City | B43: D26 | C43: F01/F28 | D43: Baseline deaths x reduction at realized daily-mean cooling. Availability is already inside 5a's realization factor, so no separate availability halving. | F43: All deaths on the heat days (B40) x mortality reduction at the realized daily-mean cooling. The RR is per degC on all-cause deaths, so it multiplies every death that day, not only the excess. Changed 2026-10: was applied to the 200 excess deaths only (conservative), and the old note said cloud availability was already inside 5a, which was not true for this tab. | H43: False note fixed.
A44: 5d. Benefit - Local - City | B44: G23 | C44: F28 | D44: Assumption (baseline excess deaths per extreme season). | F44: Assumption (200 excess deaths). Review 2026-10: published heat burdens for a 2M city give ~63-205, central ~100-137: Kephart et al. 2022 heat excess-death fraction 0.67% -> ~101; Zhao et al. 2021 (Lancet Planet. Health, doi:10.1016/S2542-5196(21)00081-4) 0.91% -> ~137; Gasparrini et al. 2015 (Lancet) -> ~63. 200 is at the top of the range. | H44: Baseline flagged as high. | I44: Kephart et al. 2022 Nat. Med. doi:10.1038/s41591-022-01872-6; Zhao et al. 2021; Gasparrini et al. 2015
A45: 5d. Benefit - Local - City | B45: G24 | C45: F28/F30 | D45: 326-city study (as noted); | F45: Kephart et al. 2022, Nat. Med. 28:1700-1705 (doi:10.1038/s41591-022-01872-6): RR 1.057 (95% CI 1.046-1.067) per 1 degC of daily mean above the city P95, 326 Latin American cities. | H45: Named the 326-city study. | I45: Kephart et al. 2022 Nat. Med. doi:10.1038/s41591-022-01872-6
A46: 5d. Benefit - Local - City | B46: G27 | C46: F28 | D46: Assumption (US-federal-range VSL). | F46: Assumption (US-federal-range VSL). Review 2026-10: EPA central $7.4M (2006$, updated to analysis year); DOT $13.2M (2023$). Fits US cities only; income-adjusted values for lower-income cities are far lower (Viscusi & Masterman 2017, doi:10.1017/bca.2017.12). | H46: VSL scope note. | I46: EPA Mortality Risk Valuation; DOT VSL guidance 2024; Viscusi & Masterman 2017
A47: 5d. Benefit - Local - City | B47: D30 | C47: F01 | D47: Share of a peak-hour cooling that shows up in the daily mean the mortality study uses. Assumption. Until 10/07 typed inside B25. | F47: Not used since 2026-10: the 5a forcing is now a 24-h mean, so the 5a chain already gives a daily-mean dose. Kept for reference. Until 10/07 typed inside B25. | H47: Cell no longer referenced.
A48: 5d. Benefit - Local - City | B48: G35 | C48: F28/F30 | D48: Harding, Keith, Vecchi & Yang 2024 (PNAS), | F48: Harding, Vecchi, Yang & Keith 2024, PNAS 121(52):e2401801121 (doi:10.1073/pnas.2401801121). Review 2026-10: 13x is mortality benefit vs risk for stratospheric sulfate (61% probability), not benefit vs cost, and not MCB. | H48: Citation and meaning fixed. | I48: Harding et al. 2024 doi:10.1073/pnas.2401801121
A49: 5d. Benefit - Local - City | B49: A37 | C49: F01/F28 | D49: =CONCATENATE("This profile (",TEXT(B29,"0.0"),"x on the daily-mean realized dose) sits at the top of the demonstrated urban-cooling range and near the global geoengineering mortality anchor. The dose basis is daily-mean, not instantaneous peak - the epidemiology does not support a peak-based dose.") | E49: This profile (515.8x on the daily-mean realized dose) sits at the top of the demonstrated urban-cooling range and near the global geoengineering mortality anchor. The dose basis is daily-mean, not instantaneous peak - the epidemiology does not support a peak-based dose. | F49: ="This profile ("&TEXT(B29,"0.0")&"x on the daily-mean realized dose, whole-vessel charter) compares with 1.5-15.2x for urban passive cooling (Estrada et al. 2017). The 13x geoengineering anchor is benefit vs risk, not benefit vs cost, so it is not a like-for-like comparison." | G49: ='5d. Benefit - Local - City'!A37 -> This profile (26.4x on the daily-mean realized dose, whole-vessel charter) compares with 1.5-15.2x for urban passive cooling (Estrada et al. 2017). The 13x geoengineering anchor is benefit vs risk, not benefit vs cost, so it is not a like-for-like comparison. | H49: Summary sentence no longer claims a fit it no longer has.
A50: 5d. Benefit - Local - City | B50: A39 | C50: F28 | D50: (empty) | F50: Crude death rate (added 2026-10) | H50: New input for the RR fix.
A51: 5d. Benefit - Local - City | B51: B39 | C51: F28 | D51: (empty) | F51: 7.55 | G51: ='5d. Benefit - Local - City'!B39 -> 7.55 | H51: World 2024 crude death rate. | I51: World Bank WDI SP.DYN.CDRT.IN
A52: 5d. Benefit - Local - City | B52: C39 | C52: F28 | D52: (empty) | F52: per 1,000 per yr | H52: Unit.
A53: 5d. Benefit - Local - City | B53: D39 | C53: F28 | D53: (empty) | F53: Converts population to all-cause deaths on heat days for the RR in B26. City age structure can move this +/-50%. | H53: Note.
A54: 5d. Benefit - Local - City | B54: G39 | C54: F28 | D54: (empty) | F54: World Bank WDI, Death rate, crude (SP.DYN.CDRT.IN), World 2024: 7.55 per 1,000. | H54: Source.
A55: 5d. Benefit - Local - City | B55: A40 | C55: F28 | D55: (empty) | F55: All-cause deaths on heat days | H55: New line.
A56: 5d. Benefit - Local - City | B56: B40 | C56: F28 | D56: (empty) | F56: =B22*B39/1000*B9/365+B23 | G56: ='5d. Benefit - Local - City'!B40 -> 779.17808 | H56: Population x crude death rate x heat days/365, plus the excess deaths (B23).
A57: 5d. Benefit - Local - City | B57: C40 | C57: F28 | D57: (empty) | F57: deaths | H57: Unit.
A58: 5d. Benefit - Local - City | B58: D40 | C58: F28 | D58: (empty) | F58: Expected deaths on the heat days at the baseline rate, plus the heat excess in B23. B26 applies the RR to this. | H58: Note.
A59: 6a. Cooling Model - Global | B59: B16 | C59: F05 | D59: 90 | E59: 90 | F59: 94.2 | G59: ='6a. Cooling Model - Global'!B16 -> 94.2 | H59: Volume-mean diameter (2 x volume radius) is the right basis for particles per tonne. Was 90. | I59: Hirasawa et al. 2026 EGUsphere preprint doi:10.5194/egusphere-2026-5460 Table 1
A60: 6a. Cooling Model - Global | B60: B17 | C60: F05 | D60: 90 | E60: 90 | F60: 94.2 | G60: ='6a. Cooling Model - Global'!B17 -> 94.2 | H60: Volume-mean diameter (2 x volume radius) is the right basis for particles per tonne. Was 90. | I60: Hirasawa et al. 2026 EGUsphere preprint doi:10.5194/egusphere-2026-5460 Table 1
A61: 6a. Cooling Model - Global | B61: B18 | C61: F05 | D61: 90 | E61: 90 | F61: 94.2 | G61: ='6a. Cooling Model - Global'!B18 -> 94.2 | H61: Volume-mean diameter (2 x volume radius) is the right basis for particles per tonne. Was 90. | I61: Hirasawa et al. 2026 EGUsphere preprint doi:10.5194/egusphere-2026-5460 Table 1
A62: 6a. Cooling Model - Global | B62: B19 | C62: F05 | D62: 172 | E62: 172 | F62: 171.8 | G62: ='6a. Cooling Model - Global'!B19 -> 171.8 | H62: Volume-mean diameter. Was 172 (rounding). | I62: Hirasawa et al. 2026 EGUsphere preprint doi:10.5194/egusphere-2026-5460 Table 1
A63: 6a. Cooling Model - Global | B63: G16 | C63: F05 | D63: Model CCN fraction (Hirasawa 2026 preprint, Table 1) | F63: CCN fraction at S=0.1%: Hirasawa 2026 preprint, Table 1. Size: volume-mean diameter 94.2 nm (2 x iSSA volume radius, same Table 1), the right basis for particles per tonne. Was 90 nm, closer to a count median. Changed 2026-10. | H63: Note.
A64: 6a. Cooling Model - Global | B64: G17 | C64: F05 | D64: Model CCN fraction (Hirasawa 2026 preprint, Table 1) | F64: CCN fraction at S=0.1%: Hirasawa 2026 preprint, Table 1. Size: volume-mean diameter 94.2 nm (2 x iSSA volume radius, same Table 1), the right basis for particles per tonne. Was 90 nm, closer to a count median. Changed 2026-10. | H64: Note.
A65: 6a. Cooling Model - Global | B65: G18 | C65: F05 | D65: Model CCN fraction (Hirasawa 2026 preprint, Table 1) | F65: CCN fraction at S=0.1%: Hirasawa 2026 preprint, Table 1. Size: volume-mean diameter 94.2 nm (2 x iSSA volume radius, same Table 1), the right basis for particles per tonne. Was 90 nm, closer to a count median. Changed 2026-10. | H65: Note.
A66: 6a. Cooling Model - Global | B66: G19 | C66: F05 | D66: Model CCN fraction (Hirasawa 2026 preprint, Table 1) | F66: CCN fraction at S=0.1%: Hirasawa 2026 preprint, Table 1. Size: volume-mean diameter 171.8 nm (2 x iSSA volume radius). Was 172. Changed 2026-10. | H66: Note.
A67: 6a. Cooling Model - Global | B67: D20 | C67: F04 | D67: ='1. Technology Description'!B9 | E67: 0.71 | F67: 0.22 | G67: ='6a. Cooling Model - Global'!D20 -> 0.22 | H67: Like-for-like CCN fraction: share of our particles that activate at S=0.1% (dry diameter > ~108.5 nm), the same definition as the model fractions in D16:D19. Estimate from a fitted size distribution. Was 0.71 = share in the 30-1000 nm window, a looser size window. | I67: Hirasawa et al. 2026 EGUsphere preprint doi:10.5194/egusphere-2026-5460 Table 1
A68: 6a. Cooling Model - Global | B68: E20 | C68: F04 | D68: (empty) | F68: CCN fraction (activated at S=0.1%, estimate) | H68: Label.
A69: 6a. Cooling Model - Global | B69: G20 | C69: F04 | D69: (empty) | F69: Estimate, review 2026-10. Same definition as D16:D19: share of particles that activate at 0.1% supersaturation. Hirasawa 2026 preprint Table 1 back-solves to a dry cutoff of ~108.5 nm across CESM2/E3SMv2/UKESM1. Fitting a lognormal to our nozzle: (a) 71% in 30-1000 nm and 150 nm volume-mean gives sigma_g 2.38, CMD 48.5 nm, 18% above 108.5 nm; (b) 40 nm count mode (CS-06 p.24) and 150 nm volume-mean gives sigma_g 2.07, CMD 67.9 nm, 26%. 0.22 is the midpoint. Was 0.71 (tab 1 B9), the share in the 30-1000 nm production window, which is a looser size cut than the models use. | H69: Derivation of the new value.
A70: 6a. Cooling Model - Global | B70: A3 | C70: F04/F05/F14 | D70: Basis conversion: CESM2/E3SMv2 emit 90 nm, UKESM1 172 nm (Hirasawa 2026, J. Climate). Restate tonnages at our 150 nm by (d_ours/d_model)^3 x (model CCN fraction / our CCN fraction), so we match cloud droplets, not raw particle counts; CCN fractions from Hirasawa 2026 preprint, Table 1). Then gross up for plume survival; ESMs emit diffuse fluxes, ours is a point source. Assumes (1) forcing is mostly cloud forcing, roughly true for CESM2, and (2) our 150 nm and the models' 90/172 nm particles stay airborne with an equally long lifetime. | F70: Basis conversion: CESM2/E3SMv2 emit 94.2 nm, UKESM1 171.8 nm volume-mean diameter (Hirasawa 2026 preprint, Table 1; the J. Climate text rounds these to 90/172 nm). Restate tonnages at our 150 nm by (d_ours/d_model)^3 x (model CCN fraction / our CCN fraction), both CCN fractions taken as the share activating at 0.1% supersaturation, so we match cloud droplets, not raw particle counts. Then gross up for near-source plume loss; ESMs emit diffuse fluxes, ours is a point source. Assumes (1) forcing is mostly cloud forcing, roughly true for CESM2 (direct scattering is ~40% of forcing in E3SMv2 and ~59% in UKESM1 at -2 W/m2, Hirasawa preprint Table 2), and (2) our 150 nm and the models' 94/172 nm particles stay airborne equally long. | H70: Basis text updated to match the new sizes and CCN definition.
A71: 6a. Cooling Model - Global | B71: D25 | C71: F04/F05 | D71: x (d_model/d_ours)^3 x (our CCN fraction / model CCN fraction): a tonne of 90 nm holds (150/90)^3 = 4.6x more particles than 150 nm, but only 15.7% of CESM2's become droplets vs our 71%, so per tonne the two make about the same number of droplets | F71: x (d_model/d_ours)^3 x (our CCN fraction / model CCN fraction): a tonne of 94.2 nm holds (150/94.2)^3 = 4.0x more particles than 150 nm, and 15.7% of CESM2's activate at 0.1% S vs ~22% of ours. | H71: Note follows the new inputs.
A72: 6a. Cooling Model - Global | B72: B27 | C72: F23 | D72: 0.012 | E72: 0.012 | F72: 0.019 | G72: ='6a. Cooling Model - Global'!B27 -> 0.019 | H72: Rasch 2024 Tables 5 and A1 imply 0.016-0.023 W/m2 per Tg/yr for UKESM1; 0.019 is the midpoint. Was 0.012. Gut check only. | I72: Rasch et al. 2024 GMD doi:10.5194/gmd-17-7963-2024
A73: 6a. Cooling Model - Global | B73: D27 | C73: F23 | D73: (empty) | F73: Rasch et al. 2024 GMD (doi:10.5194/gmd-17-7963-2024): Table A1 -2.42 W/m2 at 50 Tg/yr/region -> 0.016; Table 5 -1.7 W/m2 at 25 Tg/yr/region -> 0.023; Hirasawa preprint 2/95.7 = 0.021. 0.019 is the midpoint of the Rasch range. Was 0.012 (1.8/150). Gut check only, does not feed the BCRs. Changed 2026-10. | H73: Note.
A74: 6a. Cooling Model - Global | B74: E10 | C74: F18 | D74: -0.236 | E74: -0.236 | F74: -0.231 | G74: ='6a. Cooling Model - Global'!E10 -> -0.231 | H74: Paper value 0.231 K per Tg/yr. Was typed 0.236 (= D10/C10 rounded). | I74: Hirasawa et al. 2026 J. Climate doi:10.1175/JCLI-D-25-0337.1
A75: 6a. Cooling Model - Global | B75: G10 | C75: F18 | D75: Strongest efficiency in the study. | F75: Strongest efficiency in the study. Hirasawa et al. 2026 J. Climate reports 0.231 K per Tg/yr; D10/C10 rounds to 0.236. Changed 2026-10 from a typed 0.236. | H75: Note.
A76: 6a. Cooling Model - Global | B76: B34 | C76: F18 | D76: 0.236 | E76: 0.236 | F76: =-E10 | G76: ='6a. Cooling Model - Global'!B34 -> 0.231 | H76: Link to section A instead of a typed 0.236.
A77: 6a. Cooling Model - Global | B77: B36 | C77: F18 | D77: 0.0372 | E77: 0.0372 | F77: =-E11 | G77: ='6a. Cooling Model - Global'!B36 -> 0.0372 | H77: Link instead of typed value (same number).
A78: 6a. Cooling Model - Global | B78: B37 | C78: F18 | D78: 0.00754 | E78: 0.00754 | F78: =-E12 | G78: ='6a. Cooling Model - Global'!B37 -> 0.00754 | H78: Link instead of typed value (same number).
A79: 6a. Cooling Model - Global | B79: D13 | C79: F22/F18 | D79: =D10*(12.9/7.21) | E79: -5.2745076 | F79: =E10*C13*(3.34/2.62) | G79: ='6a. Cooling Model - Global'!D13 -> -3.6810115 | H79: Equal-tonnage forcing ratio (1.27x) instead of the equal-forcing mass ratio (1.79x), applied to the paper CESM2 efficiency (E10). | I79: Hirasawa et al. 2026 EGUsphere preprint doi:10.5194/egusphere-2026-5460 Table 2
A80: 6a. Cooling Model - Global | B80: G13 | C80: F22 | D80: Scaled from CESM2 by salt needed for -2 W/m2: CESM2 12.9 vs CESM2-Ghosh 7.21 Tg/yr (Hirasawa 2026 preprint, Table 2). Same model and particles, newer activation scheme (Ghosh et al. 2025). Cooling is scaled, not a simulated run. | F80: Scaled from CESM2 (E10 x C13) by the equal-tonnage forcing ratio at 30 Tg/yr: ERFtot -3.34 (CESM2-Ghosh) vs -2.62 W/m2 (CESM2), 1.27x (Hirasawa 2026 preprint, Table 2). Was 12.9/7.21 = 1.79x, the equal-forcing mass ratio, which overstates the gain at fixed tonnage because ERFaci is log-shaped. Table 2 is a subtropical experiment, applied here to midlatitude seeding. Same model and particles, newer activation scheme (Ghosh et al. 2025, GMD 18:4899). Cooling is scaled, not a simulated run. Changed 2026-10. | H80: Note.
A81: 6a. Cooling Model - Global | B81: D32 | C81: F17 | D81: Catch-all for every loss, including particles too small to become droplets. Assumption: same basis as the tab 5a survival factor (Frontiers plume review 2025; open research gap). | F81: Near-source plume loss only: in-plume coagulation and deposition before cloud base, which ESMs do not simulate (same basis as tab 5a B5; Stuart et al. 2013, doi:10.5194/acp-13-10385-2013). Activation (particles too small to become droplets) is handled by the CCN fraction in D20, so it is not counted here. Range 0.1-0.5, an assumption. | H81: Note no longer overlaps the CCN correction.
A82: 6a. Cooling Model - Global | B82: G44 | C82: F27 | D82: Burke, Hsiang & Miguel 2015 (Nature 527:235): ~23% GDP/capita at ~3.7C (~6%/degC). 3.3%/degC is conservative within the statistical class (Kahn 2021 ~2.5%; Bilal & Kanzig 2024 12% peak). Replaces Kotz 2024, retracted Dec 2025. | F82: Central 3.3%/degC has no single source; it sits inside Kalkuhl & Wenz 2020 (JEEM 103:102360, doi:10.1016/j.jeem.2020.102360), 2-4%/degC for a permanent level effect. Burke, Hsiang & Miguel 2015 (Nature 527:235) implies ~6%/degC; Kahn et al. 2021 ~2.5%. Replaces Kotz 2024, retracted Dec 2025. All anchors are long-run losses from lasting warming, not annual flows per degree-year. Updated 2026-10. | H82: Note. | I82: Kalkuhl & Wenz 2020 JEEM doi:10.1016/j.jeem.2020.102360
A83: 6a. Cooling Model - Global | B83: A45 | C83: F27 | D83: Damage: high (Bilal-Kanzig 2024) | F83: Damage: high (Bilal-Kanzig 2026) | H83: Label.
A84: 6a. Cooling Model - Global | B84: B45 | C84: F27 | D84: 12 | E84: 12 | F84: 14 | G84: ='6a. Cooling Model - Global'!B45 -> 14 | H84: Current Bilal & Kanzig headline: 14% peak GDP loss after a 1 degC shock. Was 12% (2024 working paper; no longer in the current version). | I84: Bilal & Kanzig, QJE 2026 / NBER w32450 doi:10.3386/w32450
A85: 6a. Cooling Model - Global | B85: G45 | C85: F27 | D85: Bilal & Kanzig 2024 (w32450): 12% GDP per degC | F85: Bilal & Kanzig, Quarterly Journal of Economics (2026); numbers from NBER w32450 rev. Jan 2026 (doi:10.3386/w32450): peak GDP loss 14% (95% CI 6-22%) six years after a 1 degC global temperature shock; permanent 1 degC warming 20-34% long run; a one-off transitory 1 degC ~4%. The transitory 4% is the closest analogue to one degree-year of cooling. Was 12% (2024 version). Updated 2026-10. | H85: Note. | I85: Bilal & Kanzig, QJE 2026 / NBER w32450 doi:10.3386/w32450
A86: 6a. Cooling Model - Global | B86: A46 | C86: F15 | D86: (empty) | F86: Response lag factor (added 2026-10) | H86: New input, default 1.0 = no change.
A87: 6a. Cooling Model - Global | B87: B46 | C87: F15 | D87: (empty) | F87: 1 | G87: ='6a. Cooling Model - Global'!B46 -> 1 | H87: Share of steady-state cooling value realized once ocean lag is counted. Default 1.0 keeps the original basis. | I87: Parker & Irvine 2018 Earth's Future doi:10.1002/2017EF000735
A88: 6a. Cooling Model - Global | B88: C46 | C88: F15 | D88: (empty) | F88: fraction | H88: Unit.
A89: 6a. Cooling Model - Global | B89: G46 | C89: F15 | D89: (empty) | F89: 1.0 = no lag (the original basis). With a ~4-yr e-folding ocean response over a 50-yr program the realized share is 0.86 at a 3% discount rate and 0.72 at 10% (0.75-0.93 for 2-8 yr e-folding; computed in review). Termination: aerosol lifetime is days, so stopping returns most of the masked warming within ~5-10 yr (Parker & Irvine 2018, Earth's Future, doi:10.1002/2017EF000735). A spare fleet for redundancy is not costed. Multiplies the value of cooling in 6b/6c. | H89: Note.
A90: 6a. Cooling Model - Global | B90: A47 | C90: F11 | D90: (empty) | F90: SAI cost per degree-year (comparison) | H90: New comparison input.
A91: 6a. Cooling Model - Global | B91: B47 | C91: F11 | D91: (empty) | F91: 18 | G91: ='6a. Cooling Model - Global'!B47 -> 18 | H91: Stratospheric aerosol injection ~$18B/yr per degC avoided. | I91: Smith 2020 ERL doi:10.1088/1748-9326/aba7e7
A92: 6a. Cooling Model - Global | B92: C47 | C92: F11 | D92: (empty) | F92: $B per K per yr | H92: Unit.
A93: 6a. Cooling Model - Global | B93: G47 | C93: F11 | D93: (empty) | F93: Smith 2020, Environ. Res. Lett. 15:114004 (doi:10.1088/1748-9326/aba7e7): ~$18B/yr per degC of warming avoided (2020 USD). Used only for the comparison column in 6b/6c. | H93: Source.
A94: 6a. Cooling Model - Global | B94: A48 | C94: F10 | D94: (empty) | F94: World merchant fleet (comparison) | H94: New comparison input.
A95: 6a. Cooling Model - Global | B95: B48 | C95: F10 | D95: (empty) | F95: 109000 | G95: ='6a. Cooling Model - Global'!B48 -> 109000 | H95: World fleet ~109,000 ships. | I95: UNCTAD Review of Maritime Transport 2024
A96: 6a. Cooling Model - Global | B96: C48 | C96: F10 | D96: (empty) | F96: vessels | H96: Unit.
A97: 6a. Cooling Model - Global | B97: G48 | C97: F10 | D97: (empty) | F97: UNCTAD Review of Maritime Transport 2024: ~109,000 ships of 100 GT and above. Used only for the feasibility block in 6b. | H97: Source.
A98: 6a. Cooling Model - Global | B98: A49 | C98: F10 | D98: (empty) | F98: World shipping CO2 (comparison) | H98: New comparison input.
A99: 6a. Cooling Model - Global | B99: B49 | C99: F10 | D99: (empty) | F99: 1056 | G99: ='6a. Cooling Model - Global'!B49 -> 1056 | H99: All shipping, 2018. | I99: IMO Fourth GHG Study 2020
A100: 6a. Cooling Model - Global | B100: C49 | C100: F10 | D100: (empty) | F100: Mt CO2/yr | H100: Unit.
A101: 6a. Cooling Model - Global | B101: G49 | C101: F10 | D101: (empty) | F101: IMO Fourth GHG Study 2020: total shipping emissions 1,056 Mt CO2 in 2018. | H101: Source.
...
